Workbook
Name Master2026StatusList: 'Data Validation'!$A$1:$A$19

Sheet Summary
A2: Geo | B2: India | G2: Geo | H2: USA
A3: Status | B3: (Multiple Items) | G3: Status | H3: Offered
A4: Position Open Date | B4: (All) | G4: Position Open Date | H4: (All)
A6: No. of Position | G6: No. of Positions
A7: 2
A11: Geo | B11: India | G11: Geo | H11: USA
A12: Status | B12: Offered | G12: Status | H12: Offered
A13: Position Open Date | B13: (All) | G13: Position Open Date | H13: (All)
A15: No. of Offered | G15: No. of Offered
A16: 2
A20: Geo | B20: India | G20: Geo | H20: USA
A21: Status | B21: Joined | G21: Status | H21: Joined
A22: Position Open Date | B22: (All) | G22: Position Open Date | H22: (All)
A24: Joining YTD | G24: Joining YTD
A25: 63 | G25: 38
A30: Geo | B30: India | G30: Geo | H30: USA
A31: Status | B31: JD Pending | G31: Status | H31: JD Pending
A32: Position Open Date | B32: (All) | G32: Position Open Date | H32: (All)
A34: JD Pending | G34: JD Pending
A35: 1 | G35: 1
A39: Geo | B39: India | G39: Geo | H39: USA
A40: Status | B40: Position Freezed | G40: Status | H40: Position Freezed
A41: Position Open Date | B41: (All) | G41: Position Open Date | H41: (All)
A43: Suspended | G43: Suspended
A44: 20 | G44: 6
A48: Geo | B48: USA
A49: Status | B49: Joined
A51: Count of Department | D51: Quarter Joining
A52: Squads | B52: Department | C52: Full-Time/Consultant | D52: Q1 | E52: Q2 | F52: Q3 | G52: Grand Total
A53: Account | B53: Account Galaxy | C53: Full-time | F53: 1 | G53: 1
A54: Account | B54: Engineering | C54: Full-time | E54: 1 | G54: 1
A55: Account | B55: PS | C55: Full-time | F55: 1 | G55: 1
A56: DevOps | B56: DevOps | C56: Consultant | E56: 1 | G56: 1
A57: DevOps | B57: DevOps | C57: Full-time | D57: 1 | F57: 1 | G57: 2
A58: DevOps | B58: Technology | C58: Full-time | F58: 1 | G58: 1
A59: Digital | B59: Engineering | C59: Full-time | E59: 1 | G59: 1
A60: Finance | B60: Finance | C60: Full-time | F60: 1 | G60: 1
A61: GTM | B61: Support | D61: 1 | G61: 1
A62: HR | B62: HR | C62: Full-time | D62: 1 | E62: 1 | G62: 2
A63: Infosec | B63: Infosec | C63: Full-time | D63: 1 | E63: 1 | G63: 2
A64: Payments | B64: Engineering | C64: Full-time | E64: 1 | F64: 1 | G64: 2
A65: Payments | B65: Payments | C65: Full-time | E65: 1 | G65: 1
A66: Payments | B66: Product | C66: Full-time | D66: 1 | G66: 1
A67: PS | B67: QA | C67: Full-time | E67: 1 | G67: 1
A68: PS | B68: Engineering | C68: Full-time | F68: 1 | G68: 1
A69: PS | B69: Product | C69: Consultant | D69: 3 | G69: 3
A70: PS | B70: Program | C70: Full-time | F70: 1 | G70: 1
A71: PS | B71: PS | C71: Full-time | F71: 4 | G71: 4
A72: Sales | B72: Sales | C72: Full-time | D72: 2 | E72: 1 | G72: 3
A73: Support | B73: Production Support | C73: Full-time | D73: 1 | E73: 1 | G73: 2
A74: Support | B74: Support | E74: 1 | F74: 2 | G74: 3
A75: Trade | B75: Engineering | C75: Full-time | F75: 1 | G75: 1
A76: Grand Total | D76: 11 | E76: 11 | F76: 15 | G76: 37

Sheet Open Reqs- INDIA
A1: Geo | B1: India
A2: Position Open Date | B2: (All)
A5: Squads | B5: Department | C5: Hiring Location | D5: Full-Time/ Consultant | E5: Positions | F5: New/ Replacement | G5: Replaced Employee Name | H5: Status | I5: Aging (Days) | J5: Comments
A6: Finance | B6: Finance | C6: Chennai | D6: Full-time | E6: NetSuite Implementation Expert | F6: New | G6: (blank) | H6: JD Pending | I6: 7 | J6: JD pending with Dharani

Sheet Open Reqs - USA
A1: Geo | B1: USA
A2: Position Open Date | B2: (All)
A5: Squads | B5: Department | C5: Hiring Location | D5: Full-Time/ Consultant | E5: Positions | F5: New/ Replacement | G5: Replaced Employee Name | H5: Aging (Days) | I5: Comments | J5: Status

Sheet Offers -INDIA
A1: Geo | B1: India
A2: Position Open Date | B2: (All)
A5: Squads | B5: Hiring Location | C5: Positions | D5: Full-Time/ Consultant | E5: Date Offered | F5: Joining Date | G5: Status | H5: Offered Candidates | I5: RAG Status | J5: Buddy - Onboarding | K5: Back-up Plans
A6: Support | B6: Remote | C6: Production Support Engineer ( Payments) | D6: Full-time | E6: 46302 | F6: 46357 | G6: Offered | H6: Mahendra Kolate | I6: Amber | J6: (blank) | K6: Sourcing
A7: Technology | B7: Chennai | C7: Junior IT Admin | D7: Full-time | E7: 46314 | F7: 46329 | G7: Offered | H7: Athiban Eswar | I7: Green | J7: Senthil | K7: Final select

Sheet Offers-USA
A1: Geo | B1: USA
A2: Position Open Date | B2: (All)
A5: Squads | B5: Hiring Location | C5: Positions | D5: Full-Time/ Consultant | E5: Date Offered | F5: Joining Date | G5: Status | H5: Offered Candidates | I5: Buddy - Onboarding | J5: Highest Qualification Degree

Sheet Joining -INDIA
A2: Geo | B2: (Multiple Items)
A3: Position Open Date | B3: (All)
A5: Squads | B5: Department | C5: Hiring Location | D5: Positions | E5: Full-Time/Consultant | F5: Joining Date | G5: Status | H5: Offered Candidates
A6: Account | B6: Engineering | C6: Chennai | D6: Compliance - AI Developer | E6: Full-time | F6: 46104 | G6: Joined | H6: Vaishnavi
A7: Account | B7: Engineering | C7: Chennai | D7: Full-stack Engineer | E7: Full-time | F7: 46162 | G7: Joined | H7: Kalirajan
A8: Account | B8: Product | C8: Chennai | D8: Product Manager - Deposits & VA | E8: Full-time | F8: 46104 | G8: Joined | H8: Arivumani N
A9: Account | B9: Product | C9: Pune | D9: Product Manager - VA | E9: Full-time | F9: 46140 | G9: Joined | H9: Dhawal
A10: Account | B10: QA | C10: Chennai | D10: QA Analyst | E10: Full-time | F10: 46083 | G10: Joined | H10: Keerthika
A11: Account | B11: QA | C11: Chennai | D11: QA Analyst | E11: Full-time | F11: 46093 | G11: Joined | H11: Nikhil C Karanam
A12: Account | B12: QA | C12: Chennai | D12: QA Analyst | E12: Full-time | F12: 46132 | G12: Joined | H12: Arul Anand
A13: DevOps | B13: DevOps | C13: Chennai | D13: DevOps Engineer | E13: Full-time | F13: 46181 | G13: Joined | H13: Deepakraj J
A14: DevOps | B14: DevOps | C14: Chennai | D14: DevOps Engineer | E14: Full-time | F14: 46086 | G14: Joined | H14: Senthil R
A15: DevOps | B15: DevOps | C15: Chennai | D15: Trainee DevOps Engineer | E15: Full-time | F15: 46195 | G15: Joined | H15: Prasanna
A16: DevOps | B16: DevOps | C16: Pune | D16: DevOps Engineer | E16: Full-time | F16: 46188 | G16: Joined | H16: Faheem
A17: Digital | B17: Engineering | C17: Chennai | D17: Backend Developer | E17: Full-time | F17: 46239 | G17: Joined | H17: Thameenansari
... A68: Trade | B68: QA | C68: Chennai | D68: QA Analyst | E68: Full-time | F68: 46160 | G68: Joined | H68: Nirmal

Sheet Joining -USA
A3: Geo | B3: USA
A4: Position Open Date | B4: (All)
A7: Squads | B7: Department | C7: Hiring Location | D7: Positions | E7: Full-Time/Consultant | F7: Joining Date | G7: Status | H7: Offered Candidates
A8: DevOps | B8: DevOps | C8: Charlotte | D8: Director of Infrastructure | E8: Full-time | F8: 46057 | G8: Joined | H8: Manoj
A9: DevOps | B9: DevOps | C9: Charlotte | D9: IT Admin Consultant | E9: Consultant | F9: 46181 | G9: Joined | H9: Tejasri Balusu
A10: DevOps | B10: DevOps | C10: Charlotte | D10: Associate AI Engineer_DecOps | E10: Full-time | F10: 46237 | G10: Joined | H10: Bladen Martin
A11: DevOps | B11: Technology | C11: Charlotte | D11: Data Architect | E11: Full-time | F11: 46226 | G11: Joined | H11: Narayanan Sundaram
A12: Finance | B12: Finance | C12: Charlotte | D12: Chief Finance Officer | E12: Full-time | F12: 46314 | G12: Joined | H12: Jack McCullen
A13: Finance | B13: Finance | C13: Charlotte | D13: Commercial Contracts Manager | E13: Full-time | F13: 46216 | G13: Joined | H13: Cystal Goodwin
A14: Infosec | B14: Infosec | C14: Charlotte | D14: CISO (Change of Role) | E14: Full-time | F14: 46055 | G14: Joined | H14: Supro
A15: Infosec | B15: Infosec | C15: Charlotte | D15: Associate AI Engineer _InfoSec | E15: Full-time | F15: 46169 | G15: Joined | H15: Shubham Bhojwani
A16: Payments | B16: Engineering | C16: Charlotte | D16: Enterprise Architect | E16: Full-time | F16: 46132 | G16: Joined | H16: Lakshminarayan
A17: Payments | B17: Engineering | C17: Charlotte | D17: Lead Software Engineer - ACH | E17: Full-time | F17: 46224 | G17: Joined | H17: Alka Lakhote
A18: Payments | B18: Product | C18: Charlotte | D18: Product Owner (Change of Role) | E18: Full-time | F18: 46042 | G18: Joined | H18: Melissa
A19: Payments | B19: Payments | C19: Charlotte | D19: AI Developer | E19: Full-time | F19: 46160 | G19: Joined | H19: Aditya Khandare
... A45: Digital | B45: Engineering | C45: Charlotte | D45: Associate AI Engineer_Digital Galaxy | E45: Full-time | F45: 46188 | G45: Joined | H45: Shubham Salonki

Sheet On Hold
A4: #VALUE!
A13: Geo | B13: USA
A14: Position Open Date | B14: (All)
A17: Squads | B17: Positions | C17: Full-Time/Consultant | D17: Replaced Employee Name | E17: New/Replacement | F17: Hiring Location | G17: Status
A18: DevOps | B18: SecOps - Enterprise Governance | C18: Full-time | D18: (blank) | E18: New | F18: Charlotte | G18: Suspended
B19: DevOps Engineer | C19: Full-time | D19: Prathamesh | E19: Replacement | F19: Charlotte | G19: Suspended
A20: PS | B20: Project Manager | C20: Full-time | D20: (blank) | E20: New | F20: Charlotte | G20: Suspended
A21: Account | B21: Solution Engineer | C21: Full-time | D21: (blank) | E21: New | F21: Charlotte | G21: Suspended
A22: GTM | B22: Marketing Trainee Associate | C22: Full-time | D22: (blank) | E22: New | F22: Charlotte | G22: Suspended
A23: AI | B23: Associate AI Engineer | C23: Full-time | D23: (blank) | E23: New | F23: Charlotte | G23: Suspended

Sheet Recruitment- Master
A1: Sr No | B1: Geo | C1: Practice | D1: Project | E1: Positions | F1: New/Replacement | G1: Full-Time/Consultant | H1: Hiring Location | I1: Position Open Date | J1: Todays Date | K1: Date Offered | L1: Joining Date | M1: Aging (Days) | N1: Position Offered | O1: Position Closed | P1: Status | Q1: Offered Candidates | R1: Remarks | S1: Recruiter Name | T1: Replaced Employee | U1: Remark
A2: 1 | B2: India | C2: Quality Assurance | D2: PS | E2: Lead Analyst | F2: Replacement | H2: Chennai | I2: 44971 | J2: 44987 | K2: 44987 | L2: 44991 | M2: =NETWORKDAYS(I2,J2) -> 13 | N2: =IF(K2="",0,NETWORKDAYS(I2,K2)) -> 13 | O2: =IF(L2="",0,NETWORKDAYS(I2,L2)) -> 15 | P2: Joined | R2: Deepak Joined on 6 Mar 23 | T2: Sudhir | U2: Sudhir replacement
A3: =A2+1 -> 2 | B3: USA | C3: Development | D3: Bank OS | E3: Senior Developer | F3: New | H3: USA | I3: 45093 | J3: 45182 | K3: 45141 | L3: 45166 | M3: =NETWORKDAYS(I3,J3) -> 64 | N3: =IF(K3="",0,NETWORKDAYS(I3,K3)) -> 35 | O3: =IF(L3="",0,NETWORKDAYS(I3,L3)) -> 52 | P3: Joined | R3: Sent an offer to Sangeetha and she accepted the offer. Joined August 28, 2023.
A4: =A3+1 -> 3 | B4: India | C4: Development | D4: Bank OS | E4: Senior Developer/Lead Developer | F4: New | H4: Chennai | I4: 45099 | J4: 45001 | M4: =NETWORKDAYS(I4,J4) -> -71 | N4: =IF(K4="",0,NETWORKDAYS(I4,K4)) -> 0 | O4: =IF(L4="",0,NETWORKDAYS(I4,L4)) -> 0 | P4: Suspended | T4: No need for Ganesh replacement | U4: No need for Ganesh replacement
A5: =A4+1 -> 4 | B5: India | C5: Development | D5: Bank OS | E5: Developer | F5: New | H5: Chennai | I5: 45139 | J5: 45182 | K5: 45182 | L5: 45202 | M5: =NETWORKDAYS(I5,J5) -> 32 | N5: =IF(K5="",0,NETWORKDAYS(I5,K5)) -> 32 | O5: =IF(L5="",0,NETWORKDAYS(I5,L5)) -> 46 | P5: Joined | R5: Vigneshwar accepted offer - 3rd Oct | T5: Keerthana is performing good now | U5: Keerthana is performing good now
A6: =A5+1 -> 5 | B6: India | C6: Quality Assurance | D6: FX | E6: Lead Analyst | F6: Replacement | H6: Chennai | I6: 44993 | J6: 45001 | K6: 45001 | L6: 45005 | M6: =NETWORKDAYS(I6,J6) -> 7 | N6: =IF(K6="",0,NETWORKDAYS(I6,K6)) -> 7 | O6: =IF(L6="",0,NETWORKDAYS(I6,L6)) -> 9 | P6: Joined | R6: Farooq Joined on 20 Mar 23 | T6: Priya | U6: Priya replacement
A7: =A6+1 -> 6 | B7: USA | C7: Development | D7: Bank OS | E7: Director of Payment Technology | F7: Replacement | H7: USA | I7: 45047 | J7: 45078 | K7: 45078 | L7: 45082 | M7: =NETWORKDAYS(I7,J7) -> 24 | N7: =IF(K7="",0,NETWORKDAYS(I7,K7)) -> 24 | O7: =IF(L7="",0,NETWORKDAYS(I7,L7)) -> 26 | P7: Joined | R7: Atul Choudhari accepted the offer and joined Finzly on June 5, 2023
A8: =A7+1 -> 7 | B8: India | C8: Quality Assurance | D8: Bank OS | E8: Automation | F8: New | H8: Chennai | I8: 45012 | J8: 45023 | K8: 45023 | L8: 45035 | M8: =NETWORKDAYS(I8,J8) -> 10 | N8: =IF(K8="",0,NETWORKDAYS(I8,K8)) -> 10 | O8: =IF(L8="",0,NETWORKDAYS(I8,L8)) -> 18 | P8: Joined | R8: Nagarajan Joined on 19th April
A9: =A8+1 -> 8 | B9: USA | C9: Professional Services | D9: PS | E9: Senior Business Analyst | F9: New | H9: USA | I9: 45047 | J9: 45112 | K9: 45089 | L9: 45096 | M9: =NETWORKDAYS(I9,J9) -> 48 | N9: =IF(K9="",0,NETWORKDAYS(I9,K9)) -> 31 | O9: =IF(L9="",0,NETWORKDAYS(I9,L9)) -> 36 | P9: Joined | R9: Pandiya Rajan started on June 19, 2023
A10: =A9+1 -> 9 | B10: India | C10: Development | D10: Cash OS | E10: Lead Engineer | F10: Replacement | H10: Chennai | I10: 45100 | J10: 45120 | K10: 45120 | L10: 45121 | M10: =NETWORKDAYS(I10,J10) -> 15 | N10: =IF(K10="",0,NETWORKDAYS(I10,K10)) -> 15 | O10: =IF(L10="",0,NETWORKDAYS(I10,L10)) -> 16 | P10: Joined | R10: Sagana Joined | T10: Sarayu/Sagana | U10: Sarayu/Sagana Replacement
A11: =A10+1 -> 10 | B11: India | C11: Development | D11: Cash OS | E11: Associate Developer | F11: Replacement | H11: Pune | I11: 45076 | J11: 45085 | K11: 45085 | L11: 45089 | M11: =NETWORKDAYS(I11,J11) -> 8 | N11: =IF(K11="",0,NETWORKDAYS(I11,K11)) -> 8 | O11: =IF(L11="",0,NETWORKDAYS(I11,L11)) -> 10 | P11: Joined | R11: Chetan DOJ -12th June | T11: Shubham terminated due to negative BGV | U11: Shubham terminated due to negative BGV
A12: =A11+1 -> 11 | B12: India | C12: Development | D12: PS | E12: Lead Developer | F12: Replacement | H12: Pune | I12: 44987 | J12: 45057 | K12: 45057 | L12: 45061 | M12: =NETWORKDAYS(I12,J12) -> 51 | N12: =IF(K12="",0,NETWORKDAYS(I12,K12)) -> 51 | O12: =IF(L12="",0,NETWORKDAYS(I12,L12)) -> 53 | P12: Joined | R12: Ravipratap joined - 15-May-23 | T12: Shriram replacement | U12: Shriram replacement
A13: =A12+1 -> 12 | B13: India | C13: Development | D13: Bank OS | E13: Lead Developer | F13: Replacement | H13: Pune | I13: 45100 | J13: 45112 | K13: 45112 | L13: 45117 | M13: =NETWORKDAYS(I13,J13) -> 9 | N13: =IF(K13="",0,NETWORKDAYS(I13,K13)) -> 9 | O13: =IF(L13="",0,NETWORKDAYS(I13,L13)) -> 12 | P13: Joined | R13: Prashant Arun Joined - 10th July 2023 | T13: Nilima P replacement | U13: Nilima P replacement
A14: =A13+1 -> 13 | B14: India | C14: Product | D14: Trade Finance | E14: Product Owner | F14: Replacement | H14: Chennai | I14: 45219 | J14: 45180 | K14: 45247 | M14: =NETWORKDAYS(I14,J14) -> -30 | N14: =IF(K14="",0,NETWORKDAYS(I14,K14)) -> 21 | O14: =IF(L14="",0,NETWORKDAYS(I14,L14)) -> 0 | P14: Suspended | R14: Mangesh Offer in approval | T14: Sathya | U14: Sathya
A15: =A14+1 -> 14 | B15: India | C15: Quality Assurance | D15: PS | E15: Lead Analyst | F15: Replacement | H15: Pune | I15: 45123 | J15: 45135 | K15: 45135 | L15: 45138 | M15: =NETWORKDAYS(I15,J15) -> 10 | N15: =IF(K15="",0,NETWORKDAYS(I15,K15)) -> 10 | O15: =IF(L15="",0,NETWORKDAYS(I15,L15)) -> 11 | P15: Joined | R15: Pravin Gurav joined 31st July | T15: Deepak Replacement | U15: Deepak Replacement
A16: =A15+1 -> 15 | B16: India | C16: Development | D16: PS | E16: Lead Developer | F16: Replacement | H16: Pune | I16: 45169 | J16: 45185 | K16: 45185 | L16: 45187 | M16: =NETWORKDAYS(I16,J16) -> 12 | N16: =IF(K16="",0,NETWORKDAYS(I16,K16)) -> 12 | O16: =IF(L16="",0,NETWORKDAYS(I16,L16)) -> 13 | P16: Joined | R16: Swapnil | T16: Vivek Honule Replacement | U16: Vivek Honule Replacement
A17: =A16+1 -> 16 | B17: India | C17: Operations | D17: Finance | E17: Accountant | F17: New | H17: Pune/Chennai | I17: 45133 | J17: 45158 | K17: 45158 | L17: 45202 | M17: =NETWORKDAYS(I17,J17) -> 18 | N17: =IF(K17="",0,NETWORKDAYS(I17,K17)) -> 18 | O17: =IF(L17="",0,NETWORKDAYS(I17,L17)) -> 50 | P17: Joined | R17: Chaitanya joined on 25th Sep 2023
A18: =A17+1 -> 17 | B18: USA | C18: Professional Services | D18: PS | E18: Senior Business Analyst | F18: New | H18: USA | I18: 45129 | J18: =TODAY() -> 46324 | K18: 45154 | L18: 45175 | M18: =NETWORKDAYS(I18,J18) -> 854 | N18: =IF(K18="",0,NETWORKDAYS(I18,K18)) -> 18 | O18: =IF(L18="",0,NETWORKDAYS(I18,L18)) -> 33 | P18: Joined | R18: Souvik started on October 5, 2023. Bala will start on October 10, 2023.
A19: =A18+1 -> 18 | B19: USA | C19: Professional Services | D19: PS | E19: Client Implementation Manager | F19: New | H19: USA | I19: 45184 | J19: 45175 | K19: 45155 | L19: 45175 | M19: =NETWORKDAYS(I19,J19) -> -8 | N19: =IF(K19="",0,NETWORKDAYS(I19,K19)) -> -22 | O19: =IF(L19="",0,NETWORKDAYS(I19,L19)) -> -8 | P19: Joined | R19: We have moved Rehman into this role, he was originally being considered for the Senior Business Analyst Role.
A20: =A19+1 -> 19 | B20: India | C20: Development | D20: Cash OS | E20: Lead Engineer | F20: Replacement | H20: Pune | I20: 45128 | J20: 45135 | K20: 45135 | L20: 45131 | M20: =NETWORKDAYS(I20,J20) -> 6 | N20: =IF(K20="",0,NETWORKDAYS(I20,K20)) -> 6 | O20: =IF(L20="",0,NETWORKDAYS(I20,L20)) -> 2 | P20: Joined | R20: Anupam joined 31st July | T20: Sagana Replacement | U20: Sagana Replacement
A21: =A20+1 -> 20 | B21: India | C21: Quality Assurance | D21: FX | E21: Automation | F21: New | H21: Chennai | I21: 45154 | J21: 45180 | K21: 45180 | L21: 45181 | M21: =NETWORKDAYS(I21,J21) -> 19 | N21: =IF(K21="",0,NETWORKDAYS(I21,K21)) -> 19 | O21: =IF(L21="",0,NETWORKDAYS(I21,L21)) -> 20 | P21: Joined | R21: Felvia P. Tentative joining - 11 September 2023
A22: =A21+1 -> 21 | B22: India | C22: Development | D22: FX | E22: Mid Developer | F22: New | H22: Chennai | I22: 45289 | J22: =TODAY() -> 46324 | K22: 45343 | L22: 45362 | M22: =NETWORKDAYS(I22,J22) -> 740 | N22: =IF(K22="",0,NETWORKDAYS(I22,K22)) -> 39 | O22: =IF(L22="",0,NETWORKDAYS(I22,L22)) -> 52 | P22: Temp Hold | S22: Sugan
A23: =A22+1 -> 22 | B23: India | C23: Customer Success | D23: Support | E23: Production Support | F23: New | H23: Pune | I23: 45159 | J23: 45175 | K23: 45175 | L23: 45176 | M23: =NETWORKDAYS(I23,J23) -> 13 | N23: =IF(K23="",0,NETWORKDAYS(I23,K23)) -> 13 | O23: =IF(L23="",0,NETWORKDAYS(I23,L23)) -> 14 | P23: Joined | R23: Dipak Patil joined 7th september 2023
A24: =A23+1 -> 23 | B24: India | C24: Customer Success | D24: Support | E24: Production Support | F24: New | H24: Chennai | I24: 45202 | J24: 45180 | K24: 45180 | L24: 45202 | M24: =NETWORKDAYS(I24,J24) -> -17 | N24: =IF(K24="",0,NETWORKDAYS(I24,K24)) -> -17 | O24: =IF(L24="",0,NETWORKDAYS(I24,L24)) -> 1 | P24: Joined | R24: Kapil joined
A25: =A24+1 -> 24 | B25: India | C25: Development | D25: PS | E25: Developer(BankOs) | F25: New | H25: Pune | I25: 45149 | J25: 45161 | K25: 45161 | L25: 45162 | M25: =NETWORKDAYS(I25,J25) -> 9 | N25: =IF(K25="",0,NETWORKDAYS(I25,K25)) -> 9 | O25: =IF(L25="",0,NETWORKDAYS(I25,L25)) -> 10 | P25: Joined | R25: Sanket DOJ- 25th August 2023
A26: =A25+1 -> 25 | B26: India | C26: Development | D26: PS | E26: Mid Developer(BankOs) | F26: New | H26: Pune | I26: 45149 | J26: 45161 | K26: 45161 | L26: 45173 | M26: =NETWORKDAYS(I26,J26) -> 9 | N26: =IF(K26="",0,NETWORKDAYS(I26,K26)) -> 9 | O26: =IF(L26="",0,NETWORKDAYS(I26,L26)) -> 17 | P26: Joined | R26: Sagar Kharche joined on 4th September
A27: =A26+1 -> 26 | B27: India | C27: Development | D27: PS | E27: Developer(FX) | F27: Replacement | H27: Pune | I27: 45149 | J27: 45161 | K27: 45161 | L27: 45173 | M27: =NETWORKDAYS(I27,J27) -> 9 | N27: =IF(K27="",0,NETWORKDAYS(I27,K27)) -> 9 | O27: =IF(L27="",0,NETWORKDAYS(I27,L27)) -> 17 | P27: Joined | R27: Srikrushna joining on 4th September | T27: Hemant replacement | U27: Hemant replacement
A28: =A27+1 -> 27 | B28: India | C28: Quality Assurance | D28: FX | E28: Manual QA | F28: New | H28: Chennai | I28: 45149 | J28: 45162 | K28: 45162 | L28: 45163 | M28: =NETWORKDAYS(I28,J28) -> 10 | N28: =IF(K28="",0,NETWORKDAYS(I28,K28)) -> 10 | O28: =IF(L28="",0,NETWORKDAYS(I28,L28)) -> 11 | P28: Joined | R28: Hari Sankar, DOJ: 25th August 2023
A29: =A28+1 -> 28 | B29: India | C29: Operations | D29: HR | E29: Recruitment | F29: New | H29: Chennai | I29: 45149 | J29: 45158 | K29: 45158 | L29: 45159 | M29: =NETWORKDAYS(I29,J29) -> 6 | N29: =IF(K29="",0,NETWORKDAYS(I29,K29)) -> 6 | O29: =IF(L29="",0,NETWORKDAYS(I29,L29)) -> 7 | P29: Joined | R29: Sugan Gopi joined on 21st Augut 2023
A30: =A29+1 -> 29 | B30: India | C30: Development | D30: FX | E30: Mid Developer | F30: New | H30: Chennai | I30: 45154 | J30: 45237 | K30: 45237 | L30: 45238 | M30: =NETWORKDAYS(I30,J30) -> 60 | N30: =IF(K30="",0,NETWORKDAYS(I30,K30)) -> 60 | O30: =IF(L30="",0,NETWORKDAYS(I30,L30)) -> 61 | P30: Joined | R30: Manikanda S joined
A31: =A30+1 -> 30 | B31: India | C31: BI | D31: Bank OS | E31: BI | F31: New | H31: Pune | I31: 45289 | J31: =TODAY() -> 46324 | M31: =NETWORKDAYS(I31,J31) -> 740 | N31: =IF(K31="",0,NETWORKDAYS(I31,K31)) -> 0 | O31: =IF(L31="",0,NETWORKDAYS(I31,L31)) -> 0 | P31: Suspended | R31: 2 Final Interview with Vijay/ L1 - 1 Sch. Suspended on 6-FEB-24 based on Atul's email. | S31: Sugan
A32: =A31+1 -> 31 | B32: India | C32: Quality Assurance | D32: PS | E32: QA | F32: Replacement | H32: Pune | I32: 45167 | J32: 45182 | K32: 45182 | L32: 45191 | M32: =NETWORKDAYS(I32,J32) -> 12 | N32: =IF(K32="",0,NETWORKDAYS(I32,K32)) -> 12 | O32: =IF(L32="",0,NETWORKDAYS(I32,L32)) -> 19 | P32: Joined | R32: Basalingaappa | T32: Tapan Replacement | U32: Tapan Replacement
A33: =A32+1 -> 32 | B33: India | C33: Development | D33: Bank OS | E33: Lead Engineer | F33: Backup | H33: Pune | I33: 45202 | J33: 45225 | K33: 45225 | L33: 45236 | M33: =NETWORKDAYS(I33,J33) -> 18 | N33: =IF(K33="",0,NETWORKDAYS(I33,K33)) -> 18 | O33: =IF(L33="",0,NETWORKDAYS(I33,L33)) -> 25 | P33: Joined | R33: Ganesh Kutaye joined on 6th November | T33: Uday Kumar | U33: Uday Kumar
A34: =A33+1 -> 33 | B34: India | C34: Quality Assurance | D34: Cash OS | E34: Automation Developer | F34: New | H34: Pune | I34: 45182 | J34: 45198 | K34: 45198 | L34: 45202 | M34: =NETWORKDAYS(I34,J34) -> 13 | N34: =IF(K34="",0,NETWORKDAYS(I34,K34)) -> 13 | O34: =IF(L34="",0,NETWORKDAYS(I34,L34)) -> 15 | P34: Joined | R34: Sarika
A35: =A34+1 -> 34 | B35: India | C35: Development | D35: Cash OS | E35: Mobile Developer (React Native) | F35: New | H35: Pune | I35: 45202 | J35: 45233 | K35: 45233 | L35: 45257 | M35: =NETWORKDAYS(I35,J35) -> 24 | N35: =IF(K35="",0,NETWORKDAYS(I35,K35)) -> 24 | O35: =IF(L35="",0,NETWORKDAYS(I35,L35)) -> 40 | P35: Joined | R35: Kishor Patil joined
A36: =A35+1 -> 35 | B36: India | C36: Development | D36: Cash OS | E36: Mid to Senior Level Full stack | F36: New | H36: Pune | I36: 45182 | J36: 45202 | K36: 45202 | L36: 45203 | M36: =NETWORKDAYS(I36,J36) -> 15 | N36: =IF(K36="",0,NETWORKDAYS(I36,K36)) -> 15 | O36: =IF(L36="",0,NETWORKDAYS(I36,L36)) -> 16 | P36: Joined | R36: Baskaran Joined
A37: =A36+1 -> 36 | B37: India | C37: Development | D37: Cash OS | E37: Mid-level Java developer | F37: New | H37: Pune | I37: 45182 | J37: 45198 | K37: 45198 | L37: 45209 | M37: =NETWORKDAYS(I37,J37) -> 13 | N37: =IF(K37="",0,NETWORKDAYS(I37,K37)) -> 13 | O37: =IF(L37="",0,NETWORKDAYS(I37,L37)) -> 20 | P37: Joined | R37: Akshay
A38: =A37+1 -> 37 | B38: USA | C38: Operations | D38: IT Admin | E38: System (IT) Administrator | F38: Replacement | H38: USA | I38: 45176 | J38: 45229 | K38: 45190 | L38: 45201 | M38: =NETWORKDAYS(I38,J38) -> 38 | N38: =IF(K38="",0,NETWORKDAYS(I38,K38)) -> 11 | O38: =IF(L38="",0,NETWORKDAYS(I38,L38)) -> 18 | P38: Joined | R38: Suman Vaishnav started on October 2, 2023 | T38: Ted replacement | U38: Ted replacement
A39: =A38+1 -> 38 | B39: USA | C39: Operations | D39: HR | E39: Recruiter | F39: New | H39: USA | I39: 45176 | J39: 45239 | K39: 45189 | L39: 45203 | M39: =NETWORKDAYS(I39,J39) -> 46 | N39: =IF(K39="",0,NETWORKDAYS(I39,K39)) -> 10 | O39: =IF(L39="",0,NETWORKDAYS(I39,L39)) -> 20 | P39: Joined | R39: Position was offered to Nella Rosas, she has accepted the offer.
A40: =A39+1 -> 39 | B40: USA | C40: Development | D40: Cash OS | E40: Senior API Developer | F40: New | H40: USA | I40: 45176 | J40: 45236 | K40: 45218 | L40: 45250 | M40: =NETWORKDAYS(I40,J40) -> 43 | N40: =IF(K40="",0,NETWORKDAYS(I40,K40)) -> 31 | O40: =IF(L40="",0,NETWORKDAYS(I40,L40)) -> 53 | P40: Joined | R40: Uday accepted the offer and started on December 4, 2023. | S40: Marissa
A41: =A40+1 -> 40 | B41: USA | C41: Development | D41: Cash OS | E41: QA Manager | F41: New | H41: USA | I41: 45176 | J41: 45204 | K41: 45204 | L41: 45215 | M41: =NETWORKDAYS(I41,J41) -> 21 | N41: =IF(K41="",0,NETWORKDAYS(I41,K41)) -> 21 | O41: =IF(L41="",0,NETWORKDAYS(I41,L41)) -> 28 | P41: Joined | R41: Pranesh joined on October 16, 2023.
A42: =A41+1 -> 41 | B42: USA | C42: Development | D42: Bank OS | E42: QA Manager | F42: New | H42: USA | I42: 45176 | J42: 45446 | K42: 45233 | L42: 45278 | M42: =NETWORKDAYS(I42,J42) -> 193 | N42: =IF(K42="",0,NETWORKDAYS(I42,K42)) -> 42 | O42: =IF(L42="",0,NETWORKDAYS(I42,L42)) -> 73 | P42: Joined | R42: Abhishek Kesharwani did not accept offer. Back to interviewing candidates. I've sent to 3 solid candidates to Atul, waiting on feedback. Atul is sending Amit Singh for L2 interview with Vijar which I've scheduled for tomorrow 10/27/23 02:30PM. Vijay selected Amit Singh for the role, pending offer approval. Start day December 18th. | S42: Nella
A43: =A42+1 -> 42 | B43: USA | C43: Development | D43: DevOps | E43: Head of Infrastructure | F43: New | H43: USA | I43: 45176 | J43: 45387 | M43: =NETWORKDAYS(I43,J43) -> 152 | N43: =IF(K43="",0,NETWORKDAYS(I43,K43)) -> 0 | O43: =IF(L43="",0,NETWORKDAYS(I43,L43)) -> 0 | P43: Joined | R43: Jim Boyer was offered the position. Anticipated start date is October 31, 2023. | S43: Marissa
A44: =A43+1 -> 43 | B44: USA | C44: Development | D44: Bank OS | E44: BI Developer | F44: New | H44: USA | I44: 45176 | J44: 45443 | M44: =NETWORKDAYS(I44,J44) -> 192 | N44: =IF(K44="",0,NETWORKDAYS(I44,K44)) -> 0 | O44: =IF(L44="",0,NETWORKDAYS(I44,L44)) -> #VALUE! | P44: Suspended | R44: Job Description has been provided. Will begin sourcing and recruiting for this role. 1 interviewed and didnt do well. 2 interviews pending for Monday 2PM and 3 PM EST time. Both Interviews L1. Aditi Rane is going for an L2 interview now with Vijay. 10/27/23 at noon EST. Vijay said no top Aditi, we are back to sourcing. Sent 2 more solid candidates today. SENT 2 MORE TODAY(11/07). 11/08-Atul wants Vamsi to go fot a L2 with Vijay. 11/09- set up (L2) interview for Vamsi with Vijay mon 13 at 1pm. Vamsi said it went exceptionally well, waiting on Vija's feedback. Vijay feedback was "Vamsi Does not sound great fit for us. Will hold on this candidate for now." I sent follow up email asking for specific feedback. Today 11/16- I've sent 2 more people. Still waiting on specific feedback from Vijay. 11/22/23 - sent 2 more profiles to Atul and scheduled 2 interviews with the prevous 2 candidates. Today 11/27/23 sent a another candidate (solid) | S44: Nella
A45: =A44+1 -> 44 | B45: USA | C45: Development | D45: FX | E45: FX STAR Dev Lead | F45: New | H45: USA | I45: 45176 | J45: 45446 | M45: =NETWORKDAYS(I45,J45) -> 193 | N45: =IF(K45="",0,NETWORKDAYS(I45,K45)) -> 0 | O45: =IF(L45="",0,NETWORKDAYS(I45,L45)) -> 0 | P45: Suspended | R45: Mark Thome to provide Job Description.Received JD from Vikas. Waiting on Mark's final approval. We are sourcing candidates now. Sent Vikas 4 solid candidates. Vikas rejected them all and updated JD and ONLY wants candidates with hands on experience building foreign applications. Sent 2 more candidates, havent gotten feedback. Vinay brought a referral (Lalit Markande) and have scheduled an interview for 11/02/23 at 3PM with Anil KK. Anil interviwed Lalit for 1 hour and recommended a 2nd evaluation. | S45: Nella
A46: =A45+1 -> 45 | B46: USA | C46: Development | D46: FX | E46: BankOS Dev Lead | F46: New | H46: USA | I46: 45176 | J46: 45489 | M46: =NETWORKDAYS(I46,J46) -> 224 | N46: =IF(K46="",0,NETWORKDAYS(I46,K46)) -> 0 | O46: =IF(L46="",0,NETWORKDAYS(I46,L46)) -> 0 | P46: Suspended | R46: Mark Thome to provide Job Description.
A47: =A46+1 -> 46 | B47: India | C47: Quality Assurance | D47: PS | E47: Mid QA Analyst | F47: Replacement | H47: Pune | J47: 45471 | M47: =NETWORKDAYS(I47,J47) -> 32480 | N47: =IF(K47="",0,NETWORKDAYS(I47,K47)) -> 0 | O47: =IF(L47="",0,NETWORKDAYS(I47,L47)) -> 0 | P47: Suspended | R47: Hold temp | T47: Onkar | U47: Onkar
A48: =A47+1 -> 47 | B48: India | C48: Development | D48: Bank OS | E48: Mid Developer | F48: Replacement | H48: Pune | I48: 45197 | J48: 45457 | M48: =NETWORKDAYS(I48,J48) -> 187 | N48: =IF(K48="",0,NETWORKDAYS(I48,K48)) -> 0 | O48: =IF(L48="",0,NETWORKDAYS(I48,L48)) -> 0 | P48: Suspended | R48: Parmeshwar is out from PIP | T48: Parmeshwar | U48: Parmeshwar
A49: =A48+1 -> 48 | B49: India | C49: Quality Assurance | D49: Bank OS | E49: Mid QA Analyst | F49: New | H49: Chennai | I49: 45215 | J49: 45492 | M49: =NETWORKDAYS(I49,J49) -> 200 | N49: =IF(K49="",0,NETWORKDAYS(I49,K49)) -> 0 | O49: =IF(L49="",0,NETWORKDAYS(I49,L49)) -> 0 | P49: Suspended | R49: Position on Hold
A50: =A49+1 -> 49 | B50: India | C50: Quality Assurance | D50: Bank OS | E50: Senior QA Analyst | F50: New | H50: Pune | I50: 45215 | J50: 45229 | K50: 45229 | L50: 45231 | M50: =NETWORKDAYS(I50,J50) -> 11 | N50: =IF(K50="",0,NETWORKDAYS(I50,K50)) -> 11 | O50: =IF(L50="",0,NETWORKDAYS(I50,L50)) -> 13 | P50: Joined | R50: Anas offer in approval
A51: =A50+1 -> 50 | B51: India | C51: Quality Assurance | D51: Deposit | E51: QA Analyst | F51: New | G51: Full-time | H51: Pune | I51: =TODAY() -> 46324 | J51: 45529 | M51: =NETWORKDAYS(I51,J51) -> -569 | N51: =IF(K51="",0,NETWORKDAYS(I51,K51)) -> 0 | O51: =IF(L51="",0,NETWORKDAYS(I51,L51)) -> 0 | P51: Suspended | R51: Sourcing | S51: Andleeb
A52: =A51+1 -> 51 | B52: USA | C52: Development | D52: Bank OS | E52: Payments Product Manager | F52: New | H52: USA | I52: 45215 | J52: 45238 | K52: 45238 | L52: 45260 | M52: =NETWORKDAYS(I52,J52) -> 18 | N52: =IF(K52="",0,NETWORKDAYS(I52,K52)) -> 18 | O52: =IF(L52="",0,NETWORKDAYS(I52,L52)) -> 34 | P52: Joined | R52: HR and Hiring manager reviewing JD. Job is posted on LinkedIn. Sent 2 candidates to Vijay. Sent 2 more. He interviwed Michael and said no. Interviewd Shikhar and wants him on hold. Extended offer letter to Srinivas Chintakrinda | S52: Nella
A53: =A52+1 -> 52 | B53: USA | C53: Development | D53: Cash OS | E53: Monitoring App Developer | F53: New | H53: USA | I53: 45215 | J53: 45513 | M53: =NETWORKDAYS(I53,J53) -> 215 | N53: =IF(K53="",0,NETWORKDAYS(I53,K53)) -> 0 | O53: =IF(L53="",0,NETWORKDAYS(I53,L53)) -> 0 | P53: Suspended | R53: Waiting on Sajeesh to go over resumes and give us his feedback. He has/ been busy with production issues, etc. I followed up with him again today 01/08/2024. | S53: Nella / Marissa
A54: =A53+1 -> 53 | B54: USA | C54: Operations | D54: Marketing | E54: Digital Marketing Director | F54: New | H54: USA | I54: 45315 | J54: 45362 | K54: 45362 | L54: 45376 | M54: =NETWORKDAYS(I54,J54) -> 34 | N54: =IF(K54="",0,NETWORKDAYS(I54,K54)) -> 34 | O54: =IF(L54="",0,NETWORKDAYS(I54,L54)) -> 44 | P54: Joined | R54: Ben Cowles has accpeted the offer. | S54: Marissa
A55: =A54+1 -> 54 | B55: USA | C55: Operations | D55: Sales | E55: Business Development Representative | F55: New | H55: USA | I55: 45334 | J55: 45512 | K55: 45335 | L55: 45355 | M55: =NETWORKDAYS(I55,J55) -> 129 | N55: =IF(K55="",0,NETWORKDAYS(I55,K55)) -> 2 | O55: =IF(L55="",0,NETWORKDAYS(I55,L55)) -> 16 | P55: Joined | R55: Grant Hamblen jonied on March 4, 2024 | S55: Marissa
A56: =A55+1 -> 55 | B56: USA | C56: Operations | D56: Marketing | E56: Chief Marketing Officer | F56: New | H56: USA | I56: 45334 | J56: 45561 | K56: 45373 | L56: 45397 | M56: =NETWORKDAYS(I56,J56) -> 164 | N56: =IF(K56="",0,NETWORKDAYS(I56,K56)) -> 30 | O56: =IF(L56="",0,NETWORKDAYS(I56,L56)) -> 46 | P56: Joined | R56: Cindy Guiterrez accpeted the offer and joined on April 15, 2024. | S56: Marissa
A57: =A56+1 -> 56 | B57: USA | C57: Development | D57: Technology | E57: Head of Engineering | F57: New | H57: USA | I57: 45369 | J57: 45377 | K57: 45373 | L57: 45377 | M57: =NETWORKDAYS(I57,J57) -> 7 | N57: =IF(K57="",0,NETWORKDAYS(I57,K57)) -> 5 | O57: =IF(L57="",0,NETWORKDAYS(I57,L57)) -> 7 | P57: Joined | R57: Duc Trinh accpeted the offer and plans to start on March 26, 2024. | S57: Marissa
A58: =A57+1 -> 57 | B58: USA | C58: Operations | D58: Sales | E58: Business Development Representative | F58: New | H58: USA | I58: 45425 | J58: 45448 | K58: 45436 | L58: 45448 | M58: =NETWORKDAYS(I58,J58) -> 18 | N58: =IF(K58="",0,NETWORKDAYS(I58,K58)) -> 10 | O58: =IF(L58="",0,NETWORKDAYS(I58,L58)) -> 18 | P58: Joined | R58: Marissa to speak with Zach on May 15 | S58: Marissa
A59: =A58+1 -> 58 | B59: USA | C59: Support | D59: Infosec | E59: Chief Information Security Officer | F59: New | H59: USA | I59: 45414 | J59: 45446 | K59: 45426 | L59: 45446 | M59: =NETWORKDAYS(I59,J59) -> 23 | N59: =IF(K59="",0,NETWORKDAYS(I59,K59)) -> 9 | O59: =IF(L59="",0,NETWORKDAYS(I59,L59)) -> 23 | P59: Joined | R59: Joining date confirmed to 3 Jun 24 | S59: Marissa
A60: =A59+1 -> 59 | B60: USA | C60: Operations | D60: Sales | E60: Solutions Engineer | F60: New | H60: USA | I60: 45460 | J60: 45467 | K60: 45436 | L60: 45467 | M60: =NETWORKDAYS(I60,J60) -> 6 | N60: =IF(K60="",0,NETWORKDAYS(I60,K60)) -> -17 | O60: =IF(L60="",0,NETWORKDAYS(I60,L60)) -> 6 | P60: Joined | R60: Dean rejected the job due his own personal health issues. We will offer the position to Rohan Shenoy. | S60: Marissa
A61: =A60+1 -> 60 | B61: USA | C61: Development | D61: Technology | E61: Senior Director of Engineering | F61: New | H61: USA | I61: 45461 | J61: 45506 | K61: 45506 | L61: 45523 | M61: =NETWORKDAYS(I61,J61) -> 34 | N61: =IF(K61="",0,NETWORKDAYS(I61,K61)) -> 34 | O61: =IF(L61="",0,NETWORKDAYS(I61,L61)) -> 45 | P61: Joined | R61: Tej Singh joined on August 19, 2024. | S61: Marissa
A62: =A61+1 -> 61 | B62: India | C62: Development | D62: FX | E62: Senior Software Engineer | F62: New | H62: Chennai | I62: 45300 | J62: 45666 | M62: =NETWORKDAYS(I62,J62) -> 263 | N62: =IF(K62="",0,NETWORKDAYS(I62,K62)) -> 0 | O62: =IF(L62="",0,NETWORKDAYS(I62,L62)) -> 0 | P62: Suspended | S62: Sugan
A63: =A62+1 -> 62 | B63: USA | C63: Development | D63: Bank OS | E63: Software Engineer | F63: Replacement | H63: USA | I63: 45231 | J63: =TODAY() -> 46324 | M63: =NETWORKDAYS(I63,J63) -> 782 | N63: =IF(K63="",0,NETWORKDAYS(I63,K63)) -> 0 | O63: =IF(L63="",0,NETWORKDAYS(I63,L63)) -> 0 | P63: Suspended | R63: Sangeetha's replacement. Waiting for Atul to provide JD. 11/07- JD Provided, job is posted, will sorce on this tonight and tomorrow. Marissa is doing a pre-screening today. 11/08- I sent 3 solid candidates, Atul requested interviews for all. I'm schedulling eveyone for 11/13 (L1 with Vinay and Anil KK). 11-09 2 interviews are scheduled for monday and 1 for tuesday. Today 11/13 , 1 interview went well - tomorrow one more to go. 11/14-I've scheduled Sai Koushik for L2 with Vijay tomorrow 11/15. 11/15 I've scheduled Sunitha for 11/20 @2PM L1 with Vinay and Anil KK. Another (L1) scheduled for 11/21 with Ritin (vinay and Anil KK). Per Vijay we are holding off this role. | S63: Nella
A64: =A63+1 -> 63 | B64: India | C64: Quality Assurance | D64: FX | E64: Mid QA(4-6) | F64: New | H64: Chennai | I64: 45223 | J64: 45239 | K64: 45239 | L64: 45240 | M64: =NETWORKDAYS(I64,J64) -> 13 | N64: =IF(K64="",0,NETWORKDAYS(I64,K64)) -> 13 | O64: =IF(L64="",0,NETWORKDAYS(I64,L64)) -> 14 | P64: Joined | R64: Kalaivani Joined
A65: =A64+1 -> 64 | B65: India | C65: Quality Assurance | D65: Bank OS | E65: Mid QA(4-6) | F65: New | H65: Chennai | I65: 45223 | J65: 45236 | K65: 45236 | L65: 45237 | M65: =NETWORKDAYS(I65,J65) -> 10 | N65: =IF(K65="",0,NETWORKDAYS(I65,K65)) -> 10 | O65: =IF(L65="",0,NETWORKDAYS(I65,L65)) -> 11 | P65: Joined | R65: Srinath Joined
A66: =A65+1 -> 65 | B66: India | C66: Operations | D66: HR | E66: HR Generalist | F66: New | H66: Chennai | I66: 45259 | J66: 45280 | K66: 45280 | L66: 45311 | M66: =NETWORKDAYS(I66,J66) -> 16 | N66: =IF(K66="",0,NETWORKDAYS(I66,K66)) -> 16 | O66: =IF(L66="",0,NETWORKDAYS(I66,L66)) -> 38 | P66: Joined | R66: Basakaran, DOJ - 20th Jan
A67: =A66+1 -> 66 | B67: USA | C67: Development | D67: Production Support | E67: Trainee Suport Engineer | H67: USA | I67: 45231 | J67: =TODAY() -> 46324 | M67: =NETWORKDAYS(I67,J67) -> 782 | N67: =IF(K67="",0,NETWORKDAYS(I67,K67)) -> 0 | O67: =IF(L67="",0,NETWORKDAYS(I67,L67)) -> 0 | P67: Joined | R67: Reporting Manager is Ranjit Sandbhor. Candidates name is Ajayraja Senthilkumar. He's flying back to the US on December 7th. Ajayraja has joined! | S67: Nella
A68: =A67+1 -> 67 | B68: India | C68: Development | D68: FX | E68: Mid Developer | F68: New | H68: Pune | I68: 45289 | J68: =TODAY() -> 46324 | M68: =NETWORKDAYS(I68,J68) -> 740 | N68: =IF(K68="",0,NETWORKDAYS(I68,K68)) -> 0 | O68: =IF(L68="",0,NETWORKDAYS(I68,L68)) -> 0 | P68: Temp Hold | S68: Sugan
A69: =A68+1 -> 68 | B69: India | C69: Development | D69: Cash OS | E69: UI/UX Developer | H69: Pune | M69: =NETWORKDAYS(I69,J69) -> 0 | N69: =IF(K69="",0,NETWORKDAYS(I69,K69)) -> 0 | O69: =IF(L69="",0,NETWORKDAYS(I69,L69)) -> 0 | P69: Suspended | R69: Suja is in discussion with one agency approved by Booshan | S69: Andleeb
A70: =A69+1 -> 69 | B70: India | C70: Development | D70: Deposit | E70: Software Engineer | F70: New | H70: Pune | I70: 45385 | J70: =TODAY() -> 46324 | M70: =NETWORKDAYS(I70,J70) -> 672 | N70: =IF(K70="",0,NETWORKDAYS(I70,K70)) -> 0 | O70: =IF(L70="",0,NETWORKDAYS(I70,L70)) -> 0 | P70: Temp Hold | R70: L1 Sch | S70: Andleeb
A71: =A70+1 -> 70 | B71: India | C71: Development | D71: PS | E71: Lead Engineer | F71: Replacement | H71: Pune | I71: 45418 | J71: 45446 | K71: 45446 | L71: 45477 | M71: =NETWORKDAYS(I71,J71) -> 21 | N71: =IF(K71="",0,NETWORKDAYS(I71,K71)) -> 21 | O71: =IF(L71="",0,NETWORKDAYS(I71,L71)) -> 44 | P71: Joined | R71: Sahil Arora in offer discussion (3rd july) | S71: Andleeb
A72: =A71+1 -> 71 | B72: India | C72: Product | D72: FX | E72: Product Owner | F72: Replacement | H72: Chennai | I72: 45327 | J72: 45387 | K72: 45387 | L72: 45411 | M72: =NETWORKDAYS(I72,J72) -> 45 | N72: =IF(K72="",0,NETWORKDAYS(I72,K72)) -> 45 | O72: =IF(L72="",0,NETWORKDAYS(I72,L72)) -> 61 | P72: Joined | R72: Naga Prasad Joined on 29th April | S72: Andleeb
A73: =A72+1 -> 72 | B73: India | C73: Business Analyst | D73: PS | E73: Business Analyst | F73: New | H73: Pune | I73: 45397 | J73: 45443 | K73: 45443 | L73: 45443 | M73: =NETWORKDAYS(I73,J73) -> 35 | N73: =IF(K73="",0,NETWORKDAYS(I73,K73)) -> 35 | O73: =IF(L73="",0,NETWORKDAYS(I73,L73)) -> 35 | P73: Joined | R73: Jayant IJOP final discussion scheduled with Nagesh | S73: Andleeb
A74: =A73+1 -> 73 | B74: India | C74: Engineering | D74: Bank OS | E74: Software Engineer | F74: Replacement | G74: Full-time | H74: Pune | I74: 45852 | J74: 45852 | K74: 45842 | L74: =K74+60 -> 45902 | M74: =NETWORKDAYS(I74,J74) -> 1 | N74: =IF(K74="",0,NETWORKDAYS(I74,K74)) -> -7 | O74: =IF(L74="",0,NETWORKDAYS(I74,L74)) -> 37 | P74: Suspended | Q74: Assessment | R74: Shuhas Kakde Offered | S74: Thirukumaran
A75: =A74+1 -> 74 | B75: India | C75: Development | D75: PS | E75: Software Engineer | F75: Replacement | H75: Pune | I75: 45422 | J75: 45446 | K75: 45446 | L75: 45531 | M75: =NETWORKDAYS(I75,J75) -> 17 | N75: =IF(K75="",0,NETWORKDAYS(I75,K75)) -> 17 | O75: =IF(L75="",0,NETWORKDAYS(I75,L75)) -> 78 | P75: Joined | R75: Sangram offer accepted , DOJ : 27th August | S75: Andleeb
A76: =A75+1 -> 75 | B76: India | C76: Quality Assurance | D76: FX | E76: QA Analyst | F76: Replacement | H76: Chennai | I76: 45441 | J76: 45489 | K76: 45489 | L76: 45499 | M76: =NETWORKDAYS(I76,J76) -> 35 | N76: =IF(K76="",0,NETWORKDAYS(I76,K76)) -> 35 | O76: =IF(L76="",0,NETWORKDAYS(I76,L76)) -> 43 | P76: Joined | R76: Gopal tentative joining 26th July | S76: Andleeb
A77: =A76+1 -> 76 | B77: India | C77: Quality Assurance | D77: FX | E77: Sr QA Analyst | H77: Chennai | I77: 45463 | J77: 45471 | K77: 45471 | L77: 45565 | M77: =NETWORKDAYS(I77,J77) -> 7 | N77: =IF(K77="",0,NETWORKDAYS(I77,K77)) -> 7 | O77: =IF(L77="",0,NETWORKDAYS(I77,L77)) -> 73 | P77: Joined | R77: Arunagiri Joined,(DOJ 30th Sept) | S77: Andleeb/Thiru
A78: =A77+1 -> 77 | B78: India | C78: Operations | D78: Finance | E78: Finance Manager | F78: Replacement | H78: Chennai | I78: 45436 | J78: 45457 | K78: 45457 | L78: 45460 | M78: =NETWORKDAYS(I78,J78) -> 16 | N78: =IF(K78="",0,NETWORKDAYS(I78,K78)) -> 16 | O78: =IF(L78="",0,NETWORKDAYS(I78,L78)) -> 17 | P78: Joined | R78: Rajesh joined on 13th June | S78: Andleeb
A79: =A78+1 -> 78 | B79: India | C79: Quality Assurance | D79: FX | E79: Lead QA Analyst | F79: Replacement | H79: Chennai | I79: 45439 | J79: 45492 | K79: 45492 | L79: 45517 | M79: =NETWORKDAYS(I79,J79) -> 40 | N79: =IF(K79="",0,NETWORKDAYS(I79,K79)) -> 40 | O79: =IF(L79="",0,NETWORKDAYS(I79,L79)) -> 57 | P79: Joined | R79: Priya offer accepted, DOJ 12th August | S79: Thirukumaran
A80: =A79+1 -> 79 | B80: India | C80: Quality Assurance | D80: Bank OS | E80: Lead QA Analyst | F80: Replacement | H80: Chennai | I80: 45582 | J80: 45600 | K80: 45600 | L80: 45628 | M80: =NETWORKDAYS(I80,J80) -> 13 | N80: =IF(K80="",0,NETWORKDAYS(I80,K80)) -> 13 | O80: =IF(L80="",0,NETWORKDAYS(I80,L80)) -> 33 | P80: Joined | R80: Sathish offered joining 2nd Dec | S80: Andleeb
A81: =A80+1 -> 80 | B81: India | C81: Development | D81: Bank OS | E81: Jr Developer | H81: Chennai | I81: 45475 | J81: 45529 | K81: 45529 | L81: 45537 | M81: =NETWORKDAYS(I81,J81) -> 39 | N81: =IF(K81="",0,NETWORKDAYS(I81,K81)) -> 39 | O81: =IF(L81="",0,NETWORKDAYS(I81,L81)) -> 45 | P81: Joined | R81: Mahalakshmi Joined, DOJ: 2nd Sept | S81: Thirukumaran
A82: =A81+1 -> 81 | B82: India | C82: Development | D82: Bank OS | E82: Technology Lead | H82: Pune | I82: 45454 | J82: 45513 | M82: =NETWORKDAYS(I82,J82) -> 44 | N82: =IF(K82="",0,NETWORKDAYS(I82,K82)) -> 0 | O82: =IF(L82="",0,NETWORKDAYS(I82,L82)) -> 0 | P82: Temp Hold | R82: Abhishek & Hitesh pending with Duc interview | S82: Andleeb
A83: =A82+1 -> 82 | B83: India | C83: Development | D83: PS | E83: Technology Lead | H83: Pune | I83: 45454 | J83: 45499 | M83: =NETWORKDAYS(I83,J83) -> 34 | N83: =IF(K83="",0,NETWORKDAYS(I83,K83)) -> 0 | O83: =IF(L83="",0,NETWORKDAYS(I83,L83)) -> 0 | P83: Temp Hold | R83: Bharath to confirm with Duc on the confirmation of hiring | S83: Andleeb
A84: =A83+1 -> 83 | B84: India | C84: Development | D84: FX | E84: Technology Lead | H84: Chennai | I84: 45454 | J84: 45512 | M84: =NETWORKDAYS(I84,J84) -> 43 | N84: =IF(K84="",0,NETWORKDAYS(I84,K84)) -> 0 | O84: =IF(L84="",0,NETWORKDAYS(I84,L84)) -> 0 | P84: Temp Hold | R84: Bharath to confirm with Duc on the confirmation of hiring | S84: Andleeb
A85: =A84+1 -> 84 | B85: India | C85: Development | D85: FX | E85: Technology Lead | H85: Chennai | I85: 45454 | J85: 45561 | M85: =NETWORKDAYS(I85,J85) -> 78 | N85: =IF(K85="",0,NETWORKDAYS(I85,K85)) -> 0 | O85: =IF(L85="",0,NETWORKDAYS(I85,L85)) -> 0 | P85: Temp Hold | R85: Bharath to confirm with Duc on the confirmation of hiring | S85: Andleeb
A86: =A85+1 -> 85 | B86: India | C86: Operations | D86: HR | E86: HR-Talent Acqusition | H86: Chennai | I86: 45464 | J86: 45471 | K86: 45471 | L86: 45475 | M86: =NETWORKDAYS(I86,J86) -> 6 | N86: =IF(K86="",0,NETWORKDAYS(I86,K86)) -> 6 | O86: =IF(L86="",0,NETWORKDAYS(I86,L86)) -> 8 | P86: Joined | R86: Thrukumaran offered, Tebtative joining 1st July
A87: =A86+1 -> 86 | B87: India | C87: Support | D87: Bank OS | E87: Production Support | H87: Pune | I87: 45483 | J87: 45513 | K87: 45513 | L87: 45523 | M87: =NETWORKDAYS(I87,J87) -> 23 | N87: =IF(K87="",0,NETWORKDAYS(I87,K87)) -> 23 | O87: =IF(L87="",0,NETWORKDAYS(I87,L87)) -> 29 | P87: Joined | R87: Piyush offer accepted, DOJ 19th August | S87: Andleeb
A88: =A87+1 -> 87 | B88: India | C88: Development | D88: PS | E88: Lead BA Analyst | H88: Pune | I88: 45467 | M88: =NETWORKDAYS(I88,J88) -> -32476 | N88: =IF(K88="",0,NETWORKDAYS(I88,K88)) -> 0 | O88: =IF(L88="",0,NETWORKDAYS(I88,L88)) -> 0 | P88: Temp Hold | R88: 2 candidates available, due to unavailablity of Nagesh, no action made | S88: Andleeb
A89: =A88+1 -> 88 | B89: India | C89: Product | D89: FX | E89: Product Owner | H89: Chennai/Pune | I89: 45513 | J89: 45611 | M89: =NETWORKDAYS(I89,J89) -> 71 | N89: =IF(K89="",0,NETWORKDAYS(I89,K89)) -> 0 | O89: =IF(L89="",0,NETWORKDAYS(I89,L89)) -> 0 | P89: Temp Hold | R89: Waiting for Vikas feedback | S89: Andleeb
A90: =A89+1 -> 89 | B90: India | C90: Program Manager | D90: PM | E90: Program Manager | H90: Chennai | I90: 45495 | J90: 45499 | K90: 45499 | L90: 45562 | M90: =NETWORKDAYS(I90,J90) -> 5 | N90: =IF(K90="",0,NETWORKDAYS(I90,K90)) -> 5 | O90: =IF(L90="",0,NETWORKDAYS(I90,L90)) -> 50 | P90: Joined | R90: Karthiga Joined, DOJ : 18th Sept | S90: Andleeb/Thiru
A91: =A90+1 -> 90 | B91: India | C91: Product | D91: Bank OS | E91: BA Lead | H91: Chennai | I91: 45502 | J91: 45512 | K91: 45512 | L91: 45530 | M91: =NETWORKDAYS(I91,J91) -> 9 | N91: =IF(K91="",0,NETWORKDAYS(I91,K91)) -> 9 | O91: =IF(L91="",0,NETWORKDAYS(I91,L91)) -> 21 | P91: Joined | R91: Prabu Joined, DOJ : 26th Aug | S91: Andleeb
A92: =A91+1 -> 91 | B92: India | C92: Product | D92: PS | E92: BA Lead | H92: Pune | I92: 45504 | J92: 45561 | K92: 45561 | L92: 45562 | M92: =NETWORKDAYS(I92,J92) -> 42 | N92: =IF(K92="",0,NETWORKDAYS(I92,K92)) -> 42 | O92: =IF(L92="",0,NETWORKDAYS(I92,L92)) -> 43 | P92: Joined | R92: Sarang Deshmukh - Joined on 27th Sept | S92: Thirukumaran
A93: =A92+1 -> 92 | B93: India | C93: Quality Assurance | D93: FX | E93: QA Analyst | H93: Chennai | I93: 45439 | J93: 45504 | K93: 45504 | L93: 45510 | M93: =NETWORKDAYS(I93,J93) -> 48 | N93: =IF(K93="",0,NETWORKDAYS(I93,K93)) -> 48 | O93: =IF(L93="",0,NETWORKDAYS(I93,L93)) -> 52 | P93: Joined | R93: Ilangumaran joined on 6th August 2024
A94: =A93+1 -> 93 | B94: India | C94: Quality Assurance | D94: PS | E94: Jr QA Analyst | F94: Replacement | H94: Pune | I94: 45588 | J94: =TODAY() -> 46324 | M94: =NETWORKDAYS(I94,J94) -> 527 | N94: =IF(K94="",0,NETWORKDAYS(I94,K94)) -> 0 | O94: =IF(L94="",0,NETWORKDAYS(I94,L94)) -> 0 | P94: Temp Hold | R94: interview in process | S94: Final Interview
A95: =A94+1 -> 94 | B95: India | C95: Engineering | D95: PS | E95: Senior Software Engineer | F95: Replacement | G95: Full-time | H95: Pune | I95: 45663 | J95: =TODAY() -> 46324 | M95: =NETWORKDAYS(I95,J95) -> 474 | N95: =IF(K95="",0,NETWORKDAYS(I95,K95)) -> 0 | O95: =IF(L95="",0,NETWORKDAYS(I95,L95)) -> 0 | P95: Suspended | R95: Akriti L2 (Shubhangi - Offer revoked) | S95: Andleeb
A96: =A95+1 -> 95 | B96: India | C96: Quality Assurance | D96: FX | E96: QA Analyst | F96: Replacement | H96: Chennai | I96: 45523 | J96: 45561 | K96: 45561 | L96: 45600 | M96: =NETWORKDAYS(I96,J96) -> 29 | N96: =IF(K96="",0,NETWORKDAYS(I96,K96)) -> 29 | O96: =IF(L96="",0,NETWORKDAYS(I96,L96)) -> 56 | P96: Joined | R96: Arun onboarded and joining us by 4th November | S96: Thirukumaran
A97: =A96+1 -> 96 | B97: India | C97: Product | D97: PS | E97: Senior BA | F97: New | H97: Pune | I97: 45547 | J97: =TODAY() -> 46324 | M97: =NETWORKDAYS(I97,J97) -> 556 | N97: =IF(K97="",0,NETWORKDAYS(I97,K97)) -> 0 | O97: =IF(L97="",0,NETWORKDAYS(I97,L97)) -> 0 | P97: Temp Hold | R97: Interview Panel Unavailability | S97: Thirukumaran
A98: =A97+1 -> 97 | B98: India | C98: Quality Assurance | D98: Bank OS | E98: Jr QA Analyst | H98: Pune | I98: 45534 | J98: 45588 | K98: 45588 | L98: 45588 | M98: =NETWORKDAYS(I98,J98) -> 39 | N98: =IF(K98="",0,NETWORKDAYS(I98,K98)) -> 39 | O98: =IF(L98="",0,NETWORKDAYS(I98,L98)) -> 39 | P98: Joined | R98: Santhosh Joined DOJ 23rd Oct | S98: Thirukumaran
A99: =A98+1 -> 98 | B99: India | C99: Engineering | D99: Bank OS | E99: Software Engineer | F99: New | G99: Full-time | H99: Pune | I99: 45790 | J99: 45817 | K99: 45817 | L99: 45820 | M99: =NETWORKDAYS(I99,J99) -> 20 | N99: =IF(K99="",0,NETWORKDAYS(I99,K99)) -> 20 | O99: =IF(L99="",0,NETWORKDAYS(I99,L99)) -> 23 | P99: Joined | Q99: Nitin K | R99: Nithin Joined (DOJ 12th June) | S99: Thirukumaran | T99: (Arnav Biswas Declined / Vijay Pal - Declined - Better compensation & flexible working (Azhar high ctc), Alok Ranjan backed out | U99: (Arnav Biswas Declined / Vijay Pal - Declined - Better compensation & flexible working (Azhar high ctc), Alok Ranjan backed out
A100: =A99+1 -> 99 | B100: India | C100: Engineering | D100: Bank OS | E100: Software Engineer | F100: New | G100: Full-time | H100: Pune | I100: 45677 | J100: 45758 | K100: 45758 | L100: 45768 | M100: =NETWORKDAYS(I100,J100) -> 60 | N100: =IF(K100="",0,NETWORKDAYS(I100,K100)) -> 60 | O100: =IF(L100="",0,NETWORKDAYS(I100,L100)) -> 66 | P100: Joined | Q100: Bhavik P | R100: Bhavik (DOJ 21st April) | S100: Thirukumaran
...

Sheet Master 2026
A1: Sr No | B1: Geo | C1: Department | D1: Squads | E1: Positions | F1: Dept Head | G1: New/Replacement | H1: Replaced Employee Name | I1: Full-Time/Consultant | J1: Hiring Location | K1: Position Open Date | L1: Todays Date | M1: Date Offered | N1: Joining Date | O1: Quarter Joining | P1: Aging (Days) | Q1: Position Offered | R1: Position Closed | S1: Status | T1: Offered Candidates | U1: Highest Qualification Degree | V1: Applied/ Sourced/ Reffered (Internal/External) | W1: RAG Status | X1: Back-up Plans | Y1: Buddy - Onboarding | Z1: Comments | AA1: Recruiter
A2: 1 | B2: India | C2: Product | D2: Account | E2: Product Manager | F2: Ashok | G2: Replacement | H2: Bhargav/Mahesh | I2: Full-time | J2: Chennai | K2: 45938 | L2: 45975 | M2: 45975 | N2: 46090 | P2: =NETWORKDAYS(K2,L2) -> 28 | Q2: =IF(M2="",0,NETWORKDAYS(K2,M2)) -> 28 | R2: =IF(N2="",0,NETWORKDAYS(K2,N2)) -> 109 | S2: Suspended | Z2: Narsimha Leela Krishna - Backedout | AA2: Thirukumaran
A3: 2 | B3: USA | C3: Infosec | D3: Infosec | E3: CISO (Change of Role) | F3: Murthy | G3: Replacement | H3: Nate | I3: Full-time | J3: Charlotte | K3: 45982 | L3: 46055 | M3: 46045 | N3: 46055 | O3: ="Q"&INT((MONTH(N3)-1)/3)+1 -> Q1 | P3: =NETWORKDAYS(K3,L3) -> 52 | Q3: =IF(M3="",0,NETWORKDAYS(K3,M3)) -> 46 | R3: =IF(N3="",0,NETWORKDAYS(K3,N3)) -> 52 | S3: Joined | T3: Supro | Z3: Eric Garcia decided to reject the offer on October 1, 2025. | AA3: Marissa
A4: 3 | B4: USA | C4: Product | D4: Payments | E4: Product Owner (Change of Role) | F4: Vijay | G4: New | I4: Full-time | J4: Charlotte | K4: 45895 | L4: 46042 | M4: 46003 | N4: 46042 | O4: ="Q"&INT((MONTH(N4)-1)/3)+1 -> Q1 | P4: =NETWORKDAYS(K4,L4) -> 106 | Q4: =IF(M4="",0,NETWORKDAYS(K4,M4)) -> 79 | R4: =IF(N4="",0,NETWORKDAYS(K4,N4)) -> 106 | S4: Joined | T4: Melissa | Z4: Melissa will join in January 12, 2025 | AA4: Marissa
A5: 4 | B5: USA | C5: Engineering | D5: Payments | E5: Enterprise Architect | F5: Murthy | G5: New | H5: N/A | I5: Full-time | J5: Charlotte | K5: 46024 | L5: 46132 | M5: 46105 | N5: 46132 | O5: ="Q"&INT((MONTH(N5)-1)/3)+1 -> Q2 | P5: =NETWORKDAYS(K5,L5) -> 77 | Q5: =IF(M5="",0,NETWORKDAYS(K5,M5)) -> 58 | R5: =IF(N5="",0,NETWORKDAYS(K5,N5)) -> 77 | S5: Joined | T5: Lakshminarayan | AA5: Andleeb
A6: 5 | B6: India | C6: Engineering | D6: Payments | E6: Senior Software Engineer | F6: Vinay | G6: Replacement | H6: Revanth | I6: Full-time | J6: Chennai | K6: 45958 | L6: 46003 | M6: 46003 | N6: 46042 | O6: ="Q"&INT((MONTH(N6)-1)/3)+1 -> Q1 | P6: =NETWORKDAYS(K6,L6) -> 34 | Q6: =IF(M6="",0,NETWORKDAYS(K6,M6)) -> 34 | R6: =IF(N6="",0,NETWORKDAYS(K6,N6)) -> 61 | S6: Joined | T6: Srinivasan | V6: Internal | AA6: Thirukumaran
A7: 6 | B7: India | C7: DevOps | D7: DevOps | E7: DevOps Engineer | F7: Prathap | G7: New | I7: Full-time | J7: Chennai | K7: 46024 | L7: 46085 | M7: 46085 | N7: 46086 | O7: ="Q"&INT((MONTH(N7)-1)/3)+1 -> Q1 | P7: =NETWORKDAYS(K7,L7) -> 44 | Q7: =IF(M7="",0,NETWORKDAYS(K7,M7)) -> 44 | R7: =IF(N7="",0,NETWORKDAYS(K7,N7)) -> 45 | S7: Joined | T7: Senthil R | V7: Internal | AA7: Andleeb
A8: 7 | B8: India | C8: DevOps | D8: DevOps | E8: Senior DevOps Engineer | F8: Prathap | G8: New | I8: Full-time | J8: Pune | K8: 46214 | L8: =TODAY() -> 46324 | P8: =NETWORKDAYS(K8,L8) -> 79 | Q8: =IF(M8="",0,NETWORKDAYS(K8,M8)) -> 0 | R8: =IF(N8="",0,NETWORKDAYS(K8,N8)) -> 0 | S8: Suspended | Z8: Role changed to IT Admin (email from Aarthie) | AA8: Andleeb/Thirukumaran
A9: 8 | B9: India | C9: QA | D9: Payments | E9: Performance Tester | F9: Divya | G9: Replacement | H9: Mageshkumar | I9: Full-time | J9: Chennai | K9: 46028 | L9: 46031 | M9: 46031 | N9: 46041 | O9: ="Q"&INT((MONTH(N9)-1)/3)+1 -> Q1 | P9: =NETWORKDAYS(K9,L9) -> 4 | Q9: =IF(M9="",0,NETWORKDAYS(K9,M9)) -> 4 | R9: =IF(N9="",0,NETWORKDAYS(K9,N9)) -> 10 | S9: Joined | T9: Pavithra Devi | V9: Internal | Z9: Pavithra Devi early attrition | AA9: Andleeb
A10: 9 | B10: India | C10: Engineering | D10: PS | E10: Senior Software Engineer | F10: Kanan | G10: Replacement | H10: Nikhilesh | I10: Consultant | J10: Pune | K10: 45945 | L10: 46094 | M10: 46094 | N10: 46104 | O10: ="Q"&INT((MONTH(N10)-1)/3)+1 -> Q1 | P10: =NETWORKDAYS(K10,L10) -> 108 | Q10: =IF(M10="",0,NETWORKDAYS(K10,M10)) -> 108 | R10: =IF(N10="",0,NETWORKDAYS(K10,N10)) -> 114 | S10: Joined | T10: Uttkarsh | V10: External | AA10: Vendor / Andleeb
A11: 10 | B11: USA | C11: DevOps | D11: DevOps | E11: Director of Infrastructure | F11: Murthy | G11: New | I11: Full-time | J11: Charlotte | K11: 45965 | L11: 46057 | M11: 46042 | N11: 46057 | O11: ="Q"&INT((MONTH(N11)-1)/3)+1 -> Q1 | P11: =NETWORKDAYS(K11,L11) -> 67 | Q11: =IF(M11="",0,NETWORKDAYS(K11,M11)) -> 56 | R11: =IF(N11="",0,NETWORKDAYS(K11,N11)) -> 67 | S11: Joined | T11: Manoj | AA11: Marissa
A12: 11 | B12: USA | C12: DevOps | D12: DevOps | E12: SecOps - Enterprise Governance | F12: Murthy | G12: New | I12: Full-time | J12: Charlotte | K12: 45966 | L12: =TODAY() -> 46324 | P12: =NETWORKDAYS(K12,L12) -> 257 | Q12: =IF(M12="",0,NETWORKDAYS(K12,M12)) -> 0 | R12: =IF(N12="",0,NETWORKDAYS(K12,N12)) -> 0 | S12: Suspended | Z12: Murthy asked to temp hold the req until the clarity on business need | AA12: Andleeb
A13: 12 | B13: USA | C13: Engineering | D13: Account | E13: Java Architect | F13: Ashok | G13: New | I13: Full-time | J13: Charlotte | K13: 45979 | L13: 46129 | M13: 46076 | N13: 46129 | O13: ="Q"&INT((MONTH(N13)-1)/3)+1 -> Q2 | P13: =NETWORKDAYS(K13,L13) -> 109 | Q13: =IF(M13="",0,NETWORKDAYS(K13,M13)) -> 70 | R13: =IF(N13="",0,NETWORKDAYS(K13,N13)) -> 109 | S13: Joined | T13: Esther M | AA13: Marissa
A14: 13 | B14: India | C14: Engineering | D14: Trade | E14: Software Engineer | F14: Raju | G14: Replacement | H14: Manikandan S | I14: Full-time | J14: Chennai | K14: 46024 | L14: 46057 | M14: 46057 | N14: 46146 | O14: ="Q"&INT((MONTH(N14)-1)/3)+1 -> Q2 | P14: =NETWORKDAYS(K14,L14) -> 24 | Q14: =IF(M14="",0,NETWORKDAYS(K14,M14)) -> 24 | R14: =IF(N14="",0,NETWORKDAYS(K14,N14)) -> 87 | S14: Joined | T14: Sridharan | V14: Internal | Z14: Sridharan - Backup / Manikandan Resigned | AA14: Thirukumaran
A15: 14 | B15: USA | C15: Finance | D15: Finance | E15: Chief Finance Officer | F15: Booshan | G15: Replacement | H15: Adam | I15: Full-time | J15: Charlotte | K15: 46009 | L15: =TODAY() -> 46324 | M15: 46283 | N15: 46314 | P15: =NETWORKDAYS(K15,L15) -> 226 | Q15: =IF(M15="",0,NETWORKDAYS(K15,M15)) -> 197 | R15: =IF(N15="",0,NETWORKDAYS(K15,N15)) -> 218 | S15: Joined | T15: Jack McCullen | AA15: TPZ
A16: 15 | B16: India | C16: Engineering | D16: Trade | E16: Software Engineer | F16: Raju | G16: Replacement | H16: Ambikeshwari | I16: Full-time | J16: Chennai | K16: 46015 | L16: 46107 | M16: 46107 | N16: 46108 | O16: ="Q"&INT((MONTH(N16)-1)/3)+1 -> Q1 | P16: =NETWORKDAYS(K16,L16) -> 67 | Q16: =IF(M16="",0,NETWORKDAYS(K16,M16)) -> 67 | R16: =IF(N16="",0,NETWORKDAYS(K16,N16)) -> 68 | S16: Joined | T16: Elumalai | V16: Internal | Z16: Ambikeshwari Resigned | AA16: Thirukumaran
A17: 16 | B17: USA | C17: Sales | D17: Sales | E17: VP of PreSales and Solution Consulting | F17: Karuna | G17: New | I17: Full-time | J17: USA-Remote | K17: 46003 | L17: 46062 | M17: 46014 | N17: 46062 | O17: ="Q"&INT((MONTH(N17)-1)/3)+1 -> Q1 | P17: =NETWORKDAYS(K17,L17) -> 42 | Q17: =IF(M17="",0,NETWORKDAYS(K17,M17)) -> 8 | R17: =IF(N17="",0,NETWORKDAYS(K17,N17)) -> 42 | S17: Joined | T17: Romil | AA17: Marissa
A18: 17 | B18: USA | C18: Sales | D18: Sales | E18: VP of Sales - Payments | F18: Karuna | G18: New | I18: Full-time | J18: USA-Remote | K18: 45981 | L18: 46031 | M18: 46015 | N18: 46031 | O18: ="Q"&INT((MONTH(N18)-1)/3)+1 -> Q1 | P18: =NETWORKDAYS(K18,L18) -> 37 | Q18: =IF(M18="",0,NETWORKDAYS(K18,M18)) -> 25 | R18: =IF(N18="",0,NETWORKDAYS(K18,N18)) -> 37 | S18: Joined | T18: Randy | AA18: Marissa
A19: 18 | B19: India | C19: HR | D19: HR | E19: HR Executive (HRBP) | F19: Bharath | G19: Replacement | H19: Baskaran D | I19: Full-time | J19: Chennai | K19: 46013 | L19: =TODAY() -> 46324 | M19: 46047 | N19: 46050 | O19: ="Q"&INT((MONTH(N19)-1)/3)+1 -> Q1 | P19: =NETWORKDAYS(K19,L19) -> 224 | Q19: =IF(M19="",0,NETWORKDAYS(K19,M19)) -> 25 | R19: =IF(N19="",0,NETWORKDAYS(K19,N19)) -> 28 | S19: Joined | T19: Janani | V19: Internal | AA19: Andleeb
A20: 19 | B20: India | C20: HR | D20: HR | E20: HR Ops | F20: Bharath | G20: Replacement | H20: Baskaran D | I20: Full-time | J20: Chennai | K20: 46013 | L20: =TODAY() -> 46324 | M20: 46041 | N20: 46042 | O20: ="Q"&INT((MONTH(N20)-1)/3)+1 -> Q1 | P20: =NETWORKDAYS(K20,L20) -> 224 | Q20: =IF(M20="",0,NETWORKDAYS(K20,M20)) -> 21 | R20: =IF(N20="",0,NETWORKDAYS(K20,N20)) -> 22 | S20: Joined | T20: Abirami R | V20: Internal | AA20: Andleeb
A21: 20 | B21: India | C21: QA | D21: PS | E21: Quality Analyst (C2H) | F21: Kanan | G21: Replacement | H21: Vineet K | I21: Consultant | J21: Pune | K21: 46024 | L21: =TODAY() -> 46324 | M21: 46038 | N21: 46055 | O21: ="Q"&INT((MONTH(N21)-1)/3)+1 -> Q1 | P21: =NETWORKDAYS(K21,L21) -> 215 | Q21: =IF(M21="",0,NETWORKDAYS(K21,M21)) -> 11 | R21: =IF(N21="",0,NETWORKDAYS(K21,N21)) -> 22 | S21: Joined | T21: Shubhankar | V21: External | Z21: DOJ Feb 4 - by Synechron | AA21: Vendor
A22: 21 | B22: India | C22: Engineering | D22: Payments | E22: Software Engineer (Rust) | F22: Prashant | G22: Replacement | H22: Ganesh | I22: Full-time | J22: Pune | K22: 46034 | L22: 46052 | M22: 46052 | N22: 46058 | O22: ="Q"&INT((MONTH(N22)-1)/3)+1 -> Q1 | P22: =NETWORKDAYS(K22,L22) -> 15 | Q22: =IF(M22="",0,NETWORKDAYS(K22,M22)) -> 15 | R22: =IF(N22="",0,NETWORKDAYS(K22,N22)) -> 19 | S22: Joined | T22: Anil P | V22: Internal | AA22: Andleeb
A23: 22 | B23: India | C23: Product | D23: Account | E23: Product Manager - VA | F23: Ashok | G23: New | I23: Full-time | J23: Pune | K23: 46024 | L23: 46049 | M23: 46049 | N23: 46140 | O23: ="Q"&INT((MONTH(N23)-1)/3)+1 -> Q2 | P23: =NETWORKDAYS(K23,L23) -> 18 | Q23: =IF(M23="",0,NETWORKDAYS(K23,M23)) -> 18 | R23: =IF(N23="",0,NETWORKDAYS(K23,N23)) -> 83 | S23: Joined | T23: Dhawal | V23: Internal | AA23: Thirukumaran
A24: 23 | B24: India | C24: QA | D24: Account | E24: QA Analyst | F24: Ashok | G24: New | I24: Full-time | J24: Chennai | K24: 46043 | L24: 46052 | M24: 46052 | N24: 46093 | O24: ="Q"&INT((MONTH(N24)-1)/3)+1 -> Q1 | P24: =NETWORKDAYS(K24,L24) -> 8 | Q24: =IF(M24="",0,NETWORKDAYS(K24,M24)) -> 8 | R24: =IF(N24="",0,NETWORKDAYS(K24,N24)) -> 37 | S24: Joined | T24: Nikhil C Karanam | V24: Internal | Z24: Nikhil early attrition | AA24: Thirukumaran
A25: 24 | B25: India | C25: QA | D25: Account | E25: QA Analyst | F25: Ashok | G25: New | I25: Full-time | J25: Chennai | K25: 46043 | L25: 46057 | M25: 46057 | N25: 46083 | O25: ="Q"&INT((MONTH(N25)-1)/3)+1 -> Q1 | P25: =NETWORKDAYS(K25,L25) -> 11 | Q25: =IF(M25="",0,NETWORKDAYS(K25,M25)) -> 11 | R25: =IF(N25="",0,NETWORKDAYS(K25,N25)) -> 29 | S25: Joined | T25: Keerthika | V25: Internal | AA25: Thirukumaran
A26: 25 | B26: India | C26: Product | D26: Payments | E26: Payment Owner | F26: Kasi | G26: Replacement | H26: Ravikumar Kasi | I26: Full-time | J26: Chennai | K26: 46043 | L26: 46052 | M26: 46052 | N26: 46077 | O26: ="Q"&INT((MONTH(N26)-1)/3)+1 -> Q1 | P26: =NETWORKDAYS(K26,L26) -> 8 | Q26: =IF(M26="",0,NETWORKDAYS(K26,M26)) -> 8 | R26: =IF(N26="",0,NETWORKDAYS(K26,N26)) -> 25 | S26: Joined | T26: Ganesh | V26: Internal | Z26: Sujata on hold | AA26: Andleeb
A27: 26 | B27: India | C27: Prod Support | D27: Support | E27: Production Support Engineer (FX) | F27: Mark D | G27: New | I27: Full-time | J27: India-Remote | K27: 46043 | L27: =TODAY() -> 46324 | M27: 46052 | N27: 46058 | O27: ="Q"&INT((MONTH(N27)-1)/3)+1 -> Q1 | P27: =NETWORKDAYS(K27,L27) -> 202 | Q27: =IF(M27="",0,NETWORKDAYS(K27,M27)) -> 8 | R27: =IF(N27="",0,NETWORKDAYS(K27,N27)) -> 12 | S27: Joined | T27: Krishnaprasad | V27: Emp Ref | AA27: Andleeb
A28: 27 | B28: India | C28: BA | D28: PS | E28: Business Analyst | F28: Kanan | G28: New | I28: Full-time | J28: Pune | K28: 46049 | L28: 46057 | M28: 46057 | N28: 46122 | O28: ="Q"&INT((MONTH(N28)-1)/3)+1 -> Q2 | P28: =NETWORKDAYS(K28,L28) -> 7 | Q28: =IF(M28="",0,NETWORKDAYS(K28,M28)) -> 7 | R28: =IF(N28="",0,NETWORKDAYS(K28,N28)) -> 54 | S28: Joined | T28: Niraj T | V28: Emp Ref | AA28: Andleeb
A29: 28 | B29: India | C29: Legal | D29: Support | E29: India Legal Assistant supporting US | F29: Hardik | G29: New | I29: Full-time | J29: India-Remote | K29: 46049 | L29: =TODAY() -> 46324 | M29: 46064 | N29: 46070 | O29: ="Q"&INT((MONTH(N29)-1)/3)+1 -> Q1 | P29: =NETWORKDAYS(K29,L29) -> 198 | Q29: =IF(M29="",0,NETWORKDAYS(K29,M29)) -> 12 | R29: =IF(N29="",0,NETWORKDAYS(K29,N29)) -> 16 | S29: Joined | T29: Uzma Sohail | V29: Emp Ref | AA29: Thirukumaran
A30: 29 | B30: India | C30: Product | D30: Digital | E30: Product Manager- DGx & OpenAPI | F30: Sajeesh | G30: New | I30: Full-time | J30: Pune | K30: 46064 | L30: =TODAY() -> 46324 | N30: 46091 | O30: ="Q"&INT((MONTH(N30)-1)/3)+1 -> Q1 | P30: =NETWORKDAYS(K30,L30) -> 187 | Q30: =IF(M30="",0,NETWORKDAYS(K30,M30)) -> 0 | R30: =IF(N30="",0,NETWORKDAYS(K30,N30)) -> 20 | S30: Joined | T30: Alice Marks | V30: Internal | AA30: Thirukumaran
A31: 30 | B31: India | C31: Engineering | D31: Digital | E31: Full-stack Engineer | F31: Sajeesh | G31: New | I31: Full-time | J31: Pune | K31: 46064 | L31: 46085 | M31: 46085 | N31: 46107 | O31: ="Q"&INT((MONTH(N31)-1)/3)+1 -> Q1 | P31: =NETWORKDAYS(K31,L31) -> 16 | Q31: =IF(M31="",0,NETWORKDAYS(K31,M31)) -> 16 | R31: =IF(N31="",0,NETWORKDAYS(K31,N31)) -> 32 | S31: Joined | T31: Omkar Chavan | V31: Internal | AA31: Thirukumaran
A32: 31 | B32: India | C32: BA | D32: Trade | E32: BA- FX | F32: Patrick | G32: New | I32: Full-time | J32: Chennai | K32: 46144 | L32: 46175 | M32: 46174 | N32: 46175 | O32: ="Q"&INT((MONTH(N32)-1)/3)+1 -> Q2 | P32: =NETWORKDAYS(K32,L32) -> 22 | Q32: =IF(M32="",0,NETWORKDAYS(K32,M32)) -> 21 | R32: =IF(N32="",0,NETWORKDAYS(K32,N32)) -> 22 | S32: Joined | T32: Muthu Meenakshi | V32: External | AA32: Thirukumaran
A33: 32 | B33: India | C33: BA | D33: Trade | E33: Business Analyst - IRD | F33: Patrick | G33: New | I33: Full-time | J33: Chennai | K33: 46144 | L33: 46190 | M33: 46190 | N33: 46283 | O33: ="Q"&INT((MONTH(N33)-1)/3)+1 -> Q3 | P33: =NETWORKDAYS(K33,L33) -> 33 | Q33: =IF(M33="",0,NETWORKDAYS(K33,M33)) -> 33 | R33: =IF(N33="",0,NETWORKDAYS(K33,N33)) -> 100 | S33: Joined | T33: Kishore | V33: Internal | W33: Amber | X33: Initial Interview | Y33: Karthikeyan | Z33: Kishore accpeted our offer | AA33: Thirukumaran
A34: 33 | B34: India | C34: Engineering | D34: Account | E34: Full-stack Engineer | F34: Ashok | G34: New | I34: Full-time | J34: Chennai | K34: 46064 | L34: 46141 | M34: 46141 | N34: 46162 | O34: ="Q"&INT((MONTH(N34)-1)/3)+1 -> Q2 | P34: =NETWORKDAYS(K34,L34) -> 56 | Q34: =IF(M34="",0,NETWORKDAYS(K34,M34)) -> 56 | R34: =IF(N34="",0,NETWORKDAYS(K34,N34)) -> 71 | S34: Joined | T34: Kalirajan | V34: Emp Ref | Z34: Sivakumar Backedout | AA34: Thirukumaran
A35: 34 | B35: India | C35: Program | D35: Payments | E35: Project Manager | F35: Ramesh | G35: New | I35: Full-time | J35: Pune | K35: 46055 | L35: 46210 | M35: 46210 | N35: 46232 | O35: ="Q"&INT((MONTH(N35)-1)/3)+1 -> Q3 | P35: =NETWORKDAYS(K35,L35) -> 112 | Q35: =IF(M35="",0,NETWORKDAYS(K35,M35)) -> 112 | R35: =IF(N35="",0,NETWORKDAYS(K35,N35)) -> 128 | S35: Joined | T35: Naveen Kulkarni | V35: Emp Ref | W35: Green | X35: Initial Interview | Y35: Amit Kulkarni | Z35: Naveen accepted our offered | AA35: Andleeb
A36: 35 | B36: India | C36: DevOps | D36: DevOps | E36: DevOps Engineer | F36: Prathap | G36: New | I36: Full-time | J36: Pune | K36: 46144 | L36: 46184 | M36: 46184 | N36: 46188 | O36: ="Q"&INT((MONTH(N36)-1)/3)+1 -> Q2 | P36: =NETWORKDAYS(K36,L36) -> 29 | Q36: =IF(M36="",0,NETWORKDAYS(K36,M36)) -> 29 | R36: =IF(N36="",0,NETWORKDAYS(K36,N36)) -> 31 | S36: Joined | T36: Faheem | V36: Internal | AA36: Andleeb
A37: 36 | B37: India | C37: DevOps | D37: DevOps | E37: DevOps Engineer | F37: Prathap | G37: New | I37: Full-time | J37: Chennai | K37: 46144 | L37: 46178 | M37: 46178 | N37: 46181 | O37: ="Q"&INT((MONTH(N37)-1)/3)+1 -> Q2 | P37: =NETWORKDAYS(K37,L37) -> 25 | Q37: =IF(M37="",0,NETWORKDAYS(K37,M37)) -> 25 | R37: =IF(N37="",0,NETWORKDAYS(K37,N37)) -> 26 | S37: Joined | T37: Deepakraj J | V37: Internal | AA37: Thirukumaran
A38: 37 | B38: India | C38: Infosec | D38: Infosec | E38: InfoSec Security Analyst | F38: Supro | G38: New | I38: Full-time | J38: Pune | K38: 46110 | L38: 46206 | M38: 46206 | N38: 46211 | O38: ="Q"&INT((MONTH(N38)-1)/3)+1 -> Q3 | P38: =NETWORKDAYS(K38,L38) -> 70 | Q38: =IF(M38="",0,NETWORKDAYS(K38,M38)) -> 70 | R38: =IF(N38="",0,NETWORKDAYS(K38,N38)) -> 73 | S38: Joined | T38: Rajesh | V38: Internal | W38: Green | X38: Sourcing | Z38: Swapnil/Gauresh / Nitesh declined our offer. Supro referral is looking remote | AA38: Andleeb
A39: 38 | B39: India | C39: Infosec | D39: Infosec | E39: InfoSec Audit & Compliance Engineer | F39: Supro | G39: New | I39: Full-time | J39: Pune | K39: 46064 | L39: 46105 | M39: 46105 | N39: 46106 | O39: ="Q"&INT((MONTH(N39)-1)/3)+1 -> Q1 | P39: =NETWORKDAYS(K39,L39) -> 30 | Q39: =IF(M39="",0,NETWORKDAYS(K39,M39)) -> 30 | R39: =IF(N39="",0,NETWORKDAYS(K39,N39)) -> 31 | S39: Joined | T39: Sayyed Karim | V39: Internal | AA39: Andleeb
A40: 39 | B40: India | C40: Program | D40: Payments | E40: Scrum Master | F40: Vijay | G40: Replacement | H40: Saravanan T | I40: Full-time | J40: Pune | K40: 46063 | L40: =TODAY() -> 46324 | N40: 46086 | O40: ="Q"&INT((MONTH(N40)-1)/3)+1 -> Q1 | P40: =NETWORKDAYS(K40,L40) -> 188 | Q40: =IF(M40="",0,NETWORKDAYS(K40,M40)) -> 0 | R40: =IF(N40="",0,NETWORKDAYS(K40,N40)) -> 18 | S40: Joined | T40: Amit KS | V40: Internal | AA40: Andleeb
A41: 40 | B41: India | C41: QA | D41: Payments | E41: Senior QA Analyst | F41: Vijay | G41: New | I41: Full-time | J41: Chennai | K41: 46063 | L41: 46107 | M41: 46107 | N41: 46108 | O41: ="Q"&INT((MONTH(N41)-1)/3)+1 -> Q1 | P41: =NETWORKDAYS(K41,L41) -> 33 | Q41: =IF(M41="",0,NETWORKDAYS(K41,M41)) -> 33 | R41: =IF(N41="",0,NETWORKDAYS(K41,N41)) -> 34 | S41: Joined | T41: Abinaya D | V41: Internal | AA41: Andleeb
A42: 41 | B42: India | C42: Engineering | D42: Payments | E42: Senior/Lead Engineer | F42: Vijay | G42: New | I42: Consultant | J42: Pune | K42: 46104 | L42: 46153 | M42: 46153 | N42: 46156 | O42: ="Q"&INT((MONTH(N42)-1)/3)+1 -> Q2 | P42: =NETWORKDAYS(K42,L42) -> 36 | Q42: =IF(M43="",0,NETWORKDAYS(K42,M43)) -> 23 | R42: =IF(N43="",0,NETWORKDAYS(K42,N43)) -> 25 | S42: Joined | T42: Prachi | V42: External
A43: 42 | B43: India | C43: Engineering | D43: Payments | E43: Senior/Lead Engineer | F43: Vijay | G43: New | I43: Full-time | J43: Pune | K43: 46104 | L43: 46134 | M43: 46134 | N43: 46136 | O43: ="Q"&INT((MONTH(N43)-1)/3)+1 -> Q2 | P43: =NETWORKDAYS(K43,L43) -> 23 | Q43: =IF(M44="",0,NETWORKDAYS(K43,M44)) -> 0 | R43: =IF(N44="",0,NETWORKDAYS(K43,N44)) -> 0 | S43: Joined | T43: Mani Prathap | V43: Internal | AA43: Andleeb
A44: 43 | B44: India | C44: HR | D44: HR | E44: Senior HR Executive | F44: Bharath | G44: Replacement | H44: Janani | I44: Full-time | J44: Chennai | K44: 46112 | L44: =TODAY() -> 46324 | P44: =NETWORKDAYS(K44,L44) -> 153 | Q44: =IF(M44="",0,NETWORKDAYS(K44,M44)) -> 0 | R44: =IF(N44="",0,NETWORKDAYS(K44,N44)) -> 0 | S44: Suspended | T44: Keerthivasan | AA44: Andleeb
A45: 44 | B45: India | C45: Engineering | D45: Digital | E45: Open API Developer | F45: Sajeesh | G45: New | I45: Full-time | J45: Chennai | K45: 46069 | L45: 46108 | M45: 46108 | N45: 46114 | O45: ="Q"&INT((MONTH(N45)-1)/3)+1 -> Q2 | P45: =NETWORKDAYS(K45,L45) -> 30 | Q45: =IF(M45="",0,NETWORKDAYS(K45,M45)) -> 30 | R45: =IF(N45="",0,NETWORKDAYS(K45,N45)) -> 34 | S45: Joined | T45: Ramya | V45: Internal | AA45: Thirukumaran
A46: 45 | B46: India | C46: Infosec | D46: Infosec | E46: System Monitoring Engineer | F46: Supro | G46: New | I46: Full-time | L46: =TODAY() -> 46324 | S46: Suspended | Z46: Supro has hold the req
A47: 46 | B47: India | C47: Engineering | D47: Payments | E47: Solution Architect | F47: Vijay | G47: New | I47: Full-time | J47: Pune | K47: 46104 | L47: 46148 | M47: 46148 | N47: 46149 | O47: ="Q"&INT((MONTH(N47)-1)/3)+1 -> Q2 | P47: =NETWORKDAYS(K47,L47) -> 33 | Q47: =IF(M47="",0,NETWORKDAYS(K47,M47)) -> 33 | R47: =IF(N47="",0,NETWORKDAYS(K47,N47)) -> 34 | S47: Joined | T47: Shankar Gaikwad | V47: Internal | AA47: Andleeb
A48: 47 | B48: India | C48: BA | D48: PS | E48: Sr.Business Analyst | F48: Kanan | G48: Replacement | H48: Jaspreet | I48: Full-time | J48: Pune | K48: 46083 | L48: 46223 | M48: 46223 | N48: 46295 | P48: =NETWORKDAYS(K48,L48) -> 101 | Q48: =IF(M48="",0,NETWORKDAYS(K48,M48)) -> 101 | R48: =IF(N48="",0,NETWORKDAYS(K48,N48)) -> 153 | S48: Internal Movement | T48: Dhawal | V48: Linkedin | W48: Green | X48: Sourcing | Y48: Prabu | Z48: Dhawal moved to PS team / Yasar Declined (30 -sept DOJ) | AA48: Andleeb/Thirukumaran
A49: 48 | B49: India | C49: Prod Support | D49: Support | E49: Wire Support Sr | F49: Mark D | G49: New | I49: Full-time | J49: India-Remote | K49: 46090 | L49: =TODAY() -> 46324 | M49: 46136 | N49: 46153 | O49: ="Q"&INT((MONTH(N49)-1)/3)+1 -> Q2 | P49: =NETWORKDAYS(K49,L49) -> 169 | Q49: =IF(M49="",0,NETWORKDAYS(K49,M49)) -> 35 | R49: =IF(N49="",0,NETWORKDAYS(K49,N49)) -> 46 | S49: Joined | T49: Yasar | V49: Emp Ref
A50: 49 | B50: India | C50: Prod Support | D50: Support | E50: Instant Payment Support Sr | F50: Mark D | G50: New | I50: Full-time | J50: India-Remote | K50: 46090 | L50: =TODAY() -> 46324 | M50: 46136 | N50: 46141 | O50: ="Q"&INT((MONTH(N50)-1)/3)+1 -> Q2 | P50: =NETWORKDAYS(K50,L50) -> 169 | Q50: =IF(M50="",0,NETWORKDAYS(K50,M50)) -> 35 | R50: =IF(N50="",0,NETWORKDAYS(K50,N50)) -> 38 | S50: Joined | T50: Prince | V50: Internal
A51: 50 | B51: USA | C51: Engineering | D51: Payments | E51: Lead Software Engineer - ACH | F51: Vijay | G51: New | I51: Full-time | J51: Charlotte | K51: 46069 | L51: 46224 | M51: 46149 | N51: 46224 | O51: ="Q"&INT((MONTH(N51)-1)/3)+1 -> Q3 | P51: =NETWORKDAYS(K51,L51) -> 112 | Q51: =IF(M51="",0,NETWORKDAYS(K51,M51)) -> 59 | R51: =IF(N51="",0,NETWORKDAYS(K51,N51)) -> 112 | S51: Joined | T51: Alka Lakhote | Z51: H-1B approved, waiting on candidate to confirm start date. | AA51: Sindhu
A52: 51 | B52: USA | C52: Engineering | D52: Digital | E52: Full Stack Developer | F52: Sajeesh | G52: New | I52: Full-time | J52: Charlotte | K52: 46064 | L52: =TODAY() -> 46324 | P52: =NETWORKDAYS(K52,L52) -> 187 | Q52: =IF(M52="",0,NETWORKDAYS(K52,M52)) -> 0 | R52: =IF(N52="",0,NETWORKDAYS(K52,N52)) -> 0 | S52: L1 Process | T52: Anupam Babar
A53: 52 | B53: USA | C53: Product | D53: PS | E53: Business Analyst- ACH | F53: Kanan | G53: New | I53: Consultant | J53: Charlotte | K53: 46056 | L53: 46066 | N53: 46066 | O53: ="Q"&INT((MONTH(N53)-1)/3)+1 -> Q1 | P53: =NETWORKDAYS(K53,L53) -> 9 | Q53: =IF(M53="",0,NETWORKDAYS(K53,M53)) -> 0 | R53: =IF(N53="",0,NETWORKDAYS(K53,N53)) -> 9 | S53: Joined | T53: Ramona Brown | AA53: Marissa
A54: 53 | B54: USA | C54: Product | D54: PS | E54: Developer | F54: Kanan | G54: New | I54: Consultant | J54: Charlotte | N54: 46070 | O54: ="Q"&INT((MONTH(N54)-1)/3)+1 -> Q1 | S54: Joined | T54: Narendra Kumar | AA54: Marissa
A55: 54 | B55: USA | C55: Product | D55: PS | E55: Project Manager | F55: Kanan | G55: New | I55: Consultant | J55: Charlotte | N55: 46076 | O55: ="Q"&INT((MONTH(N55)-1)/3)+1 -> Q1 | P55: =NETWORKDAYS(K55,L55) -> 0 | Q55: =IF(M55="",0,NETWORKDAYS(K55,M55)) -> 0 | R55: =IF(N55="",0,NETWORKDAYS(K55,N55)) -> 32911 | S55: Joined | T55: Sagarika B | AA55: Marissa
A56: 55 | B56: USA | C56: Production Support | D56: Support | E56: ACH Support | F56: Mark D | G56: New | I56: Full-time | J56: Charlotte | K56: 46083 | L56: 46190 | M56: 46171 | N56: 46190 | O56: ="Q"&INT((MONTH(N56)-1)/3)+1 -> Q2 | P56: =NETWORKDAYS(K56,L56) -> 78 | Q56: =IF(M56="",0,NETWORKDAYS(K56,M56)) -> 65 | R56: =IF(N56="",0,NETWORKDAYS(K56,N56)) -> 78 | S56: Joined | T56: Sai Narahari | V56: Employee Referral - Ranjit | AA56: Sindhu
A57: 56 | B57: USA | C57: Production Support | D57: Support | E57: Capital Market Support | F57: Mark D | G57: New | I57: Full-time | J57: Charlotte | K57: 46064 | L57: 46083 | M57: 46073 | N57: 46083 | O57: ="Q"&INT((MONTH(N57)-1)/3)+1 -> Q1 | P57: =NETWORKDAYS(K57,L57) -> 14 | Q57: =IF(M57="",0,NETWORKDAYS(K57,M57)) -> 8 | R57: =IF(N57="",0,NETWORKDAYS(K57,N57)) -> 14 | S57: Joined | T57: Manoj | AA57: Marissa
A58: 57 | B58: India | C58: Engineering | D58: Digital | E58: Full-stack Engineer | F58: Sajeesh | G58: New | H58: Full-time | I58: Full-time | J58: Pune | K58: 46065 | L58: =TODAY() -> 46324 | M58: 46079 | N58: 46132 | O58: ="Q"&INT((MONTH(N58)-1)/3)+1 -> Q2 | P58: =NETWORKDAYS(K58,L58) -> 186 | Q58: =IF(M58="",0,NETWORKDAYS(K58,M58)) -> 11 | R58: =IF(N58="",0,NETWORKDAYS(K58,N58)) -> 48 | S58: Internal Movement | T58: Meghali | V58: IJP | Z58: Amruta & Viddesh Backedout
A59: 58 | B59: India | C59: Engineering | D59: Payments | E59: Performance Engineer | F59: Vijay | G59: Replacement | H59: Pavithra M | I59: Full-time | J59: Pune | K59: 46188 | L59: =TODAY() -> 46324 | N59: 46307 | P59: =NETWORKDAYS(K59,L59) -> 99 | Q59: =IF(M59="",0,NETWORKDAYS(K59,M59)) -> 0 | R59: =IF(N59="",0,NETWORKDAYS(K59,N59)) -> 86 | S59: Temp Hold | T59: Urvashi T | V59: IJP | Z59: Urvashi internal movement (Hariprasanth -offer declined) | AA59: Andleeb
A60: 59 | B60: India | C60: Engineering | D60: Account | E60: Compliance - AI Developer | F60: Ashok | G60: New | I60: Full-time | J60: Chennai | K60: 46097 | L60: 46099 | M60: 46099 | N60: 46104 | O60: ="Q"&INT((MONTH(N60)-1)/3)+1 -> Q1 | P60: =NETWORKDAYS(K60,L60) -> 3 | Q60: =IF(M60="",0,NETWORKDAYS(K60,M60)) -> 3 | R60: =IF(N60="",0,NETWORKDAYS(K60,N60)) -> 6 | S60: Joined | T60: Vaishnavi | V60: Emp Ref
A61: 60 | B61: USA | C61: HR | D61: HR | E61: Director HR | F61: Aarthie | G61: New | I61: Full-time | J61: Charlotte | P61: =NETWORKDAYS(K61,L61) -> 0 | Q61: =IF(M61="",0,NETWORKDAYS(K61,M61)) -> 0 | R61: =IF(N61="",0,NETWORKDAYS(K61,N61)) -> 0 | S61: JD Pending | Z61: JD pending with Aarthie | AA61: Marissa
A62: 61 | B62: USA | C62: Product | D62: Others | E62: Program Manager | F62: Aarthie | G62: New | I62: Full-time | J62: Charlotte | P62: =NETWORKDAYS(K62,L62) -> 0 | Q62: =IF(M62="",0,NETWORKDAYS(K62,M62)) -> 0 | R62: =IF(N62="",0,NETWORKDAYS(K62,N62)) -> 0 | S62: Position Freezed
A63: 62 | B63: USA | C63: Product | D63: Others | E63: Chief Delivery Officer | F63: Aarthie | G63: New | I63: Full-time | J63: Charlotte | P63: =NETWORKDAYS(K63,L63) -> 0 | Q63: =IF(M63="",0,NETWORKDAYS(K63,M63)) -> 0 | R63: =IF(N63="",0,NETWORKDAYS(K63,N63)) -> 0 | S63: Position Freezed
A64: 63 | B64: USA | C64: HR | D64: HR | E64: Exec Assistant & Office Manager | F64: Aarthie | G64: New | I64: Full-time | J64: Charlotte | K64: 46055 | L64: =TODAY() -> 46324 | M64: 46098 | N64: 46111 | O64: ="Q"&INT((MONTH(N64)-1)/3)+1 -> Q1 | P64: =NETWORKDAYS(K64,L64) -> 194 | Q64: =IF(M64="",0,NETWORKDAYS(K64,M64)) -> 32 | R64: =IF(N64="",0,NETWORKDAYS(K64,N64)) -> 41 | S64: Joined | T64: Andrea Clemons | AA64: Marissa
A65: 64 | B65: USA | C65: Marketing/Customer Success | D65: GTM | E65: Marketing Trainee Associate | F65: Marc | G65: New | I65: Full-time | J65: Charlotte | K65: 46064 | L65: =TODAY() -> 46324 | P65: =NETWORKDAYS(K65,L65) -> 187 | Q65: =IF(M65="",0,NETWORKDAYS(K65,M65)) -> 0 | R65: =IF(N65="",0,NETWORKDAYS(K65,N65)) -> 0 | S65: Suspended | AA65: Marissa
A66: 65 | B66: USA | C66: DevOps | D66: DevOps | E66: DevOps Engineer | F66: Manoj | G66: Replacement | H66: Prathamesh | I66: Full-time | J66: Charlotte | K66: 46121 | L66: =TODAY() -> 46324 | P66: =NETWORKDAYS(K66,L66) -> 146 | Q66: =IF(M66="",0,NETWORKDAYS(K66,M66)) -> 0 | R66: =IF(N66="",0,NETWORKDAYS(K66,N66)) -> 0 | S66: Suspended | Z66: Adithya is on hold, This requirement is moved to India team | AA66: Sindhu
A67: 66 | B67: India | C67: Engineering | D67: Payments | E67: Enterprise Architect | F67: Murthy | G67: New | I67: Full-time/Consultant | J67: Pune | K67: =TODAY() -> 46324 | L67: =TODAY() -> 46324 | P67: =NETWORKDAYS(K67,L67) -> 1 | Q67: =IF(M67="",0,NETWORKDAYS(K67,M67)) -> 0 | R67: =IF(N67="",0,NETWORKDAYS(K67,N67)) -> 0 | S67: Suspended | AA67: Andleeb
A68: 67 | B68: India | C68: Engineering | D68: Payments | E68: AI Engineer | F68: Vijay | G68: Replacement | H68: Mallika | I68: Full-time | J68: Pune | K68: 46143 | L68: 46197 | M68: 46197 | N68: 46287 | O68: ="Q"&INT((MONTH(N68)-1)/3)+1 -> Q3 | P68: =NETWORKDAYS(K68,L68) -> 39 | Q68: =IF(M68="",0,NETWORKDAYS(K68,M68)) -> 39 | R68: =IF(N68="",0,NETWORKDAYS(K68,N68)) -> 103 | S68: Joined | T68: Shivam More | V68: External | W68: Green | X68: Sourcing | Y68: Vikrant Singh | Z68: Shivam More - DOJ 22nd Sept | AA68: Vendor/Andleeb
A69: 68 | B69: India | C69: QA | D69: Digital | E69: Senior QA Analyst | F69: Sajeesh | G69: Replacement | H69: Priyanka Kapla | I69: Full-time | J69: Chennai | K69: 46090 | L69: 46094 | M69: 46093 | N69: 46094 | O69: ="Q"&INT((MONTH(N69)-1)/3)+1 -> Q1 | P69: =NETWORKDAYS(K69,L69) -> 5 | Q69: =IF(M69="",0,NETWORKDAYS(K69,M69)) -> 4 | R69: =IF(N69="",0,NETWORKDAYS(K69,N69)) -> 5 | S69: Joined | T69: Mallika | V69: Internal
A70: 69 | B70: USA | C70: Support | D70: GTM | E70: Director, Client Onboarding | F70: Marc | G70: Replacement | I70: Full-time | J70: Charlotte | K70: 46073 | L70: =TODAY() -> 46324 | M70: 46090 | N70: 46100 | O70: ="Q"&INT((MONTH(N70)-1)/3)+1 -> Q1 | P70: =NETWORKDAYS(K70,L70) -> 180 | Q70: =IF(M70="",0,NETWORKDAYS(K70,M70)) -> 12 | R70: =IF(N70="",0,NETWORKDAYS(K70,N70)) -> 20 | S70: Joined | T70: Abhijit C | AA70: Marissa
A71: 70 | B71: India | C71: QA | D71: Account | E71: QA Analyst | F71: Ashok | G71: Replacement | H71: Nikhil | I71: Full-time | J71: Chennai | K71: 46099 | L71: 46122 | M71: 46122 | N71: 46132 | O71: ="Q"&INT((MONTH(N71)-1)/3)+1 -> Q2 | P71: =NETWORKDAYS(K71,L71) -> 18 | Q71: =IF(M71="",0,NETWORKDAYS(K71,M71)) -> 18 | R71: =IF(N71="",0,NETWORKDAYS(K71,N71)) -> 24 | S71: Joined | T71: Arul Anand | V71: Internal | AA71: Thirukumaran
A72: 71 | B72: India | C72: Engineering | D72: PS | E72: Software Engineer | F72: Nitin | G72: Replacement | H72: Meghali | I72: Full-time | J72: Pune | K72: 46104 | L72: =TODAY() -> 46324 | M72: 46105 | N72: 46106 | O72: ="Q"&INT((MONTH(N72)-1)/3)+1 -> Q1 | P72: =NETWORKDAYS(K72,L72) -> 159 | Q72: =IF(M72="",0,NETWORKDAYS(K72,M72)) -> 2 | R72: =IF(N72="",0,NETWORKDAYS(K72,N72)) -> 3 | S72: Joined | T72: Som Limbure | V72: Internal | AA72: Thirukumaran
A73: 72 | B73: USA | C73: QA | D73: PS | E73: Automation Engineer | F73: Kanan | G73: New | I73: Full-time | J73: Charlotte | K73: 46092 | L73: =TODAY() -> 46324 | M73: 46108 | N73: 46132 | O73: ="Q"&INT((MONTH(N73)-1)/3)+1 -> Q2 | P73: =NETWORKDAYS(K73,L73) -> 167 | Q73: =IF(M73="",0,NETWORKDAYS(K73,M73)) -> 13 | R73: =IF(N73="",0,NETWORKDAYS(K73,N73)) -> 29 | S73: Joined | T73: Shashank | AA73: Marissa
A74: 73 | B74: India | C74: Product | D74: Account | E74: Product Manager - Deposits & VA | F74: Ashok | I74: Full-time | J74: Chennai | K74: 46062 | L74: 46101 | M74: 46101 | N74: 46104 | O74: ="Q"&INT((MONTH(N74)-1)/3)+1 -> Q1 | P74: =NETWORKDAYS(K74,L74) -> 30 | Q74: =IF(M74="",0,NETWORKDAYS(K74,M74)) -> 30 | R74: =IF(N74="",0,NETWORKDAYS(K74,N74)) -> 31 | S74: Joined | T74: Arivumani N | V74: Internal | Z74: Narasimha Backup | AA74: Thirukumaran
A75: 74 | B75: India | C75: Finance | D75: Finance | E75: Finance Analyst | F75: Dharani | G75: New | I75: Full-time | J75: Chennai | K75: 46181 | L75: 46203 | M75: 46203 | N75: 46209 | O75: ="Q"&INT((MONTH(N75)-1)/3)+1 -> Q3 | P75: =NETWORKDAYS(K75,L75) -> 17 | Q75: =IF(M75="",0,NETWORKDAYS(K75,M75)) -> 17 | R75: =IF(N75="",0,NETWORKDAYS(K75,N75)) -> 21 | S75: Joined | T75: Vignesh Raja | V75: Internal | X75: Sourcing | Z75: Vignesh Raja - DOJ 6th July | AA75: Andleeb/Thirukumaran
A76: 75 | B76: USA | C76: HR | D76: HR | E76: Recruiter | F76: Aarthie | G76: New | I76: Full-time | J76: Charlotte | K76: 46112 | L76: =TODAY() -> 46324 | M76: 46122 | N76: 46132 | O76: ="Q"&INT((MONTH(N76)-1)/3)+1 -> Q2 | P76: =NETWORKDAYS(K76,L76) -> 153 | Q76: =IF(M76="",0,NETWORKDAYS(K76,M76)) -> 9 | R76: =IF(N76="",0,NETWORKDAYS(K76,N76)) -> 15 | S76: Joined | T76: Sindu | AA76: Marissa
A77: 76 | B77: India | C77: QA | D77: Payments | E77: Senior QA Analyst | F77: Vijay | G77: Replacement | H77: Sakshi Dhumal | I77: Full-time | J77: Pune | K77: 46153 | L77: 46183 | M77: 46183 | N77: 46184 | O77: ="Q"&INT((MONTH(N77)-1)/3)+1 -> Q2 | P77: =NETWORKDAYS(K77,L77) -> 23 | Q77: =IF(M77="",0,NETWORKDAYS(K77,M77)) -> 23 | R77: =IF(N77="",0,NETWORKDAYS(K77,N77)) -> 24 | S77: Joined | T77: Utkarsh | V77: Internal | AA77: Andleeb
A78: 77 | B78: USA | C78: Support | D78: Support | E78: VP of Training | F78: Dharmesh | G78: New | I78: Full-time | J78: Remote - USA | K78: 46129 | L78: =TODAY() -> 46324 | M78: 46134 | N78: 46161 | O78: ="Q"&INT((MONTH(N78)-1)/3)+1 -> Q2 | P78: =NETWORKDAYS(K78,L78) -> 140 | Q78: =IF(M78="",0,NETWORKDAYS(K78,M78)) -> 4 | R78: =IF(N78="",0,NETWORKDAYS(K78,N78)) -> 23 | S78: Joined | T78: Peter Ro | AA78: Marissa
A79: 78 | B79: USA | C79: Payments | D79: Payments | E79: AI Developer | F79: Vijay | G79: New | I79: Full-time | J79: Charlotte | K79: 46125 | L79: =TODAY() -> 46324 | M79: 46143 | N79: 46160 | O79: ="Q"&INT((MONTH(N79)-1)/3)+1 -> Q2 | P79: =NETWORKDAYS(K79,L79) -> 144 | Q79: =IF(M79="",0,NETWORKDAYS(K79,M79)) -> 15 | R79: =IF(N79="",0,NETWORKDAYS(K79,N79)) -> 26 | S79: Joined | T79: Aditya Khandare | AA79: Marissa
A80: 79 | B80: USA | C80: Sales | D80: Sales | E80: Business Development Representative | F80: Jack | G80: Replacement | H80: Will | I80: Full-time | J80: Remote - USA | K80: 46129 | L80: =TODAY() -> 46324 | M80: 46143 | N80: 46161 | O80: ="Q"&INT((MONTH(N80)-1)/3)+1 -> Q2 | P80: =NETWORKDAYS(K80,L80) -> 140 | Q80: =IF(M80="",0,NETWORKDAYS(K80,M80)) -> 11 | R80: =IF(N80="",0,NETWORKDAYS(K80,N80)) -> 23 | S80: Joined | T80: Eric Nowell | AA80: Marissa
A81: 80 | B81: USA | C81: PS | D81: PS | E81: Project Manager | F81: Kanan | G81: New | I81: Full-time | J81: Charlotte | K81: 46132 | L81: =TODAY() -> 46324 | P81: =NETWORKDAYS(K81,L81) -> 139 | Q81: =IF(M81="",0,NETWORKDAYS(K81,M81)) -> 0 | R81: =IF(N81="",0,NETWORKDAYS(K81,N81)) -> 0 | S81: Suspended | AA81: Kanan
A82: 81 | B82: USA | C82: PS | D82: PS | E82: Tech Manager | F82: Kanan | G82: New | I82: Full-time | J82: Charlotte | K82: 46134 | L82: =TODAY() -> 46324 | M82: 46185 | N82: 46237 | O82: Q3 | P82: =NETWORKDAYS(K82,L82) -> 137 | Q82: =IF(M82="",0,NETWORKDAYS(K82,M82)) -> 38 | R82: =IF(N82="",0,NETWORKDAYS(K82,N82)) -> 74 | S82: Joined | T82: Sirisha Meka | Z82: Waiting on H-1B approval | AA82: Sindhu
A83: 82 | B83: India | C83: QA | D83: PS | E83: QA Lead | F83: Kanan | G83: Replacement | H83: Sachin Dhome | I83: Full-time | J83: Pune | K83: 46184 | L83: =TODAY() -> 46324 | P83: =NETWORKDAYS(K83,L83) -> 101 | Q83: =IF(M83="",0,NETWORKDAYS(K83,M83)) -> 0 | R83: =IF(N83="",0,NETWORKDAYS(K83,N83)) -> 0 | S83: Position Freezed | Z83: 2 L1 Interview on hold. Waiting for Dharmesh to share resource capacity planning | AA83: Andleeb/Thirukumaran
A84: 83 | B84: USA | C84: DevOps | D84: DevOps | E84: IT Admin Consultant | F84: Murthy | G84: Replacement | H84: Suman | I84: Consultant | J84: Charlotte | K84: 46128 | L84: =TODAY() -> 46324 | M84: 46160 | N84: 46181 | O84: ="Q"&INT((MONTH(N84)-1)/3)+1 -> Q2 | P84: =NETWORKDAYS(K84,L84) -> 141 | Q84: =IF(M84="",0,NETWORKDAYS(K84,M84)) -> 23 | R84: =IF(N84="",0,NETWORKDAYS(K84,N84)) -> 38 | S84: Joined | T84: Tejasri Balusu | V84: Linkedln applied | AA84: Sindhu
A85: 84 | B85: India | C85: Engineering | D85: Digital | E85: Backend Developer | F85: Sajeesh | G85: Replacement | H85: Ramya | I85: Full-time | J85: Chennai | K85: 46148 | L85: 46224 | M85: 46224 | N85: 46239 | O85: ="Q"&INT((MONTH(N85)-1)/3)+1 -> Q3 | P85: =NETWORKDAYS(K85,L85) -> 55 | Q85: =IF(M85="",0,NETWORKDAYS(K85,M85)) -> 55 | R85: =IF(N85="",0,NETWORKDAYS(K85,N85)) -> 66 | S85: Joined | T85: Thameenansari | V85: Emp Ref | W85: Green | Y85: Abdul R | Z85: Venkatesh/ Gokulnath/ Sandeep/ GokulRaja declined our offer | AA85: Thirukumaran
A86: 85 | B86: India | C86: QA | D86: Trade | E86: QA Analyst | F86: Raju | G86: Replacement | H86: Satyasri | I86: Full-time | J86: Chennai | K86: 46148 | L86: =TODAY() -> 46324 | M86: 46157 | N86: 46160 | O86: ="Q"&INT((MONTH(N86)-1)/3)+1 -> Q2 | P86: =NETWORKDAYS(K86,L86) -> 127 | Q86: =IF(M86="",0,NETWORKDAYS(K86,M86)) -> 8 | R86: =IF(N86="",0,NETWORKDAYS(K86,N86)) -> 9 | S86: Joined | T86: Nirmal | V86: Emp Ref | AA86: Thirukumaran
A87: 86 | B87: India | C87: Engineering | D87: GTM | E87: API Integration Engineer | F87: Karuna | G87: New | I87: Full-time | J87: Pune | K87: 46183 | L87: 46199 | M87: 46199 | N87: 46202 | O87: ="Q"&INT((MONTH(N87)-1)/3)+1 -> Q2 | P87: =NETWORKDAYS(K87,L87) -> 13 | Q87: =IF(M87="",0,NETWORKDAYS(K87,M87)) -> 13 | R87: =IF(N87="",0,NETWORKDAYS(K87,N87)) -> 14 | S87: Joined | T87: Shradha | V87: Internal | Z87: Shradha- DOJ 29th June
A88: 87 | B88: USA | C88: Infosec | D88: Infosec | E88: Associate AI Engineer _InfoSec | F88: Supro | G88: New | I88: Full-time | J88: Charlotte | K88: 46142 | L88: =TODAY() -> 46324 | M88: 46155 | N88: 46169 | O88: ="Q"&INT((MONTH(N88)-1)/3)+1 -> Q2 | P88: =NETWORKDAYS(K88,L88) -> 131 | Q88: =IF(M88="",0,NETWORKDAYS(K88,M88)) -> 10 | R88: =IF(N88="",0,NETWORKDAYS(K88,N88)) -> 20 | S88: Joined | T88: Shubham Bhojwani | V88: Employee Referral - Supro | AA88: Sindhu
A89: 88 | B89: USA | C89: Account Galaxy | D89: Account | E89: Associate AI Engineer_Accounts | F89: Ashok | G89: New | I89: Full-time | J89: Charlotte | K89: 46150 | L89: =TODAY() -> 46324 | M89: 46191 | N89: 46211 | O89: ="Q"&INT((MONTH(N89)-1)/3)+1 -> Q3 | P89: =NETWORKDAYS(K89,L89) -> 125 | Q89: =IF(M89="",0,NETWORKDAYS(K89,M89)) -> 30 | R89: =IF(N89="",0,NETWORKDAYS(K89,N89)) -> 44 | S89: Joined | T89: Tejashwini Padmashali | V89: Linkedln sourcing | AA89: Sindhu
A90: 89 | B90: USA | C90: DevOps | D90: DevOps | E90: Associate AI Engineer_DecOps | F90: Manoj | G90: New | I90: Full-time | J90: Charlotte | K90: 46142 | L90: =TODAY() -> 46324 | M90: 46161 | N90: 46237 | O90: ="Q"&INT((MONTH(N90)-1)/3)+1 -> Q3 | P90: =NETWORKDAYS(K90,L90) -> 131 | Q90: =IF(M90="",0,NETWORKDAYS(K90,M90)) -> 14 | R90: =IF(N90="",0,NETWORKDAYS(K90,N90)) -> 68 | S90: Joined | T90: Bladen Martin | V90: Employee Referral - Supro | Z90: Bladen selected | AA90: Sindhu
A91: 90 | B91: India | C91: Engineering | D91: PS | E91: Senior Software Engineer | F91: Kanan | G91: New | I91: Full-time | J91: Pune | K91: 46174 | L91: 46212 | M91: 46212 | N91: 46217 | O91: ="Q"&INT((MONTH(N91)-1)/3)+1 -> Q3 | P91: =NETWORKDAYS(K91,L91) -> 29 | Q91: =IF(M91="",0,NETWORKDAYS(K91,M91)) -> 29 | R91: =IF(N91="",0,NETWORKDAYS(K91,N91)) -> 32 | S91: Joined | T91: Ajay Shinde | V91: Internal | W91: Amber | X91: Initial Interview | Z91: Ajay (14th July) Scrum Master role changed to SSE | AA91: Thirukumaran
A92: 91 | B92: India | C92: Program | D92: PS | E92: Project Manager | F92: Kanan | G92: New | I92: Full-time | J92: Pune | K92: 46153 | L92: =TODAY() -> 46324 | P92: =NETWORKDAYS(K92,L92) -> 124 | Q92: =IF(M92="",0,NETWORKDAYS(K92,M92)) -> 0 | R92: =IF(N92="",0,NETWORKDAYS(K92,N92)) -> 0 | S92: Suspended
A93: 92 | B93: USA | C93: Engineering | D93: PS | E93: Associate AI Engineer | F93: Kanan | G93: New | I93: Full-time | J93: Charlotte | K93: 46150 | L93: =TODAY() -> 46324 | M93: 46171 | N93: 46209 | O93: ="Q"&INT((MONTH(N93)-1)/3)+1 -> Q3 | P93: =NETWORKDAYS(K93,L93) -> 125 | Q93: =IF(M93="",0,NETWORKDAYS(K93,M93)) -> 16 | R93: =IF(N93="",0,NETWORKDAYS(K93,N93)) -> 42 | S93: Joined | T93: Hrisheekesh Dandekar | V93: Employee Referral - Supro | AA93: Sindhu
A94: 93 | B94: USA | C94: Engineering | D94: Trade | E94: Associate AI Engineer | F94: Brian | G94: New | I94: Full-time | J94: Charlotte | K94: 46150 | L94: =TODAY() -> 46324 | M94: 46191 | N94: 46209 | O94: ="Q"&INT((MONTH(N94)-1)/3)+1 -> Q3 | P94: =NETWORKDAYS(K94,L94) -> 125 | Q94: =IF(M94="",0,NETWORKDAYS(K94,M94)) -> 30 | R94: =IF(N94="",0,NETWORKDAYS(K94,N94)) -> 42 | S94: Joined | T94: Kiran Dhanasekaran | V94: Employee Referral - Supro | AA94: Sindhu
A95: 94 | B95: USA | C95: Engineering | D95: Digital | E95: Associate AI Engineer_Digital Galaxy | F95: Sajeesh | G95: New | I95: Full-time | J95: Charlotte | K95: 46150 | L95: =TODAY() -> 46324 | M95: 46171 | N95: 46188 | O95: ="Q"&INT((MONTH(N95)-1)/3)+1 -> Q2 | P95: =NETWORKDAYS(K95,L95) -> 125 | Q95: =IF(M95="",0,NETWORKDAYS(K95,M95)) -> 16 | R95: =IF(N95="",0,NETWORKDAYS(K95,N95)) -> 27 | S95: Joined | T95: Shubham Salonki | V95: Linkedln sourcing | AA95: Sindhu
A96: 95 | B96: USA | C96: Technology | D96: DevOps | E96: Data Architect | F96: Murthy | G96: New | I96: Full-time | J96: Charlotte | K96: 46159 | L96: =TODAY() -> 46324 | M96: 46205 | N96: 46226 | O96: ="Q"&INT((MONTH(N96)-1)/3)+1 -> Q3 | P96: =NETWORKDAYS(K96,L96) -> 119 | Q96: =IF(M96="",0,NETWORKDAYS(K96,M96)) -> 34 | R96: =IF(N96="",0,NETWORKDAYS(K96,N96)) -> 49 | S96: Joined | T96: Narayanan Sundaram | V96: Employee Referral - Deepak | Z96: Narayana selected | AA96: Sindhu
A97: 96 | B97: India | C97: Engineering | D97: Trade | E97: Software Engineer | F97: Raju | G97: Replacement | H97: Zaki | I97: Full-time | J97: Chennai | K97: 46171 | L97: 46224 | M97: 46224 | N97: 46296 | O97: ="Q"&INT((MONTH(N97)-1)/3)+1 -> Q4 | P97: =NETWORKDAYS(K97,L97) -> 38 | Q97: =IF(M97="",0,NETWORKDAYS(K97,M97)) -> 38 | R97: =IF(N97="",0,NETWORKDAYS(K97,N97)) -> 90 | S97: Joined | T97: Gowthamasaravanan | V97: Internal | W97: Green | X97: Initial Interview | Y97: Bala K | Z97: Gowtham (DOJ 1st Oct) / Sumithra L2 reject | AA97: Thirukumaran
A98: 97 | B98: India | C98: Program | D98: Payments | E98: Incident Management | F98: Kanan | G98: New | I98: Full-time | J98: Pune | K98: 46169 | L98: =TODAY() -> 46324 | N98: 46296 | O98: ="Q"&INT((MONTH(N98)-1)/3)+1 -> Q4 | P98: =NETWORKDAYS(K98,L98) -> 112 | Q98: =IF(M98="",0,NETWORKDAYS(K98,M98)) -> 0 | R98: =IF(N98="",0,NETWORKDAYS(K98,N98)) -> 92 | S98: Position Freezed | Y98: Amit Kulkarni | Z98: Neeraj - Declined due to delay in offer approval / Vishvendra (1st Oct DOJ) - Backedout | AA98: Andleeb/Thirukumaran
A99: 98 | B99: India | C99: Engineering | D99: PS | E99: Software Engineer | F99: Kanan | G99: Replacement | H99: Som Limbure | I99: Full-time | J99: Pune | K99: 46168 | L99: 46206 | M99: 46206 | N99: 46210 | O99: ="Q"&INT((MONTH(N99)-1)/3)+1 -> Q3 | P99: =NETWORKDAYS(K99,L99) -> 29 | Q99: =IF(M99="",0,NETWORKDAYS(K99,M99)) -> 29 | R99: =IF(N99="",0,NETWORKDAYS(K99,N99)) -> 31 | S99: Joined | T99: Sukhbheer | V99: Emp Ref | Z99: Sukbeer (Immidiate) | AA99: Thirukumaran
A100: 99 | B100: USA | C100: Finance | D100: Finance | E100: Commercial Contracts Manager | F100: Aarthie | G100: New | I100: Full-time | J100: Charlotte | K100: 46171 | L100: =TODAY() -> 46324 | M100: 46203 | N100: 46216 | O100: ="Q"&INT((MONTH(N100)-1)/3)+1 -> Q3 | P100: =NETWORKDAYS(K100,L100) -> 110 | Q100: =IF(M100="",0,NETWORKDAYS(K100,M100)) -> 23 | R100: =IF(N100="",0,NETWORKDAYS(K100,N100)) -> 32 | S100: Joined | T100: Cystal Goodwin | V100: Applied in Linkedln | AA100: Sindhu
...

Sheet Challenges
B1: INDIA
A5: Practice | B5: Positions | C5: Hiring Manager | D5: Challenges | E5: HR Solutions
A6: Infosec | B6: Infosec Analyst | C6: Supro | D6: • 3 candidates (Swapnil/Nitesh/Gauresh) declined our offer. • Limited pool of candidates with short notice. | E6: •Open the role to consulting firm. • Schedule the interview with shorter notice period.
A7: Payments | B7: Project Manager | C7: Ramesh | D7: • 2 candidates (Bhavik/Harsh) declined our offer • High Notice period candidates •Candidates preferred only working in office. | E7: • Shared the role with the consulting firms. Ex- employee (Naveen) scheduled with Ramesh this week Friday.
B12: USA
A13: Practice | B13: Positions | C13: Hiring Manager | D13: Challenges | E13: HR Solutions
A14: Finance | B14: CFO | C14: Booshan | D14: The CFO search yielded limited qualified candidates, with the talent pool failing to meet the strategic and technical requirements of the role. | E14: Partner with a specialized executive search firm to broaden the CFO candidate pipeline and access passive, high-caliber talent beyond standard recruitment channels.
A15: DevOps | B15: DevOps Engineer | C15: Manoj S. | D15: Current applicants are either demonstrating indications of interview integrity concerns or are failing to meet required technical competencies for the role. | E15: We plan to expand visibility on LinkedIn as an immediate next step and will evaluate engaging a third‑party recruiting firm if the hiring timeline extends.

Sheet Data Validation
A1: JD Pending | B1: Pune | C1: Full-time | D1: India | E1: New
A2: Screening | B2: Chennai | C2: Consultant | D2: USA | E2: Replacement
A3: Sourcing | B3: India-Remote | C3: Full-time/Consultant
A4: Initial Interview | B4: Charlotte | C4: Contractor
A5: Final Interview | B5: USA-Remote
A6: HR Interview | B6: Chennai/Pune
A7: Offer Approval
A8: Offered
A9: Joined
A10: Temp Hold
A11: Approval Pending
A12: AI Interview
A13: L1 Process
A14: Case study
A15: Profile shared
A16: Position Freezed
A17: Unapproved Postion
A18: Internal Movement
A19: Suspended

Sheet Livefeed
A1: Sr No | B1: Geo | C1: Department | D1: Squads | E1: Positions | F1: Dept Head | G1: New/Replacement | H1: Replaced Employee Name | I1: Full-Time/Consultant | J1: Hiring Location | K1: Position Open Date | L1: Todays Date | M1: Date Offered | N1: Joining Date | O1: Quarter Joining | P1: Aging (Days) | Q1: Position Offered | R1: Position Closed | S1: Status | T1: Offered Candidates | U1: Highest Qualification Degree | V1: Applied/ Sourced/ Reffered (Internal/External) | W1: RAG Status | X1: Back-up Plans | Y1: Buddy - Onboarding | Z1: Comments | AA1: Recruiter
A2: ='Master 2026'!A2 -> 1 | B2: ='Master 2026'!B2 -> India | C2: ='Master 2026'!C2 -> Product | D2: ='Master 2026'!D2 -> Account | E2: ='Master 2026'!E2 -> Product Manager | F2: ='Master 2026'!F2 -> Ashok | G2: ='Master 2026'!G2 -> Replacement | H2: ='Master 2026'!H2 -> Bhargav/Mahesh | ... AA2: ='Master 2026'!AA2 -> Thirukumaran
A3: ='Master 2026'!A3 -> 2 | B3: ='Master 2026'!B3 -> USA | C3: ='Master 2026'!C3 -> Infosec | D3: ='Master 2026'!D3 -> Infosec | E3: ='Master 2026'!E3 -> CISO (Change of Role) | F3: ='Master 2026'!F3 -> Murthy | G3: ='Master 2026'!G3 -> Replacement | H3: ='Master 2026'!H3 -> Nate | ... AA3: ='Master 2026'!AA3 -> Marissa
A4: ='Master 2026'!A4 -> 3 | B4: ='Master 2026'!B4 -> USA | C4: ='Master 2026'!C4 -> Product | D4: ='Master 2026'!D4 -> Payments | E4: ='Master 2026'!E4 -> Product Owner (Change of Role) | F4: ='Master 2026'!F4 -> Vijay | G4: ='Master 2026'!G4 -> New | H4: ='Master 2026'!H4 -> 0 | ... AA4: ='Master 2026'!AA4 -> Marissa
A5: ='Master 2026'!A5 -> 4 | B5: ='Master 2026'!B5 -> USA | C5: ='Master 2026'!C5 -> Engineering | D5: ='Master 2026'!D5 -> Payments | E5: ='Master 2026'!E5 -> Enterprise Architect | F5: ='Master 2026'!F5 -> Murthy | G5: ='Master 2026'!G5 -> New | H5: ='Master 2026'!H5 -> N/A | ... AA5: ='Master 2026'!AA5 -> Andleeb
A6: ='Master 2026'!A6 -> 5 | B6: ='Master 2026'!B6 -> India | C6: ='Master 2026'!C6 -> Engineering | D6: ='Master 2026'!D6 -> Payments | E6: ='Master 2026'!E6 -> Senior Software Engineer | F6: ='Master 2026'!F6 -> Vinay | G6: ='Master 2026'!G6 -> Replacement | H6: ='Master 2026'!H6 -> Revanth | ... AA6: ='Master 2026'!AA6 -> Thirukumaran
A7: ='Master 2026'!A7 -> 6 | B7: ='Master 2026'!B7 -> India | C7: ='Master 2026'!C7 -> DevOps | D7: ='Master 2026'!D7 -> DevOps | E7: ='Master 2026'!E7 -> DevOps Engineer | F7: ='Master 2026'!F7 -> Prathap | G7: ='Master 2026'!G7 -> New | H7: ='Master 2026'!H7 -> 0 | ... AA7: ='Master 2026'!AA7 -> Andleeb
A8: ='Master 2026'!A8 -> 7 | B8: ='Master 2026'!B8 -> India | C8: ='Master 2026'!C8 -> DevOps | D8: ='Master 2026'!D8 -> DevOps | E8: ='Master 2026'!E8 -> Senior DevOps Engineer | F8: ='Master 2026'!F8 -> Prathap | G8: ='Master 2026'!G8 -> New | H8: ='Master 2026'!H8 -> 0 | ... AA8: ='Master 2026'!AA8 -> Andleeb/Thirukumaran
A9: ='Master 2026'!A9 -> 8 | B9: ='Master 2026'!B9 -> India | C9: ='Master 2026'!C9 -> QA | D9: ='Master 2026'!D9 -> Payments | E9: ='Master 2026'!E9 -> Performance Tester | F9: ='Master 2026'!F9 -> Divya | G9: ='Master 2026'!G9 -> Replacement | H9: ='Master 2026'!H9 -> Mageshkumar | ... AA9: ='Master 2026'!AA9 -> Andleeb
A10: ='Master 2026'!A10 -> 9 | B10: ='Master 2026'!B10 -> India | C10: ='Master 2026'!C10 -> Engineering | D10: ='Master 2026'!D10 -> PS | E10: ='Master 2026'!E10 -> Senior Software Engineer | F10: ='Master 2026'!F10 -> Kanan | G10: ='Master 2026'!G10 -> Replacement | H10: ='Master 2026'!H10 -> Nikhilesh | ... AA10: ='Master 2026'!AA10 -> Vendor / Andleeb
A11: ='Master 2026'!A11 -> 10 | B11: ='Master 2026'!B11 -> USA | C11: ='Master 2026'!C11 -> DevOps | D11: ='Master 2026'!D11 -> DevOps | E11: ='Master 2026'!E11 -> Director of Infrastructure | F11: ='Master 2026'!F11 -> Murthy | G11: ='Master 2026'!G11 -> New | H11: ='Master 2026'!H11 -> 0 | ... AA11: ='Master 2026'!AA11 -> Marissa
A12: ='Master 2026'!A12 -> 11 | B12: ='Master 2026'!B12 -> USA | C12: ='Master 2026'!C12 -> DevOps | D12: ='Master 2026'!D12 -> DevOps | E12: ='Master 2026'!E12 -> SecOps - Enterprise Governance | F12: ='Master 2026'!F12 -> Murthy | G12: ='Master 2026'!G12 -> New | H12: ='Master 2026'!H12 -> 0 | ... AA12: ='Master 2026'!AA12 -> Andleeb
A13: ='Master 2026'!A13 -> 12 | B13: ='Master 2026'!B13 -> USA | C13: ='Master 2026'!C13 -> Engineering | D13: ='Master 2026'!D13 -> Account | E13: ='Master 2026'!E13 -> Java Architect | F13: ='Master 2026'!F13 -> Ashok | G13: ='Master 2026'!G13 -> New | H13: ='Master 2026'!H13 -> 0 | ... AA13: ='Master 2026'!AA13 -> Marissa
... A110: ='Master 2026'!A110 -> 109 | B110: ='Master 2026'!B110 -> India | C110: ='Master 2026'!C110 -> Delivery | D110: ='Master 2026'!D110 -> PS | E110: ='Master 2026'!E110 -> Director | F110: ='Master 2026'!F110 -> Kanan | G110: ='Master 2026'!G110 -> New | H110: ='Master 2026'!H110 -> 0 | ... AA110: ='Master 2026'!AA110 -> 0
A111: ='Master 2026'!A111 -> 110 | B111: ='Master 2026'!B111 -> India | C111: ='Master 2026'!C111 -> BA | D111: ='Master 2026'!D111 -> Payments | E111: ='Master 2026'!E111 -> Sr.Business Analyst | F111: ='Master 2026'!F111 -> Vijay | G111: ='Master 2026'!G111 -> Replacement | H111: ='Master 2026'!H111 -> Karthika C | ... N111: ='Master 2026'!N111 -> 46309 | O111: ='Master 2026'!O135 -> Q4 | P111: ='Master 2026'!P111 -> 19 | Q111: ='Master 2026'!Q111 -> 19 | R111: ='Master 2026'!R111 -> 81 | S111: ='Master 2026'!S111 -> Joined | T111: ='Master 2026'!T111 -> Gayathri | U111: ='Master 2026'!U111 -> 0 | V111: ='Master 2026'!V111 -> Emp Ref | W111: ='Master 2026'!W111 -> Green | ... AA111: ='Master 2026'!AA111 -> Andleeb
A112: ='Master 2026'!A112 -> 111 | B112: ='Master 2026'!B112 -> USA | C112: ='Master 2026'!C112 -> PS | D112: ='Master 2026'!D112 -> Account | E112: ='Master 2026'!E112 -> Solution Engineer | F112: ='Master 2026'!F112 -> Ashok | G112: ='Master 2026'!G112 -> New | H112: ='Master 2026'!H112 -> 0 | ... AA112: ='Master 2026'!AA112 -> Sindhu
A113: ='Master 2026'!A113 -> 112 | B113: ='Master 2026'!B113 -> USA | C113: ='Master 2026'!C113 -> Support | D113: ='Master 2026'!D113 -> Support | E113: ='Master 2026'!E113 -> Associate – Payment Production Support (Trainee) | F113: ='Master 2026'!F113 -> Anish | G113: ='Master 2026'!G113 -> New | H113: ='Master 2026'!H113 -> 0 | ... AA113: ='Master 2026'!AA113 -> Sindhu
A114: ='Master 2026'!A114 -> 113 | B114: ='Master 2026'!B114 -> India | C114: ='Master 2026'!C114 -> Support | D114: ='Master 2026'!D114 -> Support | E114: ='Master 2026'!E114 -> Production Support Engineer | F114: ='Master 2026'!F114 -> Mark/Anish | G114: ='Master 2026'!G114 -> Replacement | H114: ='Master 2026'!H114 -> Muzammil | ... AA114: ='Master 2026'!AA114 -> Thirukumaran
A115: ='Master 2026'!A115 -> 114 | B115: ='Master 2026'!B115 -> USA | C115: ='Master 2026'!C115 -> Support | D115: ='Master 2026'!D115 -> Support | E115: ='Master 2026'!E115 -> Associate - Payment Production Support(Trainee) | F115: ='Master 2026'!F115 -> Ranjith | G115: ='Master 2026'!G115 -> New | H115: ='Master 2026'!H115 -> 0 | ... AA115: ='Master 2026'!AA115 -> Sindhu
A116: ='Master 2026'!A116 -> 115 | B116: ='Master 2026'!B116 -> USA | C116: ='Master 2026'!C116 -> PS | D116: ='Master 2026'!D116 -> PS | E116: ='Master 2026'!E116 -> Associate - Implementation Analyst 1 | F116: ='Master 2026'!F116 -> Kanan | G116: ='Master 2026'!G116 -> New | H116: ='Master 2026'!H116 -> 0 | ... AA116: ='Master 2026'!AA116 -> Sindhu
A117: ='Master 2026'!A117 -> 116 | B117: ='Master 2026'!B117 -> USA | C117: ='Master 2026'!C117 -> PS | D117: ='Master 2026'!D117 -> PS | E117: ='Master 2026'!E117 -> Associate - Implementation Analyst 2 | F117: ='Master 2026'!F117 -> Kanan | G117: ='Master 2026'!G117 -> New | H117: ='Master 2026'!H117 -> 0 | ... AA117: ='Master 2026'!AA117 -> Sindhu
A118: ='Master 2026'!A118 -> 117 | B118: ='Master 2026'!B118 -> USA | C118: ='Master 2026'!C118 -> PS | D118: ='Master 2026'!D118 -> PS | E118: ='Master 2026'!E118 -> FX Business Analyst | F118: ='Master 2026'!F118 -> Kanan | G118: ='Master 2026'!G118 -> Replacement | H118: ='Master 2026'!H118 -> James | ... AA118: ='Master 2026'!AA118 -> Sindhu
A119: ='Master 2026'!A119 -> 118 | B119: ='Master 2026'!B119 -> India | C119: ='Master 2026'!C119 -> Engineering | D119: ='Master 2026'!D119 -> Payments | E119: ='Master 2026'!E119 -> Senior Software Engineer | F119: ='Master 2026'!F119 -> Vijay | G119: ='Master 2026'!G119 -> Replacement | H119: ='Master 2026'!H119 -> Maniprathap | ... AA119: ='Master 2026'!AA119 -> Andleeb
A120: ='Master 2026'!A120 -> 119 | B120: ='Master 2026'!B120 -> India | C120: ='Master 2026'!C120 -> Engineering | D120: ='Master 2026'!D120 -> Payments | E120: ='Master 2026'!E120 -> Application Architect | F120: ='Master 2026'!F120 -> Vijay | G120: ='Master 2026'!G120 -> Replacement | H120: ='Master 2026'!H120 -> Shankar | ... AA120: ='Master 2026'!AA120 -> 0
A121: ='Master 2026'!A121 -> 120 | B121: ='Master 2026'!B121 -> India | C121: ='Master 2026'!C121 -> Engineering | D121: ='Master 2026'!D121 -> Payments | E121: ='Master 2026'!E121 -> Senior Software Engineer | F121: ='Master 2026'!F121 -> Vijay | G121: ='Master 2026'!G121 -> Replacement | H121: ='Master 2026'!H121 -> Ganesh k | ... AA121: ='Master 2026'!AA121 -> Thirukumaran
A122: ='Master 2026'!A122 -> 121 | B122: ='Master 2026'!B122 -> India | C122: ='Master 2026'!C122 -> Engineering | D122: ='Master 2026'!D122 -> Payments | E122: ='Master 2026'!E122 -> Associate Software Engineer | F122: ='Master 2026'!F122 -> Vijay | G122: ='Master 2026'!G122 -> Replacement | H122: ='Master 2026'!H122 -> Shubham J | ... AA122: ='Master 2026'!AA122 -> Thirukumaran
A123: ='Master 2026'!A123 -> 122 | B123: ='Master 2026'!B123 -> USA | C123: ='Master 2026'!C123 -> PS | D123: ='Master 2026'!D123 -> Account | E123: ='Master 2026'!E123 -> Business Analyst | F123: ='Master 2026'!F123 -> Ashok | G123: ='Master 2026'!G123 -> New | H123: ='Master 2026'!H123 -> 0 | ... AA123: ='Master 2026'!AA123 -> Sindhu
... A134: ='Master 2026'!A134 -> 133 | B134: ='Master 2026'!B134 -> India | C134: ='Master 2026'!C134 -> Engineering | D134: ='Master 2026'!D134 -> Digital | E134: ='Master 2026'!E134 -> Associate Software Engineer | F134: ='Master 2026'!F134 -> Sajeesh | G134: ='Master 2026'!G134 -> Replacement | H134: ='Master 2026'!H134 -> Sai Shree | ... AA134: ='Master 2026'!AA134 -> 0
A135: ='Master 2026'!A135 -> 134 | B135: ='Master 2026'!B135 -> India | C135: ='Master 2026'!C135 -> Technology | D135: ='Master 2026'!D135 -> Technology | E135: ='Master 2026'!E135 -> Junior IT Admin | F135: ='Master 2026'!F135 -> Supro | G135: ='Master 2026'!G135 -> New | H135: ='Master 2026'!H135 -> 0 | ... N135: ='Master 2026'!N135 -> 46329 | O135: ='Master 2026'!#REF! -> #REF! | P135: ='Master 2026'!P135 -> 46 | Q135: ='Master 2026'!Q135 -> 46 | R135: ='Master 2026'!R135 -> 57 | S135: ='Master 2026'!S135 -> Offered | T135: ='Master 2026'!T135 -> Athiban Eswar | U135: ='Master 2026'!U135 -> 0 | V135: ='Master 2026'!V135 -> Internal | W135: ='Master 2026'!W135 -> Green | ... AA135: ='Master 2026'!AA135 -> Thirukumaran
A136: ='Master 2026'!A136 -> 135 | B136: ='Master 2026'!B136 -> India | C136: ='Master 2026'!C136 -> QA | D136: ='Master 2026'!D136 -> Payments | E136: ='Master 2026'!E136 -> Associate QA | F136: ='Master 2026'!F136 -> Vijay | G136: ='Master 2026'!G136 -> Replacement | H136: ='Master 2026'!H136 -> Gaurav D | ... AA136: ='Master 2026'!AA136 -> 0
A137: ='Master 2026'!A137 -> 136 | B137: ='Master 2026'!B137 -> India | C137: ='Master 2026'!C137 -> Support | D137: ='Master 2026'!D137 -> Support | E137: ='Master 2026'!E137 -> Production Support Engineer ( Payments) | F137: ='Master 2026'!F137 -> Anish | G137: ='Master 2026'!G137 -> Replacement | H137: ='Master 2026'!H137 -> Prince | ... AA137: ='Master 2026'!AA137 -> Andleeb
A138: ='Master 2026'!A138 -> 137 | B138: ='Master 2026'!B138 -> India | C138: ='Master 2026'!C138 -> HR | D138: ='Master 2026'!D138 -> HR | E138: ='Master 2026'!E138 -> Senior HR Manager | F138: ='Master 2026'!F138 -> Aarthie | G138: ='Master 2026'!G138 -> Replacement | H138: ='Master 2026'!H138 -> Bharathkumar M | ... AA138: ='Master 2026'!AA138 -> External
A139: ='Master 2026'!A139 -> 138 | B139: ='Master 2026'!B139 -> India | C139: ='Master 2026'!C139 -> Marketing | D139: ='Master 2026'!D139 -> GTM | E139: ='Master 2026'!E139 -> Director Marketing | F139: ='Master 2026'!F139 -> Suja | G139: ='Master 2026'!G139 -> New | H139: ='Master 2026'!H139 -> 0 | ... Y139: ='Master 2026'!Y139 -> 0 | Z139: ='Master 2026'!Z140 -> Karthik Joined us on 21st Sept | AA139: ='Master 2026'!AA139 -> External
A140: ='Master 2026'!A140 -> 139 | B140: ='Master 2026'!B140 -> India | C140: ='Master 2026'!C140 -> Marketing | D140: ='Master 2026'!D140 -> GTM | E140: ='Master 2026'!E140 -> Marketing Manager | F140: ='Master 2026'!F140 -> Suja | G140: ='Master 2026'!G140 -> New | H140: ='Master 2026'!H140 -> 0 | ... Y140: ='Master 2026'!Y140 -> 0 | Z140: ='Master 2026'!#REF! -> #REF! | AA140: ='Master 2026'!AA140 -> External
A141: ='Master 2026'!A141 -> 140 | B141: ='Master 2026'!B141 -> India | C141: ='Master 2026'!C141 -> Engineering | D141: ='Master 2026'!D141 -> Payments | E141: ='Master 2026'!E141 -> Associate Software Engineer | F141: ='Master 2026'!F141 -> Vijay | G141: ='Master 2026'!G141 -> Replacement | H141: ='Master 2026'!H141 -> Pradyumna | ... AA141: ='Master 2026'!AA141 -> 0
A142: ='Master 2026'!A142 -> 141 | B142: ='Master 2026'!B142 -> India | C142: ='Master 2026'!C142 -> Engineering | D142: ='Master 2026'!D142 -> Payments | E142: ='Master 2026'!E142 -> Associate Software Engineer | F142: ='Master 2026'!F142 -> Vijay | G142: ='Master 2026'!G142 -> Replacement | H142: ='Master 2026'!H142 -> Yogesh Y | ... AA142: ='Master 2026'!AA142 -> 0
A143: ='Master 2026'!A143 -> 142 | B143: ='Master 2026'!B143 -> India | C143: ='Master 2026'!C143 -> Engineering | D143: ='Master 2026'!D143 -> Payments | E143: ='Master 2026'!E143 -> Associate Software Engineer | F143: ='Master 2026'!F143 -> Vijay | G143: ='Master 2026'!G143 -> Replacement | H143: ='Master 2026'!H143 -> Vikrant J | ... AA143: ='Master 2026'!AA143 -> 0
A144: ='Master 2026'!A144 -> 143 | B144: ='Master 2026'!B144 -> India | C144: ='Master 2026'!C144 -> Engineering | D144: ='Master 2026'!D144 -> Payments | E144: ='Master 2026'!E144 -> Software Engineer | F144: ='Master 2026'!F144 -> Vijay | G144: ='Master 2026'!G144 -> Replacement | H144: ='Master 2026'!H144 -> Bhavik P | ... AA144: ='Master 2026'!AA144 -> 0
A145: ='Master 2026'!A145 -> 144 | B145: ='Master 2026'!B145 -> India | C145: ='Master 2026'!C145 -> DevOps | D145: ='Master 2026'!D145 -> DevOps | E145: ='Master 2026'!E145 -> Senior DevOps Engineer | F145: ='Master 2026'!F145 -> Manoj | G145: ='Master 2026'!G145 -> Replacement | H145: ='Master 2026'!H145 -> Prathamesh | ... AA145: ='Master 2026'!AA145 -> Andleeb/Thirukumaran
A146: ='Master 2026'!A146 -> 145 | B146: ='Master 2026'!B146 -> India | C146: ='Master 2026'!C146 -> Delivery | D146: ='Master 2026'!D146 -> PS | E146: ='Master 2026'!E146 -> Delivery Manager | F146: ='Master 2026'!F146 -> Kanan | G146: ='Master 2026'!G146 -> Replacement | H146: ='Master 2026'!H146 -> Satyavir/Kishore T | ... AA146: ='Master 2026'!AA146 -> Andleeb
A147: ='Master 2026'!A147 -> 146 | B147: ='Master 2026'!B147 -> India | C147: ='Master 2026'!C147 -> Engineering | D147: ='Master 2026'!D147 -> PS | E147: ='Master 2026'!E147 -> Senior Software Engineer | F147: ='Master 2026'!F147 -> Kanan | G147: ='Master 2026'!G147 -> Replacement | H147: ='Master 2026'!H147 -> Nitin | ... AA147: ='Master 2026'!AA147 -> Thirukumaran
A148: ='Master 2026'!A148 -> 147 | B148: ='Master 2026'!B148 -> India | C148: ='Master 2026'!C148 -> Support | D148: ='Master 2026'!D148 -> Support | E148: ='Master 2026'!E148 -> Production Support Engineer | F148: ='Master 2026'!F148 -> Anish | G148: ='Master 2026'!G148 -> Replacement | H148: ='Master 2026'!H148 -> Ajayraja | ... AA148: ='Master 2026'!AA148 -> Andleeb
A149: ='Master 2026'!A149 -> 148 | B149: ='Master 2026'!B149 -> India | C149: ='Master 2026'!C149 -> Finance | D149: ='Master 2026'!D149 -> Finance | E149: ='Master 2026'!E149 -> NetSuite Implementation Expert | F149: ='Master 2026'!F149 -> Dharani | G149: ='Master 2026'!G149 -> New | H149: ='Master 2026'!H149 -> 0 | ... AA149: ='Master 2026'!AA149 -> 0
A150: ='Master 2026'!A150 -> 149 | B150: ='Master 2026'!B150 -> 0 | C150: ='Master 2026'!C150 -> 0 | D150: ='Master 2026'!D150 -> 0 | E150: ='Master 2026'!E150 -> 0 | F150: ='Master 2026'!F150 -> 0 | G150: ='Master 2026'!G150 -> 0 | H150: ='Master 2026'!H150 -> 0 | ... AA150: ='Master 2026'!AA150 -> 0
A151: ='Master 2026'!A151 -> 150 | B151: ='Master 2026'!B151 -> 0 | C151: ='Master 2026'!C151 -> 0 | D151: ='Master 2026'!D151 -> 0 | E151: ='Master 2026'!E151 -> 0 | F151: ='Master 2026'!F151 -> 0 | G151: ='Master 2026'!G151 -> 0 | H151: ='Master 2026'!H151 -> 0 | ... AA151: ='Master 2026'!AA151 -> 0
A152: ='Master 2026'!A152 -> 151 | B152: ='Master 2026'!B152 -> 0 | C152: ='Master 2026'!C152 -> 0 | D152: ='Master 2026'!D152 -> 0 | E152: ='Master 2026'!E152 -> 0 | F152: ='Master 2026'!F152 -> 0 | G152: ='Master 2026'!G152 -> 0 | H152: ='Master 2026'!H152 -> 0 | ... AA152: ='Master 2026'!AA152 -> 0
... A1000: ='Master 2026'!A1000 -> 0 | B1000: ='Master 2026'!B1000 -> 0 | C1000: ='Master 2026'!C1000 -> 0 | D1000: ='Master 2026'!D1000 -> 0 | E1000: ='Master 2026'!E1000 -> 0 | F1000: ='Master 2026'!F1000 -> 0 | G1000: ='Master 2026'!G1000 -> 0 | H1000: ='Master 2026'!H1000 -> 0 | ... AA1000: ='Master 2026'!AA1000 -> 0

Sheet Dashboard
A1: India Joiners Dashboard
A2: FY2026 · Source: Master 2026 (Geo = India, Status = Joined) · Live formulas, auto-updates
A4: Joiners by Location & Quarter
A5: Location | B5: Q1 | C5: Q2 | D5: Q3 | E5: Q4 | F5: Total
A6: Chennai | B6: {=SUMPRODUCT((TRIM(OFFSET('Master 2026'!$B$2,0,0,COUNTA('Master 2026'!$A:$A)-1,1))="India")*(TRIM(OFFSET('Master 2026'!$S$2,0,0,COUNTA('Master 2026'!$A:$A)-1,1))="Joined")*(TRIM(OFFSET('Master 2026'!$J$2,0,0,COUNTA('Master 2026'!$A:$A)-1,1))=$A6)*(TRIM(OFFSET('Master 2026'!$O$2,0,0,COUNTA('Master 2026'!$A:$A)-1,1))=B$5))} -> 13 | C6: {=SUMPRODUCT((TRIM(OFFSET('Master 2026'!$B$2,0,0,COUNTA('Master 2026'!$A:$A)-1,1))="India")*(TRIM(OFFSET('Master 2026'!$S$2,0,0,COUNTA('Master 2026'!$A:$A)-1,1))="Joined")*(TRIM(OFFSET('Master 2026'!$J$2,0,0,COUNTA('Master 2026'!$A:$A)-1,1))=$A6)*(TRIM(OFFSET('Master 2026'!$O$2,0,0,COUNTA('Master 2026'!$A:$A)-1,1))=C$5))} -> 8 | D6: {=SUMPRODUCT((TRIM(OFFSET('Master 2026'!$B$2,0,0,COUNTA('Master 2026'!$A:$A)-1,1))="India")*(TRIM(OFFSET('Master 2026'!$S$2,0,0,COUNTA('Master 2026'!$A:$A)-1,1))="Joined")*(TRIM(OFFSET('Master 2026'!$J$2,0,0,COUNTA('Master 2026'!$A:$A)-1,1))=$A6)*(TRIM(OFFSET('Master 2026'!$O$2,0,0,COUNTA('Master 2026'!$A:$A)-1,1))=D$5))} -> 5 | E6: {=SUMPRODUCT((TRIM(OFFSET('Master 2026'!$B$2,0,0,COUNTA('Master 2026'!$A:$A)-1,1))="India")*(TRIM(OFFSET('Master 2026'!$S$2,0,0,COUNTA('Master 2026'!$A:$A)-1,1))="Joined")*(TRIM(OFFSET('Master 2026'!$J$2,0,0,COUNTA('Master 2026'!$A:$A)-1,1))=$A6)*(TRIM(OFFSET('Master 2026'!$O$2,0,0,COUNTA('Master 2026'!$A:$A)-1,1))=E$5))} -> 3 | F6: =SUM(B6:E6) -> 29
A7: Pune | B7: {=SUMPRODUCT((TRIM(OFFSET('Master 2026'!$B$2,0,0,COUNTA('Master 2026'!$A:$A)-1,1))="India")*(TRIM(OFFSET('Master 2026'!$S$2,0,0,COUNTA('Master 2026'!$A:$A)-1,1))="Joined")*(TRIM(OFFSET('Master 2026'!$J$2,0,0,COUNTA('Master 2026'!$A:$A)-1,1))=$A7)*(TRIM(OFFSET('Master 2026'!$O$2,0,0,COUNTA('Master 2026'!$A:$A)-1,1))=B$5))} -> 8 | C7: {=SUMPRODUCT((TRIM(OFFSET('Master 2026'!$B$2,0,0,COUNTA('Master 2026'!$A:$A)-1,1))="India")*(TRIM(OFFSET('Master 2026'!$S$2,0,0,COUNTA('Master 2026'!$A:$A)-1,1))="Joined")*(TRIM(OFFSET('Master 2026'!$J$2,0,0,COUNTA('Master 2026'!$A:$A)-1,1))=$A7)*(TRIM(OFFSET('Master 2026'!$O$2,0,0,COUNTA('Master 2026'!$A:$A)-1,1))=C$5))} -> 9 | D7: {=SUMPRODUCT((TRIM(OFFSET('Master 2026'!$B$2,0,0,COUNTA('Master 2026'!$A:$A)-1,1))="India")*(TRIM(OFFSET('Master 2026'!$S$2,0,0,COUNTA('Master 2026'!$A:$A)-1,1))="Joined")*(TRIM(OFFSET('Master 2026'!$J$2,0,0,COUNTA('Master 2026'!$A:$A)-1,1))=$A7)*(TRIM(OFFSET('Master 2026'!$O$2,0,0,COUNTA('Master 2026'!$A:$A)-1,1))=D$5))} -> 7 | E7: {=SUMPRODUCT((TRIM(OFFSET('Master 2026'!$B$2,0,0,COUNTA('Master 2026'!$A:$A)-1,1))="India")*(TRIM(OFFSET('Master 2026'!$S$2,0,0,COUNTA('Master 2026'!$A:$A)-1,1))="Joined")*(TRIM(OFFSET('Master 2026'!$J$2,0,0,COUNTA('Master 2026'!$A:$A)-1,1))=$A7)*(TRIM(OFFSET('Master 2026'!$O$2,0,0,COUNTA('Master 2026'!$A:$A)-1,1))=E$5))} -> 0 | F7: =SUM(B7:E7) -> 24
A8: Remote (incl. India-Remote) | B8: {=SUMPRODUCT((TRIM(OFFSET('Master 2026'!$B$2,0,0,COUNTA('Master 2026'!$A:$A)-1,1))="India")*(TRIM(OFFSET('Master 2026'!$S$2,0,0,COUNTA('Master 2026'!$A:$A)-1,1))="Joined")*((TRIM(OFFSET('Master 2026'!$J$2,0,0,COUNTA('Master 2026'!$A:$A)-1,1))="Remote")+(TRIM(OFFSET('Master 2026'!$J$2,0,0,COUNTA('Master 2026'!$A:$A)-1,1))="India-Remote"))*(TRIM(OFFSET('Master 2026'!$O$2,0,0,COUNTA('Master 2026'!$A:$A)-1,1))=B$5))} -> 2 | C8: {=SUMPRODUCT((TRIM(OFFSET('Master 2026'!$B$2,0,0,COUNTA('Master 2026'!$A:$A)-1,1))="India")*(TRIM(OFFSET('Master 2026'!$S$2,0,0,COUNTA('Master 2026'!$A:$A)-1,1))="Joined")*((TRIM(OFFSET('Master 2026'!$J$2,0,0,COUNTA('Master 2026'!$A:$A)-1,1))="Remote")+(TRIM(OFFSET('Master 2026'!$J$2,0,0,COUNTA('Master 2026'!$A:$A)-1,1))="India-Remote"))*(TRIM(OFFSET('Master 2026'!$O$2,0,0,COUNTA('Master 2026'!$A:$A)-1,1))=C$5))} -> 3 | D8: {=SUMPRODUCT((TRIM(OFFSET('Master 2026'!$B$2,0,0,COUNTA('Master 2026'!$A:$A)-1,1))="India")*(TRIM(OFFSET('Master 2026'!$S$2,0,0,COUNTA('Master 2026'!$A:$A)-1,1))="Joined")*((TRIM(OFFSET('Master 2026'!$J$2,0,0,COUNTA('Master 2026'!$A:$A)-1,1))="Remote")+(TRIM(OFFSET('Master 2026'!$J$2,0,0,COUNTA('Master 2026'!$A:$A)-1,1))="India-Remote"))*(TRIM(OFFSET('Master 2026'!$O$2,0,0,COUNTA('Master 2026'!$A:$A)-1,1))=D$5))} -> 4 | E8: {=SUMPRODUCT((TRIM(OFFSET('Master 2026'!$B$2,0,0,COUNTA('Master 2026'!$A:$A)-1,1))="India")*(TRIM(OFFSET('Master 2026'!$S$2,0,0,COUNTA('Master 2026'!$A:$A)-1,1))="Joined")*((TRIM(OFFSET('Master 2026'!$J$2,0,0,COUNTA('Master 2026'!$A:$A)-1,1))="Remote")+(TRIM(OFFSET('Master 2026'!$J$2,0,0,COUNTA('Master 2026'!$A:$A)-1,1))="India-Remote"))*(TRIM(OFFSET('Master 2026'!$O$2,0,0,COUNTA('Master 2026'!$A:$A)-1,1))=E$5))} -> 0 | F8: =SUM(B8:E8) -> 9
A9: Total | B9: =SUM(B6:B8) -> 23 | C9: =SUM(C6:C8) -> 20 | D9: =SUM(D6:D8) -> 16 | E9: =SUM(E6:E8) -> 3 | F9: =SUM(B9:E9) -> 62
A12: Joiners by Squad & Quarter
A13: Squad | B13: Q1 | C13: Q2 | D13: Q3 | E13: Q4 | F13: Total
A14: Account | B14: {=SUMPRODUCT((TRIM('Master 2026'!$B$2:$B$1000)="India")*(TRIM('Master 2026'!$S$2:$S$1000)="Joined")*(TRIM('Master 2026'!$D$2:$D$1000)=$A14)*(TRIM('Master 2026'!$O$2:$O$1000)=B$13))} -> 4 | C14: {=SUMPRODUCT((TRIM('Master 2026'!$B$2:$B$1000)="India")*(TRIM('Master 2026'!$S$2:$S$1000)="Joined")*(TRIM('Master 2026'!$D$2:$D$1000)=$A14)*(TRIM('Master 2026'!$O$2:$O$1000)=C$13))} -> 3 | D14: {=SUMPRODUCT((TRIM('Master 2026'!$B$2:$B$1000)="India")*(TRIM('Master 2026'!$S$2:$S$1000)="Joined")*(TRIM('Master 2026'!$D$2:$D$1000)=$A14)*(TRIM('Master 2026'!$O$2:$O$1000)=D$13))} -> 0 | E14: {=SUMPRODUCT((TRIM('Master 2026'!$B$2:$B$1000)="India")*(TRIM('Master 2026'!$S$2:$S$1000)="Joined")*(TRIM('Master 2026'!$D$2:$D$1000)=$A14)*(TRIM('Master 2026'!$O$2:$O$1000)=E$13))} -> 0 | F14: =SUM(B14:E14) -> 7
A15: DevOps | B15: {=SUMPRODUCT((TRIM('Master 2026'!$B$2:$B$1000)="India")*(TRIM('Master 2026'!$S$2:$S$1000)="Joined")*(TRIM('Master 2026'!$D$2:$D$1000)=$A15)*(TRIM('Master 2026'!$O$2:$O$1000)=B$13))} -> 1 | C15: {=SUMPRODUCT((TRIM('Master 2026'!$B$2:$B$1000)="India")*(TRIM('Master 2026'!$S$2:$S$1000)="Joined")*(TRIM('Master 2026'!$D$2:$D$1000)=$A15)*(TRIM('Master 2026'!$O$2:$O$1000)=C$13))} -> 3 | D15: {=SUMPRODUCT((TRIM('Master 2026'!$B$2:$B$1000)="India")*(TRIM('Master 2026'!$S$2:$S$1000)="Joined")*(TRIM('Master 2026'!$D$2:$D$1000)=$A15)*(TRIM('Master 2026'!$O$2:$O$1000)=D$13))} -> 0 | E15: {=SUMPRODUCT((TRIM('Master 2026'!$B$2:$B$1000)="India")*(TRIM('Master 2026'!$S$2:$S$1000)="Joined")*(TRIM('Master 2026'!$D$2:$D$1000)=$A15)*(TRIM('Master 2026'!$O$2:$O$1000)=E$13))} -> 0 | F15: =SUM(B15:E15) -> 4
A16: Digital | B16: {=SUMPRODUCT((TRIM('Master 2026'!$B$2:$B$1000)="India")*(TRIM('Master 2026'!$S$2:$S$1000)="Joined")*(TRIM('Master 2026'!$D$2:$D$1000)=$A16)*(TRIM('Master 2026'!$O$2:$O$1000)=B$13))} -> 3 | C16: {=SUMPRODUCT((TRIM('Master 2026'!$B$2:$B$1000)="India")*(TRIM('Master 2026'!$S$2:$S$1000)="Joined")*(TRIM('Master 2026'!$D$2:$D$1000)=$A16)*(TRIM('Master 2026'!$O$2:$O$1000)=C$13))} -> 1 | D16: {=SUMPRODUCT((TRIM('Master 2026'!$B$2:$B$1000)="India")*(TRIM('Master 2026'!$S$2:$S$1000)="Joined")*(TRIM('Master 2026'!$D$2:$D$1000)=$A16)*(TRIM('Master 2026'!$O$2:$O$1000)=D$13))} -> 1 | E16: {=SUMPRODUCT((TRIM('Master 2026'!$B$2:$B$1000)="India")*(TRIM('Master 2026'!$S$2:$S$1000)="Joined")*(TRIM('Master 2026'!$D$2:$D$1000)=$A16)*(TRIM('Master 2026'!$O$2:$O$1000)=E$13))} -> 0 | F16: =SUM(B16:E16) -> 5
A17: Finance | B17: {=SUMPRODUCT((TRIM('Master 2026'!$B$2:$B$1000)="India")*(TRIM('Master 2026'!$S$2:$S$1000)="Joined")*(TRIM('Master 2026'!$D$2:$D$1000)=$A17)*(TRIM('Master 2026'!$O$2:$O$1000)=B$13))} -> 0 | C17: {=SUMPRODUCT((TRIM('Master 2026'!$B$2:$B$1000)="India")*(TRIM('Master 2026'!$S$2:$S$1000)="Joined")*(TRIM('Master 2026'!$D$2:$D$1000)=$A17)*(TRIM('Master 2026'!$O$2:$O$1000)=C$13))} -> 0 | D17: {=SUMPRODUCT((TRIM('Master 2026'!$B$2:$B$1000)="India")*(TRIM('Master 2026'!$S$2:$S$1000)="Joined")*(TRIM('Master 2026'!$D$2:$D$1000)=$A17)*(TRIM('Master 2026'!$O$2:$O$1000)=D$13))} -> 1 | E17: {=SUMPRODUCT((TRIM('Master 2026'!$B$2:$B$1000)="India")*(TRIM('Master 2026'!$S$2:$S$1000)="Joined")*(TRIM('Master 2026'!$D$2:$D$1000)=$A17)*(TRIM('Master 2026'!$O$2:$O$1000)=E$13))} -> 1 | F17: =SUM(B17:E17) -> 2
A18: GTM | B18: {=SUMPRODUCT((TRIM('Master 2026'!$B$2:$B$1000)="India")*(TRIM('Master 2026'!$S$2:$S$1000)="Joined")*(TRIM('Master 2026'!$D$2:$D$1000)=$A18)*(TRIM('Master 2026'!$O$2:$O$1000)=B$13))} -> 0 | C18: {=SUMPRODUCT((TRIM('Master 2026'!$B$2:$B$1000)="India")*(TRIM('Master 2026'!$S$2:$S$1000)="Joined")*(TRIM('Master 2026'!$D$2:$D$1000)=$A18)*(TRIM('Master 2026'!$O$2:$O$1000)=C$13))} -> 1 | D18: {=SUMPRODUCT((TRIM('Master 2026'!$B$2:$B$1000)="India")*(TRIM('Master 2026'!$S$2:$S$1000)="Joined")*(TRIM('Master 2026'!$D$2:$D$1000)=$A18)*(TRIM('Master 2026'!$O$2:$O$1000)=D$13))} -> 2 | E18: {=SUMPRODUCT((TRIM('Master 2026'!$B$2:$B$1000)="India")*(TRIM('Master 2026'!$S$2:$S$1000)="Joined")*(TRIM('Master 2026'!$D$2:$D$1000)=$A18)*(TRIM('Master 2026'!$O$2:$O$1000)=E$13))} -> 0 | F18: =SUM(B18:E18) -> 3
A19: HR | B19: {=SUMPRODUCT((TRIM('Master 2026'!$B$2:$B$1000)="India")*(TRIM('Master 2026'!$S$2:$S$1000)="Joined")*(TRIM('Master 2026'!$D$2:$D$1000)=$A19)*(TRIM('Master 2026'!$O$2:$O$1000)=B$13))} -> 2 | C19: {=SUMPRODUCT((TRIM('Master 2026'!$B$2:$B$1000)="India")*(TRIM('Master 2026'!$S$2:$S$1000)="Joined")*(TRIM('Master 2026'!$D$2:$D$1000)=$A19)*(TRIM('Master 2026'!$O$2:$O$1000)=C$13))} -> 0 | D19: {=SUMPRODUCT((TRIM('Master 2026'!$B$2:$B$1000)="India")*(TRIM('Master 2026'!$S$2:$S$1000)="Joined")*(TRIM('Master 2026'!$D$2:$D$1000)=$A19)*(TRIM('Master 2026'!$O$2:$O$1000)=D$13))} -> 1 | E19: {=SUMPRODUCT((TRIM('Master 2026'!$B$2:$B$1000)="India")*(TRIM('Master 2026'!$S$2:$S$1000)="Joined")*(TRIM('Master 2026'!$D$2:$D$1000)=$A19)*(TRIM('Master 2026'!$O$2:$O$1000)=E$13))} -> 0 | F19: =SUM(B19:E19) -> 3
A20: Infosec | B20: {=SUMPRODUCT((TRIM('Master 2026'!$B$2:$B$1000)="India")*(TRIM('Master 2026'!$S$2:$S$1000)="Joined")*(TRIM('Master 2026'!$D$2:$D$1000)=$A20)*(TRIM('Master 2026'!$O$2:$O$1000)=B$13))} -> 1 | C20: {=SUMPRODUCT((TRIM('Master 2026'!$B$2:$B$1000)="India")*(TRIM('Master 2026'!$S$2:$S$1000)="Joined")*(TRIM('Master 2026'!$D$2:$D$1000)=$A20)*(TRIM('Master 2026'!$O$2:$O$1000)=C$13))} -> 0 | D20: {=SUMPRODUCT((TRIM('Master 2026'!$B$2:$B$1000)="India")*(TRIM('Master 2026'!$S$2:$S$1000)="Joined")*(TRIM('Master 2026'!$D$2:$D$1000)=$A20)*(TRIM('Master 2026'!$O$2:$O$1000)=D$13))} -> 1 | E20: {=SUMPRODUCT((TRIM('Master 2026'!$B$2:$B$1000)="India")*(TRIM('Master 2026'!$S$2:$S$1000)="Joined")*(TRIM('Master 2026'!$D$2:$D$1000)=$A20)*(TRIM('Master 2026'!$O$2:$O$1000)=E$13))} -> 0 | F20: =SUM(B20:E20) -> 2
A21: PS | B21: {=SUMPRODUCT((TRIM('Master 2026'!$B$2:$B$1000)="India")*(TRIM('Master 2026'!$S$2:$S$1000)="Joined")*(TRIM('Master 2026'!$D$2:$D$1000)=$A21)*(TRIM('Master 2026'!$O$2:$O$1000)=B$13))} -> 3 | C21: {=SUMPRODUCT((TRIM('Master 2026'!$B$2:$B$1000)="India")*(TRIM('Master 2026'!$S$2:$S$1000)="Joined")*(TRIM('Master 2026'!$D$2:$D$1000)=$A21)*(TRIM('Master 2026'!$O$2:$O$1000)=C$13))} -> 3 | D21: {=SUMPRODUCT((TRIM('Master 2026'!$B$2:$B$1000)="India")*(TRIM('Master 2026'!$S$2:$S$1000)="Joined")*(TRIM('Master 2026'!$D$2:$D$1000)=$A21)*(TRIM('Master 2026'!$O$2:$O$1000)=D$13))} -> 3 | E21: {=SUMPRODUCT((TRIM('Master 2026'!$B$2:$B$1000)="India")*(TRIM('Master 2026'!$S$2:$S$1000)="Joined")*(TRIM('Master 2026'!$D$2:$D$1000)=$A21)*(TRIM('Master 2026'!$O$2:$O$1000)=E$13))} -> 0 | F21: =SUM(B21:E21) -> 9
A22: Payments | B22: {=SUMPRODUCT((TRIM('Master 2026'!$B$2:$B$1000)="India")*(TRIM('Master 2026'!$S$2:$S$1000)="Joined")*(TRIM('Master 2026'!$D$2:$D$1000)=$A22)*(TRIM('Master 2026'!$O$2:$O$1000)=B$13))} -> 6 | C22: {=SUMPRODUCT((TRIM('Master 2026'!$B$2:$B$1000)="India")*(TRIM('Master 2026'!$S$2:$S$1000)="Joined")*(TRIM('Master 2026'!$D$2:$D$1000)=$A22)*(TRIM('Master 2026'!$O$2:$O$1000)=C$13))} -> 4 | D22: {=SUMPRODUCT((TRIM('Master 2026'!$B$2:$B$1000)="India")*(TRIM('Master 2026'!$S$2:$S$1000)="Joined")*(TRIM('Master 2026'!$D$2:$D$1000)=$A22)*(TRIM('Master 2026'!$O$2:$O$1000)=D$13))} -> 3 | E22: {=SUMPRODUCT((TRIM('Master 2026'!$B$2:$B$1000)="India")*(TRIM('Master 2026'!$S$2:$S$1000)="Joined")*(TRIM('Master 2026'!$D$2:$D$1000)=$A22)*(TRIM('Master 2026'!$O$2:$O$1000)=E$13))} -> 1 | F22: =SUM(B22:E22) -> 14
A23: Support | B23: {=SUMPRODUCT((TRIM('Master 2026'!$B$2:$B$1000)="India")*(TRIM('Master 2026'!$S$2:$S$1000)="Joined")*(TRIM('Master 2026'!$D$2:$D$1000)=$A23)*(TRIM('Master 2026'!$O$2:$O$1000)=B$13))} -> 2 | C23: {=SUMPRODUCT((TRIM('Master 2026'!$B$2:$B$1000)="India")*(TRIM('Master 2026'!$S$2:$S$1000)="Joined")*(TRIM('Master 2026'!$D$2:$D$1000)=$A23)*(TRIM('Master 2026'!$O$2:$O$1000)=C$13))} -> 2 | D23: {=SUMPRODUCT((TRIM('Master 2026'!$B$2:$B$1000)="India")*(TRIM('Master 2026'!$S$2:$S$1000)="Joined")*(TRIM('Master 2026'!$D$2:$D$1000)=$A23)*(TRIM('Master 2026'!$O$2:$O$1000)=D$13))} -> 2 | E23: {=SUMPRODUCT((TRIM('Master 2026'!$B$2:$B$1000)="India")*(TRIM('Master 2026'!$S$2:$S$1000)="Joined")*(TRIM('Master 2026'!$D$2:$D$1000)=$A23)*(TRIM('Master 2026'!$O$2:$O$1000)=E$13))} -> 0 | F23: =SUM(B23:E23) -> 6
A24: Technology | B24: {=SUMPRODUCT((TRIM('Master 2026'!$B$2:$B$1000)="India")*(TRIM('Master 2026'!$S$2:$S$1000)="Joined")*(TRIM('Master 2026'!$D$2:$D$1000)=$A24)*(TRIM('Master 2026'!$O$2:$O$1000)=B$13))} -> 0 | C24: {=SUMPRODUCT((TRIM('Master 2026'!$B$2:$B$1000)="India")*(TRIM('Master 2026'!$S$2:$S$1000)="Joined")*(TRIM('Master 2026'!$D$2:$D$1000)=$A24)*(TRIM('Master 2026'!$O$2:$O$1000)=C$13))} -> 0 | D24: {=SUMPRODUCT((TRIM('Master 2026'!$B$2:$B$1000)="India")*(TRIM('Master 2026'!$S$2:$S$1000)="Joined")*(TRIM('Master 2026'!$D$2:$D$1000)=$A24)*(TRIM('Master 2026'!$O$2:$O$1000)=D$13))} -> 1 | E24: {=SUMPRODUCT((TRIM('Master 2026'!$B$2:$B$1000)="India")*(TRIM('Master 2026'!$S$2:$S$1000)="Joined")*(TRIM('Master 2026'!$D$2:$D$1000)=$A24)*(TRIM('Master 2026'!$O$2:$O$1000)=E$13))} -> 0 | F24: =SUM(B24:E24) -> 1
A25: Trade | B25: {=SUMPRODUCT((TRIM('Master 2026'!$B$2:$B$1000)="India")*(TRIM('Master 2026'!$S$2:$S$1000)="Joined")*(TRIM('Master 2026'!$D$2:$D$1000)=$A25)*(TRIM('Master 2026'!$O$2:$O$1000)=B$13))} -> 1 | C25: {=SUMPRODUCT((TRIM('Master 2026'!$B$2:$B$1000)="India")*(TRIM('Master 2026'!$S$2:$S$1000)="Joined")*(TRIM('Master 2026'!$D$2:$D$1000)=$A25)*(TRIM('Master 2026'!$O$2:$O$1000)=C$13))} -> 3 | D25: {=SUMPRODUCT((TRIM('Master 2026'!$B$2:$B$1000)="India")*(TRIM('Master 2026'!$S$2:$S$1000)="Joined")*(TRIM('Master 2026'!$D$2:$D$1000)=$A25)*(TRIM('Master 2026'!$O$2:$O$1000)=D$13))} -> 1 | E25: {=SUMPRODUCT((TRIM('Master 2026'!$B$2:$B$1000)="India")*(TRIM('Master 2026'!$S$2:$S$1000)="Joined")*(TRIM('Master 2026'!$D$2:$D$1000)=$A25)*(TRIM('Master 2026'!$O$2:$O$1000)=E$13))} -> 1 | F25: =SUM(B25:E25) -> 6
A26: Total | B26: =SUM(B14:B25) -> 23 | C26: =SUM(C14:C25) -> 20 | D26: =SUM(D14:D25) -> 16 | E26: =SUM(E14:E25) -> 3 | F26: =SUM(B26:E26) -> 62
A29: Joiners by Type of Hire & Quarter
A30: Type of Hire | B30: Q1 | C30: Q2 | D30: Q3 | E30: Q4 | F30: Total
A31: Full-time | B31: {=SUMPRODUCT((TRIM('Master 2026'!$B$2:$B$1000)="India")*(TRIM('Master 2026'!$S$2:$S$1000)="Joined")*(TRIM('Master 2026'!$I$2:$I$1000)=$A31)*(TRIM('Master 2026'!$O$2:$O$1000)=B$30))} -> 21 | C31: {=SUMPRODUCT((TRIM('Master 2026'!$B$2:$B$1000)="India")*(TRIM('Master 2026'!$S$2:$S$1000)="Joined")*(TRIM('Master 2026'!$I$2:$I$1000)=$A31)*(TRIM('Master 2026'!$O$2:$O$1000)=C$30))} -> 19 | D31: {=SUMPRODUCT((TRIM('Master 2026'!$B$2:$B$1000)="India")*(TRIM('Master 2026'!$S$2:$S$1000)="Joined")*(TRIM('Master 2026'!$I$2:$I$1000)=$A31)*(TRIM('Master 2026'!$O$2:$O$1000)=D$30))} -> 16 | E31: {=SUMPRODUCT((TRIM('Master 2026'!$B$2:$B$1000)="India")*(TRIM('Master 2026'!$S$2:$S$1000)="Joined")*(TRIM('Master 2026'!$I$2:$I$1000)=$A31)*(TRIM('Master 2026'!$O$2:$O$1000)=E$30))} -> 3 | F31: =SUM(B31:E31) -> 59
A32: Consultant | B32: {=SUMPRODUCT((TRIM('Master 2026'!$B$2:$B$1000)="India")*(TRIM('Master 2026'!$S$2:$S$1000)="Joined")*(TRIM('Master 2026'!$I$2:$I$1000)=$A32)*(TRIM('Master 2026'!$O$2:$O$1000)=B$30))} -> 2 | C32: {=SUMPRODUCT((TRIM('Master 2026'!$B$2:$B$1000)="India")*(TRIM('Master 2026'!$S$2:$S$1000)="Joined")*(TRIM('Master 2026'!$I$2:$I$1000)=$A32)*(TRIM('Master 2026'!$O$2:$O$1000)=C$30))} -> 1 | D32: {=SUMPRODUCT((TRIM('Master 2026'!$B$2:$B$1000)="India")*(TRIM('Master 2026'!$S$2:$S$1000)="Joined")*(TRIM('Master 2026'!$I$2:$I$1000)=$A32)*(TRIM('Master 2026'!$O$2:$O$1000)=D$30))} -> 0 | E32: {=SUMPRODUCT((TRIM('Master 2026'!$B$2:$B$1000)="India")*(TRIM('Master 2026'!$S$2:$S$1000)="Joined")*(TRIM('Master 2026'!$I$2:$I$1000)=$A32)*(TRIM('Master 2026'!$O$2:$O$1000)=E$30))} -> 0 | F32: =SUM(B32:E32) -> 3
A33: Total | B33: =SUM(B31:B32) -> 23 | C33: =SUM(C31:C32) -> 20 | D33: =SUM(D31:D32) -> 16 | E33: =SUM(E31:E32) -> 3 | F33: =SUM(B33:E33) -> 62
A36: Joiners by Department & Quarter
A37: Department | B37: Q1 | C37: Q2 | D37: Q3 | E37: Q4 | F37: Total
A38: BA | B38: {=SUMPRODUCT((TRIM(OFFSET('Master 2026'!$B$2,0,0,COUNTA('Master 2026'!$A:$A)-1,1))="India")*(TRIM(OFFSET('Master 2026'!$S$2,0,0,COUNTA('Master 2026'!$A:$A)-1,1))="Joined")*(TRIM(SUBSTITUTE(OFFSET('Master 2026'!$C$2,0,0,COUNTA('Master 2026'!$A:$A)-1,1),CHAR(160)," "))=$A38)*(TRIM(OFFSET('Master 2026'!$O$2,0,0,COUNTA('Master 2026'!$A:$A)-1,1))=B$37))} -> 0 | C38: {=SUMPRODUCT((TRIM(OFFSET('Master 2026'!$B$2,0,0,COUNTA('Master 2026'!$A:$A)-1,1))="India")*(TRIM(OFFSET('Master 2026'!$S$2,0,0,COUNTA('Master 2026'!$A:$A)-1,1))="Joined")*(TRIM(SUBSTITUTE(OFFSET('Master 2026'!$C$2,0,0,COUNTA('Master 2026'!$A:$A)-1,1),CHAR(160)," "))=$A38)*(TRIM(OFFSET('Master 2026'!$O$2,0,0,COUNTA('Master 2026'!$A:$A)-1,1))=C$37))} -> 2 | D38: {=SUMPRODUCT((TRIM(OFFSET('Master 2026'!$B$2,0,0,COUNTA('Master 2026'!$A:$A)-1,1))="India")*(TRIM(OFFSET('Master 2026'!$S$2,0,0,COUNTA('Master 2026'!$A:$A)-1,1))="Joined")*(TRIM(SUBSTITUTE(OFFSET('Master 2026'!$C$2,0,0,COUNTA('Master 2026'!$A:$A)-1,1),CHAR(160)," "))=$A38)*(TRIM(OFFSET('Master 2026'!$O$2,0,0,COUNTA('Master 2026'!$A:$A)-1,1))=D$37))} -> 1 | E38: {=SUMPRODUCT((TRIM(OFFSET('Master 2026'!$B$2,0,0,COUNTA('Master 2026'!$A:$A)-1,1))="India")*(TRIM(OFFSET('Master 2026'!$S$2,0,0,COUNTA('Master 2026'!$A:$A)-1,1))="Joined")*(TRIM(SUBSTITUTE(OFFSET('Master 2026'!$C$2,0,0,COUNTA('Master 2026'!$A:$A)-1,1),CHAR(160)," "))=$A38)*(TRIM(OFFSET('Master 2026'!$O$2,0,0,COUNTA('Master 2026'!$A:$A)-1,1))=E$37))} -> 1 | F38: =SUM(B38:E38) -> 4
A39: Delivery | B39: {=SUMPRODUCT((TRIM(OFFSET('Master 2026'!$B$2,0,0,COUNTA('Master 2026'!$A:$A)-1,1))="India")*(TRIM(OFFSET('Master 2026'!$S$2,0,0,COUNTA('Master 2026'!$A:$A)-1,1))="Joined")*(TRIM(SUBSTITUTE(OFFSET('Master 2026'!$C$2,0,0,COUNTA('Master 2026'!$A:$A)-1,1),CHAR(160)," "))=$A39)*(TRIM(OFFSET('Master 2026'!$O$2,0,0,COUNTA('Master 2026'!$A:$A)-1,1))=B$37))} -> 0 | C39: {=SUMPRODUCT((TRIM(OFFSET('Master 2026'!$B$2,0,0,COUNTA('Master 2026'!$A:$A)-1,1))="India")*(TRIM(OFFSET('Master 2026'!$S$2,0,0,COUNTA('Master 2026'!$A:$A)-1,1))="Joined")*(TRIM(SUBSTITUTE(OFFSET('Master 2026'!$C$2,0,0,COUNTA('Master 2026'!$A:$A)-1,1),CHAR(160)," "))=$A39)*(TRIM(OFFSET('Master 2026'!$O$2,0,0,COUNTA('Master 2026'!$A:$A)-1,1))=C$37))} -> 1 | D39: {=SUMPRODUCT((TRIM(OFFSET('Master 2026'!$B$2,0,0,COUNTA('Master 2026'!$A:$A)-1,1))="India")*(TRIM(OFFSET('Master 2026'!$S$2,0,0,COUNTA('Master 2026'!$A:$A)-1,1))="Joined")*(TRIM(SUBSTITUTE(OFFSET('Master 2026'!$C$2,0,0,COUNTA('Master 2026'!$A:$A)-1,1),CHAR(160)," "))=$A39)*(TRIM(OFFSET('Master 2026'!$O$2,0,0,COUNTA('Master 2026'!$A:$A)-1,1))=D$37))} -> 1 | E39: {=SUMPRODUCT((TRIM(OFFSET('Master 2026'!$B$2,0,0,COUNTA('Master 2026'!$A:$A)-1,1))="India")*(TRIM(OFFSET('Master 2026'!$S$2,0,0,COUNTA('Master 2026'!$A:$A)-1,1))="Joined")*(TRIM(SUBSTITUTE(OFFSET('Master 2026'!$C$2,0,0,COUNTA('Master 2026'!$A:$A)-1,1),CHAR(160)," "))=$A39)*(TRIM(OFFSET('Master 2026'!$O$2,0,0,COUNTA('Master 2026'!$A:$A)-1,1))=E$37))} -> 0 | F39: =SUM(B39:E39) -> 2
A40: DevOps | B40: {=SUMPRODUCT((TRIM(OFFSET('Master 2026'!$B$2,0,0,COUNTA('Master 2026'!$A:$A)-1,1))="India")*(TRIM(OFFSET('Master 2026'!$S$2,0,0,COUNTA('Master 2026'!$A:$A)-1,1))="Joined")*(TRIM(SUBSTITUTE(OFFSET('Master 2026'!$C$2,0,0,COUNTA('Master 2026'!$A:$A)-1,1),CHAR(160)," "))=$A40)*(TRIM(OFFSET('Master 2026'!$O$2,0,0,COUNTA('Master 2026'!$A:$A)-1,1))=B$37))} -> 1 | C40: {=SUMPRODUCT((TRIM(OFFSET('Master 2026'!$B$2,0,0,COUNTA('Master 2026'!$A:$A)-1,1))="India")*(TRIM(OFFSET('Master 2026'!$S$2,0,0,COUNTA('Master 2026'!$A:$A)-1,1))="Joined")*(TRIM(SUBSTITUTE(OFFSET('Master 2026'!$C$2,0,0,COUNTA('Master 2026'!$A:$A)-1,1),CHAR(160)," "))=$A40)*(TRIM(OFFSET('Master 2026'!$O$2,0,0,COUNTA('Master 2026'!$A:$A)-1,1))=C$37))} -> 3 | D40: {=SUMPRODUCT((TRIM(OFFSET('Master 2026'!$B$2,0,0,COUNTA('Master 2026'!$A:$A)-1,1))="India")*(TRIM(OFFSET('Master 2026'!$S$2,0,0,COUNTA('Master 2026'!$A:$A)-1,1))="Joined")*(TRIM(SUBSTITUTE(OFFSET('Master 2026'!$C$2,0,0,COUNTA('Master 2026'!$A:$A)-1,1),CHAR(160)," "))=$A40)*(TRIM(OFFSET('Master 2026'!$O$2,0,0,COUNTA('Master 2026'!$A:$A)-1,1))=D$37))} -> 0 | E40: {=SUMPRODUCT((TRIM(OFFSET('Master 2026'!$B$2,0,0,COUNTA('Master 2026'!$A:$A)-1,1))="India")*(TRIM(OFFSET('Master 2026'!$S$2,0,0,COUNTA('Master 2026'!$A:$A)-1,1))="Joined")*(TRIM(SUBSTITUTE(OFFSET('Master 2026'!$C$2,0,0,COUNTA('Master 2026'!$A:$A)-1,1),CHAR(160)," "))=$A40)*(TRIM(OFFSET('Master 2026'!$O$2,0,0,COUNTA('Master 2026'!$A:$A)-1,1))=E$37))} -> 0 | F40: =SUM(B40:E40) -> 4
A41: Engineering | B41: {=SUMPRODUCT((TRIM(OFFSET('Master 2026'!$B$2,0,0,COUNTA('Master 2026'!$A:$A)-1,1))="India")*(TRIM(OFFSET('Master 2026'!$S$2,0,0,COUNTA('Master 2026'!$A:$A)-1,1))="Joined")*(TRIM(SUBSTITUTE(OFFSET('Master 2026'!$C$2,0,0,COUNTA('Master 2026'!$A:$A)-1,1),CHAR(160)," "))=$A41)*(TRIM(OFFSET('Master 2026'!$O$2,0,0,COUNTA('Master 2026'!$A:$A)-1,1))=B$37))} -> 7 | C41: {=SUMPRODUCT((TRIM(OFFSET('Master 2026'!$B$2,0,0,COUNTA('Master 2026'!$A:$A)-1,1))="India")*(TRIM(OFFSET('Master 2026'!$S$2,0,0,COUNTA('Master 2026'!$A:$A)-1,1))="Joined")*(TRIM(SUBSTITUTE(OFFSET('Master 2026'!$C$2,0,0,COUNTA('Master 2026'!$A:$A)-1,1),CHAR(160)," "))=$A41)*(TRIM(OFFSET('Master 2026'!$O$2,0,0,COUNTA('Master 2026'!$A:$A)-1,1))=C$37))} -> 7 | D41: {=SUMPRODUCT((TRIM(OFFSET('Master 2026'!$B$2,0,0,COUNTA('Master 2026'!$A:$A)-1,1))="India")*(TRIM(OFFSET('Master 2026'!$S$2,0,0,COUNTA('Master 2026'!$A:$A)-1,1))="Joined")*(TRIM(SUBSTITUTE(OFFSET('Master 2026'!$C$2,0,0,COUNTA('Master 2026'!$A:$A)-1,1),CHAR(160)," "))=$A41)*(TRIM(OFFSET('Master 2026'!$O$2,0,0,COUNTA('Master 2026'!$A:$A)-1,1))=D$37))} -> 4 | E41: {=SUMPRODUCT((TRIM(OFFSET('Master 2026'!$B$2,0,0,COUNTA('Master 2026'!$A:$A)-1,1))="India")*(TRIM(OFFSET('Master 2026'!$S$2,0,0,COUNTA('Master 2026'!$A:$A)-1,1))="Joined")*(TRIM(SUBSTITUTE(OFFSET('Master 2026'!$C$2,0,0,COUNTA('Master 2026'!$A:$A)-1,1),CHAR(160)," "))=$A41)*(TRIM(OFFSET('Master 2026'!$O$2,0,0,COUNTA('Master 2026'!$A:$A)-1,1))=E$37))} -> 1 | F41: =SUM(B41:E41) -> 19
A42: Finance | B42: {=SUMPRODUCT((TRIM(OFFSET('Master 2026'!$B$2,0,0,COUNTA('Master 2026'!$A:$A)-1,1))="India")*(TRIM(OFFSET('Master 2026'!$S$2,0,0,COUNTA('Master 2026'!$A:$A)-1,1))="Joined")*(TRIM(SUBSTITUTE(OFFSET('Master 2026'!$C$2,0,0,COUNTA('Master 2026'!$A:$A)-1,1),CHAR(160)," "))=$A42)*(TRIM(OFFSET('Master 2026'!$O$2,0,0,COUNTA('Master 2026'!$A:$A)-1,1))=B$37))} -> 0 | C42: {=SUMPRODUCT((TRIM(OFFSET('Master 2026'!$B$2,0,0,COUNTA('Master 2026'!$A:$A)-1,1))="India")*(TRIM(OFFSET('Master 2026'!$S$2,0,0,COUNTA('Master 2026'!$A:$A)-1,1))="Joined")*(TRIM(SUBSTITUTE(OFFSET('Master 2026'!$C$2,0,0,COUNTA('Master 2026'!$A:$A)-1,1),CHAR(160)," "))=$A42)*(TRIM(OFFSET('Master 2026'!$O$2,0,0,COUNTA('Master 2026'!$A:$A)-1,1))=C$37))} -> 0 | D42: {=SUMPRODUCT((TRIM(OFFSET('Master 2026'!$B$2,0,0,COUNTA('Master 2026'!$A:$A)-1,1))="India")*(TRIM(OFFSET('Master 2026'!$S$2,0,0,COUNTA('Master 2026'!$A:$A)-1,1))="Joined")*(TRIM(SUBSTITUTE(OFFSET('Master 2026'!$C$2,0,0,COUNTA('Master 2026'!$A:$A)-1,1),CHAR(160)," "))=$A42)*(TRIM(OFFSET('Master 2026'!$O$2,0,0,COUNTA('Master 2026'!$A:$A)-1,1))=D$37))} -> 1 | E42: {=SUMPRODUCT((TRIM(OFFSET('Master 2026'!$B$2,0,0,COUNTA('Master 2026'!$A:$A)-1,1))="India")*(TRIM(OFFSET('Master 2026'!$S$2,0,0,COUNTA('Master 2026'!$A:$A)-1,1))="Joined")*(TRIM(SUBSTITUTE(OFFSET('Master 2026'!$C$2,0,0,COUNTA('Master 2026'!$A:$A)-1,1),CHAR(160)," "))=$A42)*(TRIM(OFFSET('Master 2026'!$O$2,0,0,COUNTA('Master 2026'!$A:$A)-1,1))=E$37))} -> 1 | F42: =SUM(B42:E42) -> 2
A43: HR | B43: {=SUMPRODUCT((TRIM(OFFSET('Master 2026'!$B$2,0,0,COUNTA('Master 2026'!$A:$A)-1,1))="India")*(TRIM(OFFSET('Master 2026'!$S$2,0,0,COUNTA('Master 2026'!$A:$A)-1,1))="Joined")*(TRIM(SUBSTITUTE(OFFSET('Master 2026'!$C$2,0,0,COUNTA('Master 2026'!$A:$A)-1,1),CHAR(160)," "))=$A43)*(TRIM(OFFSET('Master 2026'!$O$2,0,0,COUNTA('Master 2026'!$A:$A)-1,1))=B$37))} -> 2 | C43: {=SUMPRODUCT((TRIM(OFFSET('Master 2026'!$B$2,0,0,COUNTA('Master 2026'!$A:$A)-1,1))="India")*(TRIM(OFFSET('Master 2026'!$S$2,0,0,COUNTA('Master 2026'!$A:$A)-1,1))="Joined")*(TRIM(SUBSTITUTE(OFFSET('Master 2026'!$C$2,0,0,COUNTA('Master 2026'!$A:$A)-1,1),CHAR(160)," "))=$A43)*(TRIM(OFFSET('Master 2026'!$O$2,0,0,COUNTA('Master 2026'!$A:$A)-1,1))=C$37))} -> 0 | D43: {=SUMPRODUCT((TRIM(OFFSET('Master 2026'!$B$2,0,0,COUNTA('Master 2026'!$A:$A)-1,1))="India")*(TRIM(OFFSET('Master 2026'!$S$2,0,0,COUNTA('Master 2026'!$A:$A)-1,1))="Joined")*(TRIM(SUBSTITUTE(OFFSET('Master 2026'!$C$2,0,0,COUNTA('Master 2026'!$A:$A)-1,1),CHAR(160)," "))=$A43)*(TRIM(OFFSET('Master 2026'!$O$2,0,0,COUNTA('Master 2026'!$A:$A)-1,1))=D$37))} -> 1 | E43: {=SUMPRODUCT((TRIM(OFFSET('Master 2026'!$B$2,0,0,COUNTA('Master 2026'!$A:$A)-1,1))="India")*(TRIM(OFFSET('Master 2026'!$S$2,0,0,COUNTA('Master 2026'!$A:$A)-1,1))="Joined")*(TRIM(SUBSTITUTE(OFFSET('Master 2026'!$C$2,0,0,COUNTA('Master 2026'!$A:$A)-1,1),CHAR(160)," "))=$A43)*(TRIM(OFFSET('Master 2026'!$O$2,0,0,COUNTA('Master 2026'!$A:$A)-1,1))=E$37))} -> 0 | F43: =SUM(B43:E43) -> 3
A44: Infosec | B44: {=SUMPRODUCT((TRIM(OFFSET('Master 2026'!$B$2,0,0,COUNTA('Master 2026'!$A:$A)-1,1))="India")*(TRIM(OFFSET('Master 2026'!$S$2,0,0,COUNTA('Master 2026'!$A:$A)-1,1))="Joined")*(TRIM(SUBSTITUTE(OFFSET('Master 2026'!$C$2,0,0,COUNTA('Master 2026'!$A:$A)-1,1),CHAR(160)," "))=$A44)*(TRIM(OFFSET('Master 2026'!$O$2,0,0,COUNTA('Master 2026'!$A:$A)-1,1))=B$37))} -> 1 | C44: {=SUMPRODUCT((TRIM(OFFSET('Master 2026'!$B$2,0,0,COUNTA('Master 2026'!$A:$A)-1,1))="India")*(TRIM(OFFSET('Master 2026'!$S$2,0,0,COUNTA('Master 2026'!$A:$A)-1,1))="Joined")*(TRIM(SUBSTITUTE(OFFSET('Master 2026'!$C$2,0,0,COUNTA('Master 2026'!$A:$A)-1,1),CHAR(160)," "))=$A44)*(TRIM(OFFSET('Master 2026'!$O$2,0,0,COUNTA('Master 2026'!$A:$A)-1,1))=C$37))} -> 0 | D44: {=SUMPRODUCT((TRIM(OFFSET('Master 2026'!$B$2,0,0,COUNTA('Master 2026'!$A:$A)-1,1))="India")*(TRIM(OFFSET('Master 2026'!$S$2,0,0,COUNTA('Master 2026'!$A:$A)-1,1))="Joined")*(TRIM(SUBSTITUTE(OFFSET('Master 2026'!$C$2,0,0,COUNTA('Master 2026'!$A:$A)-1,1),CHAR(160)," "))=$A44)*(TRIM(OFFSET('Master 2026'!$O$2,0,0,COUNTA('Master 2026'!$A:$A)-1,1))=D$37))} -> 1 | E44: {=SUMPRODUCT((TRIM(OFFSET('Master 2026'!$B$2,0,0,COUNTA('Master 2026'!$A:$A)-1,1))="India")*(TRIM(OFFSET('Master 2026'!$S$2,0,0,COUNTA('Master 2026'!$A:$A)-1,1))="Joined")*(TRIM(SUBSTITUTE(OFFSET('Master 2026'!$C$2,0,0,COUNTA('Master 2026'!$A:$A)-1,1),CHAR(160)," "))=$A44)*(TRIM(OFFSET('Master 2026'!$O$2,0,0,COUNTA('Master 2026'!$A:$A)-1,1))=E$37))} -> 0 | F44: =SUM(B44:E44) -> 2
A45: Legal | B45: {=SUMPRODUCT((TRIM(OFFSET('Master 2026'!$B$2,0,0,COUNTA('Master 2026'!$A:$A)-1,1))="India")*(TRIM(OFFSET('Master 2026'!$S$2,0,0,COUNTA('Master 2026'!$A:$A)-1,1))="Joined")*(TRIM(SUBSTITUTE(OFFSET('Master 2026'!$C$2,0,0,COUNTA('Master 2026'!$A:$A)-1,1),CHAR(160)," "))=$A45)*(TRIM(OFFSET('Master 2026'!$O$2,0,0,COUNTA('Master 2026'!$A:$A)-1,1))=B$37))} -> 1 | C45: {=SUMPRODUCT((TRIM(OFFSET('Master 2026'!$B$2,0,0,COUNTA('Master 2026'!$A:$A)-1,1))="India")*(TRIM(OFFSET('Master 2026'!$S$2,0,0,COUNTA('Master 2026'!$A:$A)-1,1))="Joined")*(TRIM(SUBSTITUTE(OFFSET('Master 2026'!$C$2,0,0,COUNTA('Master 2026'!$A:$A)-1,1),CHAR(160)," "))=$A45)*(TRIM(OFFSET('Master 2026'!$O$2,0,0,COUNTA('Master 2026'!$A:$A)-1,1))=C$37))} -> 0 | D45: {=SUMPRODUCT((TRIM(OFFSET('Master 2026'!$B$2,0,0,COUNTA('Master 2026'!$A:$A)-1,1))="India")*(TRIM(OFFSET('Master 2026'!$S$2,0,0,COUNTA('Master 2026'!$A:$A)-1,1))="Joined")*(TRIM(SUBSTITUTE(OFFSET('Master 2026'!$C$2,0,0,COUNTA('Master 2026'!$A:$A)-1,1),CHAR(160)," "))=$A45)*(TRIM(OFFSET('Master 2026'!$O$2,0,0,COUNTA('Master 2026'!$A:$A)-1,1))=D$37))} -> 0 | E45: {=SUMPRODUCT((TRIM(OFFSET('Master 2026'!$B$2,0,0,COUNTA('Master 2026'!$A:$A)-1,1))="India")*(TRIM(OFFSET('Master 2026'!$S$2,0,0,COUNTA('Master 2026'!$A:$A)-1,1))="Joined")*(TRIM(SUBSTITUTE(OFFSET('Master 2026'!$C$2,0,0,COUNTA('Master 2026'!$A:$A)-1,1),CHAR(160)," "))=$A45)*(TRIM(OFFSET('Master 2026'!$O$2,0,0,COUNTA('Master 2026'!$A:$A)-1,1))=E$37))} -> 0 | F45: =SUM(B45:E45) -> 1
A46: Prod Support | B46: {=SUMPRODUCT((TRIM(OFFSET('Master 2026'!$B$2,0,0,COUNTA('Master 2026'!$A:$A)-1,1))="India")*(TRIM(OFFSET('Master 2026'!$S$2,0,0,COUNTA('Master 2026'!$A:$A)-1,1))="Joined")*(TRIM(SUBSTITUTE(OFFSET('Master 2026'!$C$2,0,0,COUNTA('Master 2026'!$A:$A)-1,1),CHAR(160)," "))=$A46)*(TRIM(OFFSET('Master 2026'!$O$2,0,0,COUNTA('Master 2026'!$A:$A)-1,1))=B$37))} -> 1 | C46: {=SUMPRODUCT((TRIM(OFFSET('Master 2026'!$B$2,0,0,COUNTA('Master 2026'!$A:$A)-1,1))="India")*(TRIM(OFFSET('Master 2026'!$S$2,0,0,COUNTA('Master 2026'!$A:$A)-1,1))="Joined")*(TRIM(SUBSTITUTE(OFFSET('Master 2026'!$C$2,0,0,COUNTA('Master 2026'!$A:$A)-1,1),CHAR(160)," "))=$A46)*(TRIM(OFFSET('Master 2026'!$O$2,0,0,COUNTA('Master 2026'!$A:$A)-1,1))=C$37))} -> 2 | D46: {=SUMPRODUCT((TRIM(OFFSET('Master 2026'!$B$2,0,0,COUNTA('Master 2026'!$A:$A)-1,1))="India")*(TRIM(OFFSET('Master 2026'!$S$2,0,0,COUNTA('Master 2026'!$A:$A)-1,1))="Joined")*(TRIM(SUBSTITUTE(OFFSET('Master 2026'!$C$2,0,0,COUNTA('Master 2026'!$A:$A)-1,1),CHAR(160)," "))=$A46)*(TRIM(OFFSET('Master 2026'!$O$2,0,0,COUNTA('Master 2026'!$A:$A)-1,1))=D$37))} -> 0 | E46: {=SUMPRODUCT((TRIM(OFFSET('Master 2026'!$B$2,0,0,COUNTA('Master 2026'!$A:$A)-1,1))="India")*(TRIM(OFFSET('Master 2026'!$S$2,0,0,COUNTA('Master 2026'!$A:$A)-1,1))="Joined")*(TRIM(SUBSTITUTE(OFFSET('Master 2026'!$C$2,0,0,COUNTA('Master 2026'!$A:$A)-1,1),CHAR(160)," "))=$A46)*(TRIM(OFFSET('Master 2026'!$O$2,0,0,COUNTA('Master 2026'!$A:$A)-1,1))=E$37))} -> 0 | F46: =SUM(B46:E46) -> 3
A47: Product | B47: {=SUMPRODUCT((TRIM(OFFSET('Master 2026'!$B$2,0,0,COUNTA('Master 2026'!$A:$A)-1,1))="India")*(TRIM(OFFSET('Master 2026'!$S$2,0,0,COUNTA('Master 2026'!$A:$A)-1,1))="Joined")*(TRIM(SUBSTITUTE(OFFSET('Master 2026'!$C$2,0,0,COUNTA('Master 2026'!$A:$A)-1,1),CHAR(160)," "))=$A47)*(TRIM(OFFSET('Master 2026'!$O$2,0,0,COUNTA('Master 2026'!$A:$A)-1,1))=B$37))} -> 3 | C47: {=SUMPRODUCT((TRIM(OFFSET('Master 2026'!$B$2,0,0,COUNTA('Master 2026'!$A:$A)-1,1))="India")*(TRIM(OFFSET('Master 2026'!$S$2,0,0,COUNTA('Master 2026'!$A:$A)-1,1))="Joined")*(TRIM(SUBSTITUTE(OFFSET('Master 2026'!$C$2,0,0,COUNTA('Master 2026'!$A:$A)-1,1),CHAR(160)," "))=$A47)*(TRIM(OFFSET('Master 2026'!$O$2,0,0,COUNTA('Master 2026'!$A:$A)-1,1))=C$37))} -> 1 | D47: {=SUMPRODUCT((TRIM(OFFSET('Master 2026'!$B$2,0,0,COUNTA('Master 2026'!$A:$A)-1,1))="India")*(TRIM(OFFSET('Master 2026'!$S$2,0,0,COUNTA('Master 2026'!$A:$A)-1,1))="Joined")*(TRIM(SUBSTITUTE(OFFSET('Master 2026'!$C$2,0,0,COUNTA('Master 2026'!$A:$A)-1,1),CHAR(160)," "))=$A47)*(TRIM(OFFSET('Master 2026'!$O$2,0,0,COUNTA('Master 2026'!$A:$A)-1,1))=D$37))} -> 0 | E47: {=SUMPRODUCT((TRIM(OFFSET('Master 2026'!$B$2,0,0,COUNTA('Master 2026'!$A:$A)-1,1))="India")*(TRIM(OFFSET('Master 2026'!$S$2,0,0,COUNTA('Master 2026'!$A:$A)-1,1))="Joined")*(TRIM(SUBSTITUTE(OFFSET('Master 2026'!$C$2,0,0,COUNTA('Master 2026'!$A:$A)-1,1),CHAR(160)," "))=$A47)*(TRIM(OFFSET('Master 2026'!$O$2,0,0,COUNTA('Master 2026'!$A:$A)-1,1))=E$37))} -> 0 | F47: =SUM(B47:E47) -> 4
A48: Program | B48: {=SUMPRODUCT((TRIM(OFFSET('Master 2026'!$B$2,0,0,COUNTA('Master 2026'!$A:$A)-1,1))="India")*(TRIM(OFFSET('Master 2026'!$S$2,0,0,COUNTA('Master 2026'!$A:$A)-1,1))="Joined")*(TRIM(SUBSTITUTE(OFFSET('Master 2026'!$C$2,0,0,COUNTA('Master 2026'!$A:$A)-1,1),CHAR(160)," "))=$A48)*(TRIM(OFFSET('Master 2026'!$O$2,0,0,COUNTA('Master 2026'!$A:$A)-1,1))=B$37))} -> 1 | C48: {=SUMPRODUCT((TRIM(OFFSET('Master 2026'!$B$2,0,0,COUNTA('Master 2026'!$A:$A)-1,1))="India")*(TRIM(OFFSET('Master 2026'!$S$2,0,0,COUNTA('Master 2026'!$A:$A)-1,1))="Joined")*(TRIM(SUBSTITUTE(OFFSET('Master 2026'!$C$2,0,0,COUNTA('Master 2026'!$A:$A)-1,1),CHAR(160)," "))=$A48)*(TRIM(OFFSET('Master 2026'!$O$2,0,0,COUNTA('Master 2026'!$A:$A)-1,1))=C$37))} -> 0 | D48: {=SUMPRODUCT((TRIM(OFFSET('Master 2026'!$B$2,0,0,COUNTA('Master 2026'!$A:$A)-1,1))="India")*(TRIM(OFFSET('Master 2026'!$S$2,0,0,COUNTA('Master 2026'!$A:$A)-1,1))="Joined")*(TRIM(SUBSTITUTE(OFFSET('Master 2026'!$C$2,0,0,COUNTA('Master 2026'!$A:$A)-1,1),CHAR(160)," "))=$A48)*(TRIM(OFFSET('Master 2026'!$O$2,0,0,COUNTA('Master 2026'!$A:$A)-1,1))=D$37))} -> 1 | E48: {=SUMPRODUCT((TRIM(OFFSET('Master 2026'!$B$2,0,0,COUNTA('Master 2026'!$A:$A)-1,1))="India")*(TRIM(OFFSET('Master 2026'!$S$2,0,0,COUNTA('Master 2026'!$A:$A)-1,1))="Joined")*(TRIM(SUBSTITUTE(OFFSET('Master 2026'!$C$2,0,0,COUNTA('Master 2026'!$A:$A)-1,1),CHAR(160)," "))=$A48)*(TRIM(OFFSET('Master 2026'!$O$2,0,0,COUNTA('Master 2026'!$A:$A)-1,1))=E$37))} -> 0 | F48: =SUM(B48:E48) -> 2
A49: QA | B49: {=SUMPRODUCT((TRIM(OFFSET('Master 2026'!$B$2,0,0,COUNTA('Master 2026'!$A:$A)-1,1))="India")*(TRIM(OFFSET('Master 2026'!$S$2,0,0,COUNTA('Master 2026'!$A:$A)-1,1))="Joined")*(TRIM(SUBSTITUTE(OFFSET('Master 2026'!$C$2,0,0,COUNTA('Master 2026'!$A:$A)-1,1),CHAR(160)," "))=$A49)*(TRIM(OFFSET('Master 2026'!$O$2,0,0,COUNTA('Master 2026'!$A:$A)-1,1))=B$37))} -> 6 | C49: {=SUMPRODUCT((TRIM(OFFSET('Master 2026'!$B$2,0,0,COUNTA('Master 2026'!$A:$A)-1,1))="India")*(TRIM(OFFSET('Master 2026'!$S$2,0,0,COUNTA('Master 2026'!$A:$A)-1,1))="Joined")*(TRIM(SUBSTITUTE(OFFSET('Master 2026'!$C$2,0,0,COUNTA('Master 2026'!$A:$A)-1,1),CHAR(160)," "))=$A49)*(TRIM(OFFSET('Master 2026'!$O$2,0,0,COUNTA('Master 2026'!$A:$A)-1,1))=C$37))} -> 4 | D49: {=SUMPRODUCT((TRIM(OFFSET('Master 2026'!$B$2,0,0,COUNTA('Master 2026'!$A:$A)-1,1))="India")*(TRIM(OFFSET('Master 2026'!$S$2,0,0,COUNTA('Master 2026'!$A:$A)-1,1))="Joined")*(TRIM(SUBSTITUTE(OFFSET('Master 2026'!$C$2,0,0,COUNTA('Master 2026'!$A:$A)-1,1),CHAR(160)," "))=$A49)*(TRIM(OFFSET('Master 2026'!$O$2,0,0,COUNTA('Master 2026'!$A:$A)-1,1))=D$37))} -> 1 | E49: {=SUMPRODUCT((TRIM(OFFSET('Master 2026'!$B$2,0,0,COUNTA('Master 2026'!$A:$A)-1,1))="India")*(TRIM(OFFSET('Master 2026'!$S$2,0,0,COUNTA('Master 2026'!$A:$A)-1,1))="Joined")*(TRIM(SUBSTITUTE(OFFSET('Master 2026'!$C$2,0,0,COUNTA('Master 2026'!$A:$A)-1,1),CHAR(160)," "))=$A49)*(TRIM(OFFSET('Master 2026'!$O$2,0,0,COUNTA('Master 2026'!$A:$A)-1,1))=E$37))} -> 0 | F49: =SUM(B49:E49) -> 11
... A52: Marketing | B52: {=SUMPRODUCT((TRIM(OFFSET('Master 2026'!$B$2,0,0,COUNTA('Master 2026'!$A:$A)-1,1))="India")*(TRIM(OFFSET('Master 2026'!$S$2,0,0,COUNTA('Master 2026'!$A:$A)-1,1))="Joined")*(TRIM(SUBSTITUTE(OFFSET('Master 2026'!$C$2,0,0,COUNTA('Master 2026'!$A:$A)-1,1),CHAR(160)," "))=$A52)*(TRIM(OFFSET('Master 2026'!$O$2,0,0,COUNTA('Master 2026'!$A:$A)-1,1))=B$37))} -> 0 | C52: {=SUMPRODUCT((TRIM(OFFSET('Master 2026'!$B$2,0,0,COUNTA('Master 2026'!$A:$A)-1,1))="India")*(TRIM(OFFSET('Master 2026'!$S$2,0,0,COUNTA('Master 2026'!$A:$A)-1,1))="Joined")*(TRIM(SUBSTITUTE(OFFSET('Master 2026'!$C$2,0,0,COUNTA('Master 2026'!$A:$A)-1,1),CHAR(160)," "))=$A52)*(TRIM(OFFSET('Master 2026'!$O$2,0,0,COUNTA('Master 2026'!$A:$A)-1,1))=C$37))} -> 0 | D52: {=SUMPRODUCT((TRIM(OFFSET('Master 2026'!$B$2,0,0,COUNTA('Master 2026'!$A:$A)-1,1))="India")*(TRIM(OFFSET('Master 2026'!$S$2,0,0,COUNTA('Master 2026'!$A:$A)-1,1))="Joined")*(TRIM(SUBSTITUTE(OFFSET('Master 2026'!$C$2,0,0,COUNTA('Master 2026'!$A:$A)-1,1),CHAR(160)," "))=$A52)*(TRIM(OFFSET('Master 2026'!$O$2,0,0,COUNTA('Master 2026'!$A:$A)-1,1))=D$37))} -> 2 | E52: {=SUMPRODUCT((TRIM(OFFSET('Master 2026'!$B$2,0,0,COUNTA('Master 2026'!$A:$A)-1,1))="India")*(TRIM(OFFSET('Master 2026'!$S$2,0,0,COUNTA('Master 2026'!$A:$A)-1,1))="Joined")*(TRIM(SUBSTITUTE(OFFSET('Master 2026'!$C$2,0,0,COUNTA('Master 2026'!$A:$A)-1,1),CHAR(160)," "))=$A52)*(TRIM(OFFSET('Master 2026'!$O$2,0,0,COUNTA('Master 2026'!$A:$A)-1,1))=E$37))} -> 0 | F52: =SUM(B52:E52) -> 2
A53: Total | B53: =SUM(B38:B52) -> 23 | C53: =SUM(C38:C52) -> 20 | D53: =SUM(D38:D52) -> 16 | E53: =SUM(E38:E52) -> 3 | F53: =SUM(B53:E53) -> 62
D73: F9 — recalculate all open workbooks
D74: Ctrl + Alt + F9 — full recalculation (rebuilds everything, useful if something looks stale)
